Workbook
Name _ANN10: 'COTIZACIÓN '!#REF!
Name _ANN10: 'COTIZACION (Financ)'!#REF!
Name _ANN10: #REF!
Name _ANN20: 'COTIZACIÓN '!#REF!
Name _ANN20: 'COTIZACION (Financ)'!#REF!
Name _ANN20: #REF!
Name a: 'COTIZACIÓN '!#REF!
Name a: 'COTIZACION (Financ)'!#REF!
Name a: #REF!
Name aa: #REF!
Name activo: '[1]B$E'!$D$48
Name activoc: '[1]B$E'!$D$11
Name activof: '[1]B$E'!$D$30
Name Años_préstamo: '[2]Ptmo P'!$D$7
Name Años_préstamo: '[2]Ptmo P'!$D$7
Name Años_préstamo: #REF!
Name Años_préstamo: '[2]Ptmo P'!$D$7
Name Años_préstamo: #REF!
Name Años_préstamo: #REF!
Name Años_préstamo: #REF!
Name Area: [3]!Tabla1[area]
Name b: 'COTIZACIÓN '!#REF!
Name b: 'COTIZACION (Financ)'!#REF!
Name b: #REF!
Name Beginning_Balance: -FV(Interest_Rate/12,'COTIZACIÓN '!Payment_Number-1,-'COTIZACIÓN '!Monthly_Payment,Loan_Amount)
Name Beginning_Balance: -FV([0]!Interest_Rate/12,'COTIZACION (Financ)'!Payment_Number-1,-'COTIZACION (Financ)'!Monthly_Payment,[0]!Loan_Amount)
Name Beginning_Balance: -FV(Interest_Rate/12,Payment_Number-1,-Monthly_Payment,Loan_Amount)
Name Cap_Base: [4]Performance!$D$24
Name Cap_kW: [5]Variables!$B$25
Name Capital: '[2]Ptmo P'!$G$18:$G$497
Name Capital: '[2]Ptmo P'!$G$18:$G$497
Name Capital: #REF!
Name Capital: '[2]Ptmo P'!$G$18:$G$497
Name Capital: #REF!
Name Capital: #REF!
Name Capital: #REF!
Name capsocial: '[1]B$E'!$H$44
Name CF_OM_Bz: '[6]O&M'!#REF!
Name CF_OM_US: '[6]O&M'!#REF!
Name Clientes: '[1]B$E'!$B$14
Name Cum_Cash_Flow: [6]CF!#REF!
Name Datos: 'COTIZACIÓN '!#REF!
Name Datos: 'COTIZACION (Financ)'!#REF!
Name Datos: #REF!
Name Datos: #REF!
Name Datos: #REF!
Name Demanda_Máxima_kW: [5]Variables!$B$7
Name Día_de_pago: #N/A
Name Día_de_pago: #N/A
Name Día_de_pago: #N/A
Name Día_de_pago: #N/A
Name Día_de_pago: DATE(YEAR([0]!Inicio_prestamo),MONTH([0]!Inicio_prestamo)+Payment_Number,DAY([0]!Inicio_prestamo))
Name Día_de_pago: DATE(YEAR([0]!Inicio_prestamo),MONTH([0]!Inicio_prestamo)+Payment_Number,DAY([0]!Inicio_prestamo))
Name Día_de_pago: DATE(YEAR([0]!Inicio_prestamo),MONTH([0]!Inicio_prestamo)+Payment_Number,DAY([0]!Inicio_prestamo))
Name Día_de_pago: DATE(YEAR([0]!Inicio_prestamo),MONTH([0]!Inicio_prestamo)+Payment_Number,DAY([0]!Inicio_prestamo))
Name Día_de_pago: DATE(YEAR([0]!Inicio_prestamo),MONTH([0]!Inicio_prestamo)+Payment_Number,DAY([0]!Inicio_prestamo))
Name Día_de_pago: DATE(YEAR([0]!Inicio_prestamo),MONTH([0]!Inicio_prestamo)+Payment_Number,DAY([0]!Inicio_prestamo))
Name Día_de_pago: DATE(YEAR([0]!Inicio_prestamo),MONTH([0]!Inicio_prestamo)+Payment_Number,DAY([0]!Inicio_prestamo))
Name Día_de_pago: DATE(YEAR([0]!Inicio_prestamo),MONTH([0]!Inicio_prestamo)+Payment_Number,DAY([0]!Inicio_prestamo))
Name Día_de_pago: DATE(YEAR([0]!Inicio_prestamo),MONTH([0]!Inicio_prestamo)+Payment_Number,DAY([0]!Inicio_prestamo))

Sheet LEEME
B1: MATRIZ Y OFERTA
B2: Leer esto primero. Son cinco minutos y evitan los errores que mas caro salen.
B4: QUE ES ESTE ARCHIVO
B5: Es el machote oficial de matriz de costo y oferta. No se trabaja sobre el original: se copia una vez a la carpeta Matriz-Oferta de la cotizacion, y se llena esa copia.
B6: Tiene 34 pestanas: 14 de trabajo, 4 de guia (esta y las tres del final) y 16 ocultas. Las ocultas son estructura de reserva y hojas de analisis que hoy no se usan.
B8: LA REGLA DE ORO
B9: En cada pestana de producto se escriben CUATRO columnas. Todo lo demas son formulas que calculan solas.
B10: Si al escribir en una celda cambia un numero en otra, esa otra es formula: no la toques ni la pises.
B11: Nunca escribas un precio de venta a mano. El precio de venta SALE del costo, no al reves.
B13: EN QUE ORDEN SE LLENA
B14: 1. Datos del proyecto | C14: La ultima pestana antes de las guias. Cliente, tipo de cotizacion, regimen fiscal, porcentajes y financiamiento.
B15: 2. Equipos | C15: Las lineas de equipo que se van a vender. Es la pestana principal.
B16: 3. MATERIALES | C16: Materiales de instalacion, si el alcance los incluye.
B17: 4. MANO DE OBRA y Transporte | C17: Solo si la oferta incluye instalacion.
B18: 5. Financiamiento | C18: Solo si el proyecto lleva esa modalidad. Si no, se deja en blanco y no pasa nada.
B19: 6. COTIZACION | C19: No se escribe: se revisa. Es lo que ve el cliente.
B21: LAS UNICAS CUATRO COLUMNAS QUE SE ESCRIBEN
B22: Columna | C22: Que va ahi, y con que cuidado
B23: Description | C23: Marca + modelo + descripcion del catalogo. Se copia tal cual a la cotizacion, asi que tiene que entenderse del lado del cliente.
B24: IMPORTADO | C24: si / no, segun si Grupo Vision compra ese articulo fuera del pais. NO es donde se fabrica: una camara coreana comprada a un proveedor tico es 'no'. Una linea de flete va siempre como 'no': si va 'si', se le cobra transporte al transporte.
B25: Qty | C25: Cuantas unidades pide el proyecto. Si no la sabes, preguntala. No la estimes.
B26: Costo Unit | C26: Lo que Grupo Vision PAGA por una unidad, en dolares: la columna Precio de compra GV del catalogo (el precio dealer). Si la fila no tiene costo, se usa el precio de lista y se avisa, porque ahi el margen real queda mayor que el que muestra la matriz. NUNCA el MSRP como costo.
B28: LOS CUATRO ERRORES QUE MAS CARO SALEN
B29: 1. Poner el MSRP como costo | C29: La cotizacion sale cerca del DOBLE. El MSRP es donde suele terminar el precio al cliente, no de donde arranca el calculo. Medido: en 57.607 lineas de 1.119 cotizaciones reales, nadie lo hizo nunca.
B30: 2. Poner mal IMPORTADO | C30: Medido: sobre 10 unidades de 100 dolares, la diferencia entre 'si' y 'no' es de 387,24 dolares, un 26,5%. Excel no muestra ningun error.
B31: 3. Confundir los dos IVA | C31: El IVA de la columna es un COSTO: lo que el proveedor nos cobra a nosotros al comprar. El impuesto del cliente es la fila IMPUESTO de COTIZACION, y depende del regimen fiscal del cliente.
B32: 4. Cambiar el margen en Equipos | C32: El margen de OPEX GV es la formula =Equipos!N4. Si cambias el margen en Equipos, tambien se mueve el de OPEX GV, sin ningun aviso.
B33: LAS OTRAS TRES GUIAS, AL FINAL DEL LIBRO
B34: Guia de pestanas | C34: Que hace cada pestana de trabajo, que se escribe a mano y que sale solo.
B35: Guia de formulas | C35: Las formulas que deciden la plata, explicadas en palabras.

Sheet CCTV DISEÑO
B1: Description | C1: Qty | J1: Ancho de Banda
B2: Sistema CCTV Perímetro | E2: No. | F2: Modelo | G2: Tipo | H2: Resolución | I2: Cantidad | J2: Visualización | K2: Grabación | L2: LPR | M2: Reconocimiento Facial | N2: Conteo | O2: Total | P2: Analíticas
B3: Cámara fija IP para Perimetro Exterior Modelo: XNV-6080R | C3: 48 | E3: 1 | F3: XNV-6080R | G3: Domo Exterior | H3: 2MP | J3: 77.35 Mbps | K3: 168.76 Mbps | O3: 246.10 Mbps | P3: • Manipulación • Merodeo • Detección direccional, • Detección de desenfoque, • Detección de empañamiento, • Línea virtual, entrada y salida, (des)aparición, • Detección de audio, • Detección de rostros, • Detección de movimiento, • Seguimiento automático digital, • Clasificación de sonidos
B4: Cámara fija IP para Perimetro Interior Modelo: XND-6080RV | C4: 30 | E4: 2 | F4: XND-6080RV | G4: Domo Interior | H4: 2MP | J4: 204.25 Mbps | K4: 445.64 Mbps | O4: 649.90 Mbps | P4: • Manipulación, • Merodeo, • Detección direccional, • Detección de desenfoque, • Detección de empañamiento, • Línea virtual, entrada y salida, (des)aparición, • Detección de audio, • Detección de rostros, • Detección de movimiento, • Seguimiento automático digital, • Clasificación de sonidos
B5: Cámara fija IP para Estacionamientos Modelo: XNO-6080R | C5: 15 | E5: 3 | F5: XNO-6080R | G5: Bullet Exterior | H5: 2MP | J5: 22.12 Mbps | K5: 44.24 Mbps | O5: 66.36 Mbps | P5: • Manipulación, • Merodeo, • Detección direccional, • Detección de desenfoque, • Detección de empañamiento, • Línea virtual, entrada y salida, (des)aparición, • Detección de audio, • Detección de rostros, • Detección de movimiento, • Seguimiento automático digital, • Clasificación de sonidos
B6: Cámara fija IP para Reconocimiento Modelo: XNO-6080R | C6: 12 | E6: 4 | F6: PNM-9020V | G6: Panoramica Multi-sensor 180˚ | H6: 7.3MP | J6: 6.76 Mbps | K6: 51.61 Mbps | O6: 58.37 Mbps | P6: • Manipulación, • Línea virtual, entrada / salida, aparecer / desaparecer, • Detección de audio, • Detección de desenfoque, • Seguimiento automático digital, • Mapa de calor
B7: Cámara fija IP Panoramica 180° Modelo: PNM-9020V | C7: 9 | E7: 5 | F7: PNM-9000VQ | G7: Panoramica Multi-directional 360° | H7: 8MP | J7: 81.10 Mbps | K7: 176.95 Mbps | O7: 258.05 Mbps | P7: • Manipulación, • Merodeo, • Detección direccional, • Detección de empañamiento, • Línea virtual, entrada y salida, (des)aparición, • Detección facial, • Detección de movimiento, • Detección de desenfoque
B8: Camara fija IP Panoramica 360° Modelo: PNM-9000VQ | C8: 20 | E8: 6 | F8: PNM-9320VQP | G8: Panoramica Multi-directional 360° + PTZ | H8: 10MP | J8: 172.71 Mbps | K8: 282.62 Mbps | O8: 455.34 Mbps | P8: • Adulteración, • Ociosidad, • Detección direccional, • Detección de neblina, • Línea virtual, entradas y salidas, apariciones y desapariciones, • Detección facial, • Detección de movimiento, • Detección de desenfoque (cámara multidireccional)
B9: Camara IP Panoramica 360°/PTZ Modelo: PNM-9320VQP | C9: 14 | E9: 7 | F9: XNP-6320H | G9: Domo PTZ Exterior | H9: 2MP | J9: 14.27 Mbps | K9: 31.13 Mbps | O9: 45.40 Mbps | P9: • Manipulación, • Merodeo, • Detección de dirección, • Detección de niebla, • Línea virtual, entrada y salida, (Des) aparece, • Detección de audio, • Detección de rostros, • Detección de movimiento, • Clasificación de sonidos
B10: Camara IP PTZ Perimetral Modelo: XNP-6320H | C10: 19 | E10: 8 | F10: XNP-6320 | G10: Domo PTZ Interior | H10: 2MP | J10: 1.50 Mbps | K10: 3.28 Mbps | O10: 4.78 Mbps | P10: • Manipulación, • Merodeo, • Detección de dirección, • Detección de niebla, • Línea virtual, entrada y salida, (Des) aparece, • Detección de audio, • Detección de rostros, • Detección de movimiento, • Clasificación de sonidos
B11: Sistema CCTV Terminal | E11: 9 | F11: XNF-8010R | G11: Panoramica 360° Fisheye | H11: 6MP | J11: 39.42 Mbps | K11: 77.41 Mbps | O11: 116.84 Mbps | P11: • Manipulación, • Merodeo, • Detección de dirección, • Línea virtual, entrada y salida, (des) aparece, • Detección de audio, • Clasificación de sonidos, • Conteo de personas, • Mapa de calor, • Gestión de colas
B12: Camara IP Visualizacion Interior Modelo: XND-6080RV | C12: 242
B13: Camara IP Visualizacion Exterior Modelo: XNV-6080R | C13: 55
B14: Camara IP 360°/PTZ Interior Modelo: PNM-9320VQP | C14: 7 | F14: Notas:
B15: Camara IP 360°/PTZ Exterior Modelo: PNM-9320VQP | C15: 2 | G15: • Se recomienda la configuración de una red Multicast para la optimización de los streams de video demandados a cada cámara.
B16: Camara IP Panoramicas 360° Interior Modelo: XNF-8010R | C16: 21
B17: Camara IP Panoramica 360° Exterior Modelo: PNM-9000VQ | C17: 7
B18: Camara IP PTZ Modelo: XNP-6320 | C18: 2 | F18: Accesorios por Modelo
B19: Camara para Ascensores Modelo: XND-6010 | C19: 6 | F19: Accesorios por Modelo | J19: Resumen
F20: Cámara | G20: Accesorios | H20: Cantidad | J20: No. | K20: Modelo | L20: Cantidad
F21: XNV-6080R | G21: Hanging Mount Modelo: SBP-300HM6 | H21: 50 | J21: 1 | K21: 1.5" Coupler Modelo: SBP-HCF | M21: 95 | N21: 1.5" Coupler Modelo: SBP-HCF
F22: 103 | G22: Parapet Mount Modelo: SBP-300LM | J22: 2 | K22: Back Box Modelo: SBP-302CMB | M22: 9 | N22: 1.5" Coupler Modelo: SBP-HCF
G23: Hanging Mount Modelo: SBP-300HM6 | J23: 3 | K23: Flush Mount Modelo: SHD-3000F1 | M23: 15 | N23: 1.5" Coupler Modelo: SBP-HCF
G24: Wall Mount Arm Modelo: SBP-390WM1 | J24: 4 | K24: Hanging Mount Modelo: SBP-201HM | M24: 10 | N24: 1.5" Coupler Modelo: SBP-HCF
G25: Installation Box Modelo: SBP-300NB | J25: 5 | K25: Hanging Mount Modelo: SBP-276HM | M25: 10 | N25: 1.5" Coupler Modelo: SBP-HCF
F26: XND-6080RV | G26: Hanging Mount Modelo: SBP-300HM6 | H26: 95 | J26: 6 | K26: Hanging Mount Modelo: SBP-300HM5 | M26: 10 | N26: 1.5" Coupler Modelo: SBP-HCF
F27: 272 | G27: 1.5" Coupler Modelo: SBP-HCF | J27: 7 | K27: Hanging Mount Modelo: SBP-300HM6 | M27: 95 | N27: Back Box Modelo: SBP-302CMB
G28: Back Box Modelo: SBP-302CMB | J28: 8 | K28: Installation Box Modelo: SBP-300NB | M28: 9 | N28: Back Box Modelo: SBP-302CMB
G29: Flush Mount Modelo: SHD-3000F1 | J29: 9 | K29: Lentes 2M 2.8mm Modelo: SLA-2M2800P | M29: 15 | N29: Back Box Modelo: SBP-302CMB
G30: Hanging Mount Modelo: SBP-300HM6 | J30: 10 | K30: Lentes 2M 2.8mm Modelo: SLA-2M2800Q | M30: 10 | N30: Back Box Modelo: SBP-302CMB
G31: Wall Mount Arm Modelo: SBP-390WM1 | J31: 11 | K31: Parapet Mount Modelo: SBP-300LM | M31: 10 | N31: Back Box Modelo: SBP-302CMB
G32: Installation Box Modelo: SBP-300NB | J32: 12 | K32: Pole Mount Modelo: SBP-300PM | M32: 10 | N32: Back Box Modelo: SBP-302CMB
F33: XNO-6080R | G33: Pole Mount Modelo: SBP-302PM | H33: 27 | J33: 13 | K33: Pole Mount Modelo: SBP-302PM | M33: 95 | N33: Flush Mount Modelo: SHD-3000F1
F34: PNM-9020V | G34: Hanging Mount Modelo: SBP-201HM | H34: 9 | J34: 14 | K34: Wall Mount Arm Modelo: SBP-390WM1 | M34: 9 | N34: Hanging Mount Modelo: SBP-201HM
F35: 9 | G35: 1.5" Coupler Modelo: SBP-HCF | M35: 15 | N35: Hanging Mount Modelo: SBP-276HM
G36: Back Box Modelo: SBP-302CMB | M36: 12 | N36: Hanging Mount Modelo: SBP-276HM
F37: PNM-9000VQ | G37: Hanging Mount Modelo: SBP-276HM | H37: 15 | M37: 10 | N37: Hanging Mount Modelo: SBP-300HM5
F38: 27 | G38: 1.5" Coupler Modelo: SBP-HCF | M38: 11 | N38: Hanging Mount Modelo: SBP-300HM5
G39: Back Box Modelo: SBP-302CMB | M39: 50 | N39: Hanging Mount Modelo: SBP-300HM6
G40: Hanging Mount Modelo: SBP-276HM | M40: 53 | N40: Hanging Mount Modelo: SBP-300HM6
G41: Wall Mount Arm Modelo: SBP-390WM1 | M41: 95 | N41: Hanging Mount Modelo: SBP-300HM6
G42: Installation Box Modelo: SBP-300NB | M42: 177 | N42: Hanging Mount Modelo: SBP-300HM6
G43: Lentes 2M 2.8mm Modelo: SLA-2M2800Q | M43: 53 | N43: Installation Box Modelo: SBP-300NB
F44: PNM-9320VQP | G44: 1.5" Coupler Modelo: SBP-HCF | H44: 10 | M44: 177 | N44: Installation Box Modelo: SBP-300NB
F45: 23 | G45: Back Box Modelo: SBP-302CMB | M45: 12 | N45: Installation Box Modelo: SBP-300NB
G46: Wall Mount Arm Modelo: SBP-390WM1 | M46: 13 | N46: Installation Box Modelo: SBP-300NB
G47: Installation Box Modelo: SBP-300NB | M47: 9 | N47: Installation Box Modelo: SBP-300NB
G48: Lentes 2M 2.8mm Modelo: SLA-2M2800P | M48: 2 | N48: Installation Box Modelo: SBP-300NB
F49: XNP-6320H | G49: 1.5" Coupler Modelo: SBP-HCF | H49: 10 | M49: 11 | N49: Installation Box Modelo: SBP-300NB
F50: 19 | G50: Back Box Modelo: SBP-302CMB | M50: 92 | N50: Lentes 2M 2.8mm Modelo: SLA-2M2800P
G51: Wall Mount Arm Modelo: SBP-390WM1 | H51: 9 | M51: 108 | N51: Lentes 2M 2.8mm Modelo: SLA-2M2800Q
G52: Installation Box Modelo: SBP-300NB | M52: 50 | N52: Parapet Mount Modelo: SBP-300LM
G53: Pole Mount Modelo: SBP-300PM | H53: 10 | M53: 10 | N53: Pole Mount Modelo: SBP-300PM
F54: XNP-6320 | G54: Wall Mount Arm Modelo: SBP-390WM1 | H54: 2 | M54: 2 | N54: Pole Mount Modelo: SBP-300PM
F55: 2 | G55: Installation Box Modelo: SBP-300NB | H55: 2 | M55: 27 | N55: Pole Mount Modelo: SBP-302PM
G56: Pole Mount Modelo: SBP-300PM | H56: 2 | M56: 53 | N56: Wall Mount Arm Modelo: SBP-390WM1
F57: XNF-8010R | G57: Hanging Mount Modelo: SBP-300HM5 | H57: 10 | M57: 177 | N57: Wall Mount Arm Modelo: SBP-390WM1
F58: 21 | G58: 1.5" Coupler Modelo: SBP-HCF | M58: 12 | N58: Wall Mount Arm Modelo: SBP-390WM1
G59: Back Box Modelo: SBP-302CMB | M59: 13 | N59: Wall Mount Arm Modelo: SBP-390WM1
G60: Hanging Mount Modelo: SBP-300HM5 | H60: 11 | M60: 9 | N60: Wall Mount Arm Modelo: SBP-390WM1
G61: Wall Mount Arm Modelo: SBP-390WM1 | M61: 2 | N61: Wall Mount Arm Modelo: SBP-390WM1
G62: Installation Box Modelo: SBP-300NB | M62: 11 | N62: Wall Mount Arm Modelo: SBP-390WM1
F65: Materiales de Instalación
B66: Description | C66: Qty | F66: Materiales Varios Perímetro | K66: Materiales Varios Terminal
B67: Sistema CCTV Perímetro | F67: Materiales | G67: Precio Uni. | H67: Cantidad ML | I67: Costo Materiales | K67: Materiales | L67: Precio Uni. | M67: Cantidad ML | N67: Costo Materiales
B68: Cámara fija IP para Perimetro Exterior Modelo: XNV-6080R | C68: 48 | F68: Materiales Varios | K68: Materiales Varios
B69: Cámara fija IP para Perimetro Interior Modelo: XND-6080RV | C69: 30 | F69: Expansor Metalico S10 (Gabinetes) | G69: 50 | K69: Expansor Metalico S10 (Gabinetes) | L69: 50
B70: Cámara fija IP para Estacionamientos Modelo: XNO-6080R | C70: 15 | F70: Cinta aislante Negra | G70: 126.5 | K70: Cinta aislante Negra | L70: 126.5
B71: Cámara fija IP para Reconocimiento Modelo: XNO-6080R | C71: 12 | F71: Adecuaciones físicas | G71: 3000 | K71: Adecuaciones físicas | L71: 3000
B72: Cámara fija IP Panoramica 180° Modelo: PNM-9020V | C72: 9 | F72: Pegamento PVC 1/4 | G72: 218.48 | K72: Pegamento PVC 1/4 | L72: 218.48
B73: Camara fija IP Panoramica 360° Modelo: PNM-9000VQ | C73: 20 | F73: Canaleta plastica 1/2" | G73: 40 | K73: Canaleta plastica 1/2" | L73: 40
B74: Camara IP Panoramica 360°/PTZ Modelo: PNM-9320VQP | C74: 14 | F74: Canaleta plastica 3/4" | G74: 60 | K74: Canaleta plastica 3/4" | L74: 60
B75: Camara IP PTZ Perimetral Modelo: XNP-6320H | C75: 19 | F75: Espuma selladora | G75: 144 | K75: Espuma selladora | L75: 144
B76: Sistema CCTV Terminal | F76: Caja metalica 2x4 " pexon para exterior | G76: 270.6 | K76: Caja metalica 2x4 " pexon para exterior | L76: 270.6
B77: Camara IP Visualizacion Interior Modelo: XND-6080RV | C77: 242 | F77: Fajillas Plastica # 08 | G77: 0.95 | K77: Fajillas Plastica # 08 | L77: 0.95
B78: Camara IP Visualizacion Exterior Modelo: XNV-6080R | C78: 55 | F78: Fajillas Plastica # 12 | G78: 1.25 | K78: Fajillas Plastica # 12 | L78: 1.25
B79: Camara IP 360°/PTZ Interior Modelo: PNM-9320VQP | C79: 7 | F79: Conector Romex 3/8" | G79: 4.7 | K79: Conector Romex 3/8" | L79: 4.7
B80: Camara IP 360°/PTZ Exterior Modelo: PNM-9320VQP | C80: 2 | F80: Tubo Corrugado Rollo | G80: 2000 | K80: Tubo Corrugado Rollo | L80: 2000
B81: Camara IP Panoramicas 360° Interior Modelo: XNF-8010R | C81: 21 | F81: Rollo de Velcro 20m | K81: Rollo de Velcro 20m
B82: Camara IP Panoramica 360° Exterior Modelo: PNM-9000VQ | C82: 7 | F82: Tapadera ciega con salida de media Metalica 4x4" | G82: 7.39 | K82: Tapadera ciega con salida de media Metalica 4x4" | L82: 7.39
B83: Camara IP PTZ Modelo: XNP-6320 | C83: 2 | F83: Postes | K83: Postes
F84: Mastil 2-1/2" | G84: 2900 | K84: Mastil 2-1/2" | L84: 2900
F85: Mastil 4" | G85: 6000 | H85: 56 | K85: Mastil 4" | L85: 6000
F86: Poste 35 Ft Croncreto | G86: 7500 | K86: Poste 35 Ft Croncreto | L86: 7500
F87: Conector prensaestopa 1/2" | G87: 12.8 | K87: Conector prensaestopa 1/2" | L87: 12.8
F88: Abrazadera Strug 3/4" | G88: 6.7 | K88: Abrazadera Strug 3/4" | L88: 6.7
F89: Abrazadera Strug 1/2" | G89: 6.65 | K89: Abrazadera Strug 1/2" | L89: 6.65
F90: Tapaderas | K90: Tapaderas
F91: Canaleta Ranurada de 1-1/2" | G91: 67 | K91: Canaleta Ranurada de 1-1/2" | L91: 67
F92: Tapadera ciega Plastica 2x4" | G92: 45.5 | K92: Tapadera ciega Plastica 2x4" | L92: 45.5
F93: Tapadera ciega Metalica 2x4" | G93: 8.7 | K93: Tapadera ciega Metalica 2x4" | L93: 8.7
F94: Tapadera ciega Plastica 4x4" | G94: 37 | K94: Tapadera ciega Plastica 4x4" | L94: 37
F95: Tapadera ciega Metalica 4x4" | G95: 7.39 | K95: Tapadera ciega Metalica 4x4" | L95: 7.39
F96: Soportes de Tubería | K96: Soportes de Tubería
F97: Varilla Roscada 3/8" | G97: 100 | K97: Varilla Roscada 3/8" | L97: 100
F98: Arandela plana 3/8 | G98: 2 | K98: Arandela plana 3/8 | L98: 2
F99: Tuerca 3/8 Galvanizada | G99: 2 | K99: Tuerca 3/8 Galvanizada | L99: 2
F100: Riel Strut 1-5/8" | G100: 325 | K100: Riel Strut 1-5/8" | L100: 325
F101: Abrazadera 1/2" | G101: 3 | H101: 0 | K101: Abrazadera 1/2" | L101: 3 | M101: 0
F102: Taco fisher S8 con tornillo | G102: 2 | K102: Taco fisher S8 con tornillo | L102: 2
...

Sheet Evaluacion TIR-VAN
B3: Flujo de Caja | F3: 60 meses
G4: 2020 | H4: 2021 | I4: 2022 | J4: 2023 | K4: 2024 | L4: 2024
B5: Ingresos
B6: Ingresos Operativos | C6: USDk | G6: 0 | H6: 0 | I6: =+H6 -> 0 | J6: =+I6 -> 0 | K6: =+J6 -> 0
B8: Costos
B9: COGS | C9: USDk | G9: 0 | H9: 0 | I9: =+H9 -> 0 | J9: =+I9 -> 0 | K9: =+J9 -> 0
B10: Costos Variables | C10: USDk | G10: =-RESUMEN!C19 -> 0 | H10: 0 | I10: 0 | J10: 0 | K10: 0
B11: OPEX | C11: USDk | G11: 0 | H11: =-(SUM(RESUMEN!C10:C11)+RESUMEN!C18)/4 -> 0 | I11: =+H11 -> 0 | J11: =+I11 -> 0 | K11: =+J11 -> 0
B12: Otros gastos (incluye depreciaciones) | C12: USDk | G12: 0
B13: (-) Depreciaciones y amortizaciones | C13: USDk | G13: 0 | H13: 0 | I13: =+H13 -> 0 | J13: =+I13 -> 0 | K13: =+J13 -> 0
B14: Otros Ingresos | C14: USDk | G14: 0 | H14: 0 | I14: 0 | J14: 0 | K14: 0
B16: Impuestos | C16: USDk | G16: 0 | H16: =-SUM(H6:H14)*0.3 -> 0 | I16: =-SUM(I6:I14)*0.3 -> 0 | J16: =-SUM(J6:J14)*0.3 -> 0 | K16: =-SUM(K6:K14)*0.3 -> 0
B18: Flujo de Caja Operativo | C18: USDk | G18: =SUM(G6:G16) -> 0 | H18: =SUM(H6:H16) -> 0 | I18: =SUM(I6:I16) -> 0 | J18: =SUM(J6:J16) -> 0 | K18: =SUM(K6:K16) -> 0
B20: Inversiones
B21: Capex | C21: USDk | G21: 0 | H21: 0 | I21: 0 | J21: 0 | K21: 0
B22: Ajuste de Flujo | C22: USDk | H22: =H9*-1 -> 0 | I22: =I9*-1 -> 0 | J22: =J9*-1 -> 0 | K22: =K9*-1 -> 0
B23: Flujo de Caja de Inversión | C23: USDk | G23: =SUM(G21:G22) -> 0 | H23: =SUM(H21:H22) -> 0 | I23: =SUM(I21:I22) -> 0 | J23: =SUM(J21:J22) -> 0 | K23: =SUM(K21:K22) -> 0
B25: Financiamiento Adicional
B26: Capital Adicional | C26: USDk | G26: 0 | H26: 0 | I26: 0 | J26: 0 | K26: 0
B27: Total | C27: USDk | G27: =SUM(G26:G26) -> 0 | H27: =SUM(H26:H26) -> 0 | I27: =SUM(I26:I26) -> 0 | J27: =SUM(J26:J26) -> 0 | K27: =SUM(K26:K26) -> 0
B29: Flujo de caja disponible para servicio de Deuda | C29: USDk | G29: =G18+G23+G27 -> 0 | H29: =H18+H23+H27 -> 0 | I29: =I18+I23+I27 -> 0 | J29: =J18+J23+J27 -> 0 | K29: =K18+K23+K27 -> 0
B31: Servicio de Deuda
B32: Intereses | C32: USDk | G32: 0 | H32: 0 | I32: 0 | J32: 0 | K32: 0
B33: Principal | C33: USDk | G33: 0 | H33: 0 | I33: 0 | J33: 0 | K33: 0
B34: Total | C34: USDk | G34: =SUM(G32:G33) -> 0 | H34: =SUM(H32:H33) -> 0 | I34: =SUM(I32:I33) -> 0 | J34: =SUM(J32:J33) -> 0 | K34: =SUM(K32:K33) -> 0
B36: Flujo de Caja Neto | C36: USDk | G36: =G29+G34 -> 0 | H36: =H29+H34 -> 0 | I36: =I29+I34 -> 0 | J36: =J29+J34 -> 0 | K36: =K29+K34 -> 0
B38: Balance De Caja Inicial | C38: USDk | G38: 0 | H38: =G39 -> 0 | I38: =H39 -> 0 | J38: =I39 -> 0 | K38: =J39 -> 0
B39: Balance De Caja Final | C39: USDk | G39: =+G36+G38 -> 0 | H39: =+H36+H38 -> 0 | I39: =+I36+I38 -> 0 | J39: =+J36+J38 -> 0 | K39: =+K36+K38 -> 0
B40: Flujo acumulado | C40: # | G40: =+G39 -> 0 | H40: =+H39 -> 0 | I40: =+I39 -> 0 | J40: =+J39 -> 0 | K40: =+K39 -> 0
G41: 0 | H41: 1 | I41: 2 | J41: 3 | K41: 4
B42: Tasa de descuento | G42: 0 | H42: =G42 -> 0 | I42: =H42 -> 0 | J42: =I42 -> 0 | K42: =J42 -> 0
B43: Flujo descontado | G43: =+G36 -> 0 | H43: =H36/(1+H$42)^H41 -> 0 | I43: =I36/(1+I$42)^I41 -> 0 | J43: =J36/(1+J$42)^J41 -> 0 | K43: =K36/(1+K$42)^K41 -> 0
B44: VAN | F44: =+SUM(G43:L43) -> 0
B45: TIR | F45: =IFERROR(+IRR(G36:L36),"")
H46: =H43 -> 0 | I46: =I43 -> 0 | J46: =J43 -> 0 | K46: =K43 -> 0
H47: =SUM(H46:L46) -> 0

Sheet Resumen por Servicio
B1: Resumen de Costos por Servicio
B2: RESUMEN DE PROYECTO - CCTV
B3: Resumen del Proyecto | C3: Cantidad total para proyecto | D3: Costo Unitario | E3: Costo total | F3: % del costo | G3: Venta Unitario | H3: P. Venta total | I3: Costo Mensual (4 años) | J3: Venta mensual (4 años) Unitaria | K3: Venta mensual total | L3: Precio venta Ofertado unitario | M3: Precio venta total
B4: Cámaras PTZ | F4: =IFERROR(E4/$E$14,"")
B5: Cámaras Bullet | F5: =IFERROR(E5/$E$14,"")
B6: Centro de Monitoreo | F6: =IFERROR(E6/$E$14,"")
B7: Almacenamiento | F7: =IFERROR(E7/$E$14,"")
B8: VMS | F8: =IFERROR(E8/$E$14,"")
B9: Fibra optica | F9: =IFERROR(E9/$E$14,"")
B10: Gabinetes y paneles | F10: =IFERROR(E10/$E$14,"")
B11: Postes | F11: =IFERROR(E11/$E$14,"")
B12: Cámaras LPR | F12: =IFERROR(E12/$E$14,"")
B13: Control de Acceso | F13: =IFERROR(E13/$E$14,"")
B14: TOTALES
B17: Servicio | C17: Porcentaje de margen con financiamiento (unitario)
B18: Cámaras PTZ | C18: =IFERROR((J4-I4)/J4,"")
B19: Cámaras Bullet | C19: =IFERROR((J5-I5)/J5,"")
B20: Centro de Monitoreo | C20: =IFERROR((J6-I6)/J6,"")
B21: Almacenamiento | C21: =IFERROR((J7-I7)/J7,"")
B22: VMS | C22: =IFERROR((J8-I8)/J8,"")
B23: Fibra optica | C23: =IFERROR((J9-I9)/J9,"")
B24: Gabinetes y paneles | C24: =IFERROR((J10-I10)/J10,"")
B25: Postes | C25: =IFERROR((J11-I11)/J11,"")
B26: Cámaras LPR | C26: =IFERROR((J12-I12)/J12,"")
B27: Control de Acceso | C27: =IFERROR((J13-I13)/J13,"")
B30: Oferta Version 2 | C30: Oferta Version 1
A31: Costo | C31: 477579.73
A32: Venta sin impuesto | C32: 676559.19
A33: Margen | B33: =IFERROR((B32-B31)/B32,"")
A34: Cuota por financiamiento | C34: 33773.639
A35: Numero de cuotas | B35: 48 | C35: 48
A36: Venta financiada
A37: Utilidad esperada | C37: 1004708.1
C38: Utilidad de proyecto

Sheet RESUMEN
B1: Resumen de Costos por Componente | F1: Tasa $ | G1: 25
B2: RESUMEN DE PROYECTO - CCTV | J2: OPCIÓN DE SERVICIOS POR 4 AÑOS
B3: Resumen del Proyecto | C3: Costo | D3: % del costo | E3: % de venta | F3: P. Venta | G3: Margen X Componente | J3: Monto | K3: =+F12 -> 0 | L3: Int.s | M3: 0.1
A4: CCTV | B4: =Equipos!B3 -> Productos 1 | C4: =+Equipos!M57 -> 0 | D4: =IFERROR(C4/$C$12,"") | E4: =+Equipos!N4 -> 0.274 | F4: =Tabla2[[#This Row],[Costo]]/(1-Tabla2[[#This Row],[% de venta]]) -> 0 | G4: =+Tabla2[[#This Row],[P. Venta ]]-Tabla2[[#This Row],[Costo]] -> 0 | J4: Plazo | K4: 48
B5: =+'Productos 2'!A3 -> Productos 2 | C5: =+'Productos 2'!L17 -> 0 | D5: =IFERROR(C5/$C$12,"") | E5: =+'Productos 2'!M4 -> 0.3 | F5: =Tabla2[[#This Row],[Costo]]/(1-Tabla2[[#This Row],[% de venta]]) -> 0 | G5: =+Tabla2[[#This Row],[P. Venta ]]-Tabla2[[#This Row],[Costo]] -> 0 | J5: Cuota | K5: =PMT(M3/12,K4,-K3) -> 0
B6: =+'Productos 3'!A3 -> Productos 3 | C6: =+'Productos 3'!L22 -> 0 | D6: =IFERROR(C6/$C$12,"") | E6: =+'Productos 3'!M4 -> 0.3 | F6: =Tabla2[[#This Row],[Costo]]/(1-Tabla2[[#This Row],[% de venta]]) -> 0 | G6: =+Tabla2[[#This Row],[P. Venta ]]-Tabla2[[#This Row],[Costo]] -> 0 | J6: TIR | K6: =IFERROR('Evaluacion TIR-VAN'!F45,"")
B7: =+'Productos 4'!A3 -> Productos 4 | C7: =+'Productos 4'!L21 -> 0 | D7: =IFERROR(C7/$C$12,"") | E7: =+'Productos 4'!M4 -> 0.3 | F7: =Tabla2[[#This Row],[Costo]]/(1-Tabla2[[#This Row],[% de venta]]) -> 0 | G7: =+Tabla2[[#This Row],[P. Venta ]]-Tabla2[[#This Row],[Costo]] -> 0 | J7: Utilidad Neta del Ejercicio | L7: ='Evaluacion TIR-VAN'!H47 -> 0 | M7: =IFERROR(L7/K3,"")
B8: =+'Productos 5'!A3 -> Productos 5 | C8: =+'Productos 5'!L25 -> 0 | D8: =IFERROR(C8/$C$12,"") | E8: =+'Productos 5'!M4 -> 0.3 | F8: =Tabla2[[#This Row],[Costo]]/(1-Tabla2[[#This Row],[% de venta]]) -> 0 | G8: =+Tabla2[[#This Row],[P. Venta ]]-Tabla2[[#This Row],[Costo]] -> 0
A9: Materiales/otros | B9: =+MATERIALES!A3 -> Materiales | C9: =+MATERIALES!L46 -> 0 | D9: =IFERROR(C9/$C$12,"") | E9: =+MATERIALES!M4 -> 0.3 | F9: =Tabla2[[#This Row],[Costo]]/(1-Tabla2[[#This Row],[% de venta]]) -> 0 | G9: =+Tabla2[[#This Row],[P. Venta ]]-Tabla2[[#This Row],[Costo]] -> 0
B10: =+'OPEX GV'!A3 -> OPEX GV | C10: 0 | D10: =IFERROR(C10/$C$12,"") | E10: =+'OPEX GV'!M4 -> 0.274 | F10: =Tabla2[[#This Row],[Costo]]/(1-Tabla2[[#This Row],[% de venta]]) -> 0 | G10: =+Tabla2[[#This Row],[P. Venta ]]-Tabla2[[#This Row],[Costo]] -> 0
A11: OPEX | B11: =+'OPEX Proyecto'!A3 -> OPEX | C11: 0 | D11: =IFERROR(C11/$C$12,"") | E11: =+'OPEX Proyecto'!M4 -> 0.3 | F11: =Tabla2[[#This Row],[Costo]]/(1-Tabla2[[#This Row],[% de venta]]) -> 0 | G11: =+Tabla2[[#This Row],[P. Venta ]]-Tabla2[[#This Row],[Costo]] -> 0
B12: TOTALES | C12: =SUBTOTAL(109,C4:C11) -> 0 | D12: =SUBTOTAL(109,D4:D11) -> 0 | E12: =+AVERAGE(E4:E11) -> 0.2935 | F12: =SUBTOTAL(109,F4:F11) -> 0 | G12: =SUBTOTAL(109,G4:G11) -> 0
B15: Ingresos | C15: =F12 -> 0
B16: Costos | C16: =C12 -> 0
B17: Margen bruto | C17: =C15-C16 -> 0
B18: Opex | C18: =C11 -> 0
B19: Opex administrativo
B20: Comisiones | C20: =C15*3% -> 0
B21: Utilidad Operativa | C21: =+C17-SUM(C18:C20) -> 0
B22: Fianzas | C22: 0
B23: Costo financiero | C23: 0
B24: Utilidad antes de ISR | C24: =C21-C22-C23 -> 0
B25: ISR | C25: =C24*Tabla2[[#This Row],[% del costo]] -> 0 | D25: =_xlfn.IFS(C24<=D34,C34,C24<=D35,C35,C24>D36,C36) -> 0.1
B26: Utilidad neta | C26: =C24-C25 -> 0 | D26: =IFERROR(Tabla2[[#This Row],[Costo]]/F12,"")
B29: Utilidad Neta del Ejercicio | C29: =C26 -> 0 | D29: =IFERROR(+C29/F12,"")
A32: Hasta | B32: IMPUESTO SOBRE LA RENTA COSTA RICA
A33: Hasta | B33: Ingresos brutos | C33: Tarifa(Se aplica sobre renta neta total) | D33: Ingresos Brutos $
A34: Mayor de | B34: 54303000 | C34: 0.1 | D34: =B34/565 -> 96111.504
B35: 109228000 | C35: 0.2 | D35: =B35/565 -> 193323.89 | F35: =_xlfn.IFS(C14<=D34,C34,C14<=D35,C35,C14>D36,C36) -> 0.1
B36: 109228000 | C36: 0.3 | D36: =B36/565 -> 193323.89

Sheet Resumen para oferta
B1: Ítem | C1: Descripción | D1: Cant. | E1: Precio Venta | F1: Total
B2: 1 | C2: HARDWARE | D2: 1 | F2: =E2*D2 -> 0
B3: 2 | C3: MATERIALES DE INSTALACION Y REDES | D3: 1 | E3: 0 | F3: =E3*D3 -> 0
B4: 3 | C4: Centro de Datos/Monitoreo | D4: 1 | E4: 0 | F4: =E4*D4 -> 0
B5: 5 | C5: GASTOS DE VIAJE Y ESTADIAS | D5: 1 | E5: 0 | F5: =E5*D5 -> 0
B6: 6 | C6: ADMINISTRACION DE PROYECTO | D6: 1 | E6: 0 | F6: =E6*D6 -> 0
E7: Sub Total | F7: =SUM(F2:F6) -> 0
B8: 4 | C8: SERVICIOS DE IMPLEMENTACION | D8: 1 | E8: 0 | F8: =E8*D8 -> 0
E9: IVA | F9: =F7*0.13 -> 0
E10: Total | F10: =SUM(F7:F9) -> 0
B15: Ítem | C15: Cantidad | D15: Proveedor | E15: #Parte | F15: Marca | G15: Marca | H15: Descripción / Código | J15: Costo Unitario | K15: Sub Total
B17: 1 | K17: =+J17*C17 -> 0
B18: 2 | C18: =+Equipos!D6 -> 0 | H18: =+Equipos!B6 -> 0 | J18: =+Equipos!O6 -> 0 | K18: =+J18*C18 -> 0
B19: 3 | C19: =+Equipos!D7 -> 0 | H19: =+Equipos!B7 -> 0 | J19: =+Equipos!O7 -> 0 | K19: =+J19*C19 -> 0
B20: 4 | K20: =+J20*C20 -> 0
B21: 5 | K21: =J21*C21 -> 0
B22: 6 | K22: =J22*C22 -> 0
B23: 7 | C23: =+'Productos 5'!C9 -> 0 | J23: =+'Productos 5'!N9 -> 0 | K23: =J23*C23 -> 0
B24: 6 | C24: =+'Productos 5'!C10 -> 0 | J24: =+'Productos 5'!N10 -> 0 | K24: =J24*C24 -> 0
B25: 7 | C25: =+'Productos 5'!C11 -> 0 | J25: =+'Productos 5'!N11 -> 0 | K25: =J25*C25 -> 0
B26: Precios ya incluyen impuesto de venta
J27: Subtotal | K27: =SUM(K17:K25) -> 0
J28: Materiales y accesorios | K28: =+MATERIALES!O46 -> 0
J29: Mano de obra por instalación y puesta en marcha | K29: =+'OPEX GV'!O17 -> 0
J30: Impuesto de Ventas | K30: =(K27+K28+K29)*0.13 -> 0
J31: Total de Oferta | K31: =SUM(K27:K30) -> 0
K39: =K31*635 -> 0
B44: Ítem | C44: Cantidad | F44: IMG | G44: Marca | H44: Descripción / Código | J44: Costo Unitario | K44: Sub Total
B45: Implementación de sistemas de seguridad
B46: 1 | C46: 1 | G46: GV | H46: ='Productos 2'!A6 -> 0 | J46: ='Productos 2'!N6 -> 0 | K46: =+J46*C46 -> 0
B47: Precios ya incluyen impuesto de venta
J48: Subtotal | K48: =K46 -> 0
J49: Materiales y accesorios | K49: =+MATERIALES!O83 -> 0
J50: Mano de obra por instalación y puesta en marcha | K50: 0
J51: Impuesto de Ventas | K51: =(K48+K49+K50)*0.13 -> 0
J52: Total de Oferta | K52: =SUM(K48:K51) -> 0

Sheet COTIZACIÓN 
B5: Cédula Jurídica: 3101666618 | I5: www.grupovision.org
B6: Tibas Anselmo Llorente, Cámara Costarricense de la Construción
B7: San José, Costa Rica
B8: Teléfonos: (506) 40101090
J10: V1
B12: Nombre: | I12: Fecha: | J12: =TODAY() -> 46314
B13: Atención: | I13: Cotización #: | J13: T5-0000000-26
B14: Correo: | I14: Validez de: | J14: 15 días
B15: Tel: | I15: Método de envío: | J15: Electrónico
B16: Dirreción: | C16: San José, Costa Rica | I16: Ref:
B17: Asesor:
B20: Cantidad | C20: Descripción | I20: Precio U. | J20: Total Contado
C21: Equipos
B22: =Equipos!D6 -> 0 | C22: =Equipos!B6 -> 0 | I22: =Equipos!O6 -> 0 | J22: =I22*B22 -> 0
B23: =Equipos!D7 -> 0 | C23: =Equipos!B7 -> 0 | I23: =Equipos!O7 -> 0 | J23: =I23*B23 -> 0
B24: =Equipos!D8 -> 0 | C24: =Equipos!B8 -> 0 | I24: =Equipos!O8 -> 0 | J24: =I24*B24 -> 0
B25: =Equipos!D9 -> 0 | C25: =Equipos!B9 -> 0 | I25: =Equipos!O9 -> 0 | J25: =I25*B25 -> 0
B26: =Equipos!D10 -> 0 | C26: =Equipos!B10 -> 0 | I26: =Equipos!O10 -> 0 | J26: =I26*B26 -> 0
B27: =Equipos!D11 -> 0 | C27: =Equipos!B11 -> 0 | I27: =Equipos!O11 -> 0 | J27: =I27*B27 -> 0
B28: =Equipos!D12 -> 0 | C28: =Equipos!B12 -> 0 | I28: =Equipos!O12 -> 0 | J28: =I28*B28 -> 0
B29: =Equipos!D13 -> 0 | C29: =Equipos!B13 -> 0 | I29: =Equipos!O13 -> 0 | J29: =I29*B29 -> 0
B30: =Equipos!D14 -> 0 | C30: =Equipos!B14 -> 0 | I30: =Equipos!O14 -> 0 | J30: =I30*B30 -> 0
B31: =Equipos!D15 -> 0 | C31: =Equipos!B15 -> 0 | I31: =Equipos!O15 -> 0 | J31: =I31*B31 -> 0
B32: =Equipos!D16 -> 0 | C32: =Equipos!B16 -> 0 | I32: =Equipos!O16 -> 0 | J32: =I32*B32 -> 0
B33: =Equipos!D17 -> 0 | C33: =Equipos!B17 -> 0 | I33: =Equipos!O17 -> 0 | J33: =I33*B33 -> 0
... B71: =Equipos!D55 -> 0 | C71: =Equipos!B55 -> 0 | I71: =Equipos!O55 -> 0 | J71: =I71*B71 -> 0
B72: ****************************************U.L****************************************
I74: SUBTOTAL | J74: =SUM(J21:J73) -> 0 | K74: =+Equipos!P57+'OPEX GV'!O17 -> 0 | L74: =IF(ROUND(SUM(J22:J71)-SUBTOTAL(109,J22:J71),2)<>0,"OJO: hay l"&_xlfn.UNICHAR(237)&"neas ocultas con monto. Mostralas: si no, suman pero no aparecen en la cotizaci"&_xlfn.UNICHAR(243)&"n.","")
I75: IMPUESTO | J75: =J74*IF(LOWER(TRIM('Datos del proyecto'!$B$15))="si",0,IF(ISNUMBER('Datos del proyecto'!$B$16),IF('Datos del proyecto'!$B$16>1,'Datos del proyecto'!$B$16/100,'Datos del proyecto'!$B$16),0.13)) -> 0
B76: ss | I76: TOTAL | J76: =ROUNDDOWN(J74+J75,2) -> 0
B88: [Nombre del asesor responsable]
B89: Depto Preventa y Diseño
B90: Edificio Cámara Costarricense de la Construcción Piso 4, oficina 401
B91: Teléfonos: (506) 40101090
B92: E-mail: [correo del asesor]

Sheet COTIZACION (Financ)
B5: Cédula Jurídica: 3101666618 | I5: www.grupovision.org
B6: Tibas Anselmo Llorente, Cámara Costarricense de la Construción
B7: San José, Costa Rica
B8: Teléfonos: (506) 40101090
J10: V1
B12: Nombre: | I12: Fecha: | J12: =TODAY() -> 46314
B13: Atención: | I13: Cotización #: | J13: T5-0000000-26
B14: Correo: | I14: Validez de: | J14: 15 días
B15: Tel: | I15: Método de envío: | J15: Electrónico
B16: Dirreción: | C16: San José, Costa Rica | I16: Ref:
B17: Asesor:
B20: Cantidad | C20: Descripción | I20: Precio Unitario Mensual | J20: Total Mensual
C21: Equipos
B22: =Equipos!D6 -> 0 | C22: =Equipos!B6 -> 0 | I22: =IFERROR(IF(Equipos!Q6="","",INDEX(Financiamiento!$C:$C,12+(Equipos!Q6-1)*17)),"") | J22: =IFERROR(I22*B22,"")
B23: =Equipos!D7 -> 0 | C23: =Equipos!B7 -> 0 | I23: =IFERROR(IF(Equipos!Q7="","",INDEX(Financiamiento!$C:$C,12+(Equipos!Q7-1)*17)),"") | J23: =IFERROR(I23*B23,"")
B24: =Equipos!D8 -> 0 | C24: =Equipos!B8 -> 0 | I24: =IFERROR(IF(Equipos!Q8="","",INDEX(Financiamiento!$C:$C,12+(Equipos!Q8-1)*17)),"") | J24: =IFERROR(I24*B24,"")
B25: =Equipos!D9 -> 0 | C25: =Equipos!B9 -> 0 | I25: =IFERROR(IF(Equipos!Q9="","",INDEX(Financiamiento!$C:$C,12+(Equipos!Q9-1)*17)),"") | J25: =IFERROR(I25*B25,"")
B26: =Equipos!D10 -> 0 | C26: =Equipos!B10 -> 0 | I26: =IFERROR(IF(Equipos!Q10="","",INDEX(Financiamiento!$C:$C,12+(Equipos!Q10-1)*17)),"") | J26: =IFERROR(I26*B26,"")
B27: =Equipos!D11 -> 0 | C27: =Equipos!B11 -> 0 | I27: =IFERROR(IF(Equipos!Q11="","",INDEX(Financiamiento!$C:$C,12+(Equipos!Q11-1)*17)),"") | J27: =IFERROR(I27*B27,"")
B28: =Equipos!D12 -> 0 | C28: =Equipos!B12 -> 0 | I28: =IFERROR(IF(Equipos!Q12="","",INDEX(Financiamiento!$C:$C,12+(Equipos!Q12-1)*17)),"") | J28: =IFERROR(I28*B28,"")
B29: =Equipos!D13 -> 0 | C29: =Equipos!B13 -> 0 | I29: =IFERROR(IF(Equipos!Q13="","",INDEX(Financiamiento!$C:$C,12+(Equipos!Q13-1)*17)),"") | J29: =IFERROR(I29*B29,"")
B30: =Equipos!D14 -> 0 | C30: =Equipos!B14 -> 0 | I30: =IFERROR(IF(Equipos!Q14="","",INDEX(Financiamiento!$C:$C,12+(Equipos!Q14-1)*17)),"") | J30: =IFERROR(I30*B30,"")
B31: =Equipos!D15 -> 0 | C31: =Equipos!B15 -> 0 | I31: =IFERROR(IF(Equipos!Q15="","",INDEX(Financiamiento!$C:$C,12+(Equipos!Q15-1)*17)),"") | J31: =IFERROR(I31*B31,"")
B32: =Equipos!D16 -> 0 | C32: =Equipos!B16 -> 0 | I32: =IFERROR(IF(Equipos!Q16="","",INDEX(Financiamiento!$C:$C,12+(Equipos!Q16-1)*17)),"") | J32: =IFERROR(I32*B32,"")
B33: =Equipos!D17 -> 0 | C33: =Equipos!B17 -> 0 | I33: =IFERROR(IF(Equipos!Q17="","",INDEX(Financiamiento!$C:$C,12+(Equipos!Q17-1)*17)),"") | J33: =IFERROR(I33*B33,"")
... B71: =Equipos!D55 -> 0 | C71: =Equipos!B55 -> 0 | I71: =IFERROR(IF(Equipos!Q55="","",INDEX(Financiamiento!$C:$C,12+(Equipos!Q55-1)*17)),"") | J71: =IFERROR(I71*B71,"")
B72: ****************************************U.L****************************************
I74: SUBTOTAL | J74: =SUM(J21:J73) -> 0 | K74: =+Equipos!P57+'OPEX GV'!O17 -> 0 | L74: =IF(ROUND(SUM(J22:J71)-SUBTOTAL(109,J22:J71),2)<>0,"OJO: hay l"&_xlfn.UNICHAR(237)&"neas ocultas con monto. Mostralas: si no, suman pero no aparecen en la cotizaci"&_xlfn.UNICHAR(243)&"n.","")
I75: IMPUESTO | J75: =J74*IF(LOWER(TRIM('Datos del proyecto'!$B$15))="si",0,IF(ISNUMBER('Datos del proyecto'!$B$16),IF('Datos del proyecto'!$B$16>1,'Datos del proyecto'!$B$16/100,'Datos del proyecto'!$B$16),0.13)) -> 0
B76: ss | I76: TOTAL MENSUAL | J76: =ROUNDDOWN(J74+J75,2) -> 0
B88: [Nombre del asesor responsable]
B89: Depto Preventa y Diseño
B90: Edificio Cámara Costarricense de la Construcción Piso 4, oficina 401
B91: Teléfonos: (506) 40101090
B92: E-mail: [correo del asesor]

Sheet Equipos
B1: MATRIZ DE COSTO PROYECTO:
L2: 0.04
B3: Productos 1 | G3: Transporte | H3: Imprevistos | I3: IVA | J3: DAI | K3: Costo Untit | L3: Administración | M3: Costo total | N3: Margen GV | O3: Precio Venta | P3: Precio Venta | Q3: Financ.
B4: Description | C4: IMPORTADO | D4: Qty | E4: Costo Unit | F4: Costo Total | G4: 0.1 | H4: 0.03 | I4: 0 | J4: 0.15 | K4: Nacionalizado | L4: 0.03 | M4: Nacionalizado | N4: 0.274 | O4: Unitario | P4: Total
B5: Sección 1
C6: no | D6: 0 | E6: 0 | F6: =E6*D6 -> 0 | G6: =IF(C6="si",E6*$G$4,0) -> 0 | H6: =(E6+G6)*$H$4 -> 0 | I6: =+(E6+G6+H6)*$I$4 -> 0 | J6: =IF(C6="si",(E6+G6+H6+I6)*$J$4,0) -> 0 | K6: =E6+G6+H6+I6+J6 -> 0 | L6: =K6*$L$4 -> 0 | M6: =(K6+L6)*D6 -> 0 | N6: =(K6+L6)*$N$4/(1-$N$4) -> 0 | O6: =N6+K6+L6 -> 0 | P6: =O6*D6 -> 0
C7: no | D7: 0 | E7: 0 | F7: =E7*D7 -> 0 | G7: =IF(C7="si",E7*$G$4,0) -> 0 | H7: =(E7+G7)*$H$4 -> 0 | I7: =+(E7+G7+H7)*$I$4 -> 0 | J7: =IF(C7="si",(E7+G7+H7+I7)*$J$4,0) -> 0 | K7: =E7+G7+H7+I7+J7 -> 0 | L7: =K7*$L$4 -> 0 | M7: =(K7+L7)*D7 -> 0 | N7: =(K7+L7)*$N$4/(1-$N$4) -> 0 | O7: =N7+K7+L7 -> 0 | P7: =O7*D7 -> 0
C8: no | D8: 0 | E8: 0 | F8: =E8*D8 -> 0 | G8: =IF(C8="si",E8*$G$4,0) -> 0 | H8: =(E8+G8)*$H$4 -> 0 | I8: =+(E8+G8+H8)*$I$4 -> 0 | J8: =IF(C8="si",(E8+G8+H8+I8)*$J$4,0) -> 0 | K8: =E8+G8+H8+I8+J8 -> 0 | L8: =K8*$L$4 -> 0 | M8: =(K8+L8)*D8 -> 0 | N8: =(K8+L8)*$N$4/(1-$N$4) -> 0 | O8: =N8+K8+L8 -> 0 | P8: =O8*D8 -> 0
C9: no | D9: 0 | E9: 0 | F9: =E9*D9 -> 0 | G9: =IF(C9="si",E9*$G$4,0) -> 0 | H9: =(E9+G9)*$H$4 -> 0 | I9: =+(E9+G9+H9)*$I$4 -> 0 | J9: =IF(C9="si",(E9+G9+H9+I9)*$J$4,0) -> 0 | K9: =E9+G9+H9+I9+J9 -> 0 | L9: =K9*$L$4 -> 0 | M9: =(K9+L9)*D9 -> 0 | N9: =(K9+L9)*$N$4/(1-$N$4) -> 0 | O9: =N9+K9+L9 -> 0 | P9: =O9*D9 -> 0
C10: no | D10: 0 | E10: 0 | F10: =E10*D10 -> 0 | G10: =IF(C10="si",E10*$G$4,0) -> 0 | H10: =(E10+G10)*$H$4 -> 0 | I10: =+(E10+G10+H10)*$I$4 -> 0 | J10: =IF(C10="si",(E10+G10+H10+I10)*$J$4,0) -> 0 | K10: =E10+G10+H10+I10+J10 -> 0 | L10: =K10*$L$4 -> 0 | M10: =(K10+L10)*D10 -> 0 | N10: =(K10+L10)*$N$4/(1-$N$4) -> 0 | O10: =N10+K10+L10 -> 0 | P10: =O10*D10 -> 0
C11: no | D11: 0 | E11: 0 | F11: =E11*D11 -> 0 | G11: =IF(C11="si",E11*$G$4,0) -> 0 | H11: =(E11+G11)*$H$4 -> 0 | I11: =+(E11+G11+H11)*$I$4 -> 0 | J11: =IF(C11="si",(E11+G11+H11+I11)*$J$4,0) -> 0 | K11: =E11+G11+H11+I11+J11 -> 0 | L11: =K11*$L$4 -> 0 | M11: =(K11+L11)*D11 -> 0 | N11: =(K11+L11)*$N$4/(1-$N$4) -> 0 | O11: =N11+K11+L11 -> 0 | P11: =O11*D11 -> 0
C12: no | D12: 0 | E12: 0 | F12: =E12*D12 -> 0 | G12: =IF(C12="si",E12*$G$4,0) -> 0 | H12: =(E12+G12)*$H$4 -> 0 | I12: =+(E12+G12+H12)*$I$4 -> 0 | J12: =IF(C12="si",(E12+G12+H12+I12)*$J$4,0) -> 0 | K12: =E12+G12+H12+I12+J12 -> 0 | L12: =K12*$L$4 -> 0 | M12: =(K12+L12)*D12 -> 0 | N12: =(K12+L12)*$N$4/(1-$N$4) -> 0 | O12: =N12+K12+L12 -> 0 | P12: =O12*D12 -> 0
C13: no | D13: 0 | E13: 0 | F13: =E13*D13 -> 0 | G13: =IF(C13="si",E13*$G$4,0) -> 0 | H13: =(E13+G13)*$H$4 -> 0 | I13: =+(E13+G13+H13)*$I$4 -> 0 | J13: =IF(C13="si",(E13+G13+H13+I13)*$J$4,0) -> 0 | K13: =E13+G13+H13+I13+J13 -> 0 | L13: =K13*$L$4 -> 0 | M13: =(K13+L13)*D13 -> 0 | N13: =(K13+L13)*$N$4/(1-$N$4) -> 0 | O13: =N13+K13+L13 -> 0 | P13: =O13*D13 -> 0
C14: no | D14: 0 | E14: 0 | F14: =E14*D14 -> 0 | G14: =IF(C14="si",E14*$G$4,0) -> 0 | H14: =(E14+G14)*$H$4 -> 0 | I14: =+(E14+G14+H14)*$I$4 -> 0 | J14: =IF(C14="si",(E14+G14+H14+I14)*$J$4,0) -> 0 | K14: =E14+G14+H14+I14+J14 -> 0 | L14: =K14*$L$4 -> 0 | M14: =(K14+L14)*D14 -> 0 | N14: =(K14+L14)*$N$4/(1-$N$4) -> 0 | O14: =N14+K14+L14 -> 0 | P14: =O14*D14 -> 0
C15: no | D15: 0 | E15: 0 | F15: =E15*D15 -> 0 | G15: =IF(C15="si",E15*$G$4,0) -> 0 | H15: =(E15+G15)*$H$4 -> 0 | I15: =+(E15+G15+H15)*$I$4 -> 0 | J15: =IF(C15="si",(E15+G15+H15+I15)*$J$4,0) -> 0 | K15: =E15+G15+H15+I15+J15 -> 0 | L15: =K15*$L$4 -> 0 | M15: =(K15+L15)*D15 -> 0 | N15: =(K15+L15)*$N$4/(1-$N$4) -> 0 | O15: =N15+K15+L15 -> 0 | P15: =O15*D15 -> 0
C16: no | D16: 0 | E16: 0 | F16: =E16*D16 -> 0 | G16: =IF(C16="si",E16*$G$4,0) -> 0 | H16: =(E16+G16)*$H$4 -> 0 | I16: =+(E16+G16+H16)*$I$4 -> 0 | J16: =IF(C16="si",(E16+G16+H16+I16)*$J$4,0) -> 0 | K16: =E16+G16+H16+I16+J16 -> 0 | L16: =K16*$L$4 -> 0 | M16: =(K16+L16)*D16 -> 0 | N16: =(K16+L16)*$N$4/(1-$N$4) -> 0 | O16: =N16+K16+L16 -> 0 | P16: =O16*D16 -> 0
C17: no | D17: 0 | E17: 0 | F17: =E17*D17 -> 0 | G17: =IF(C17="si",E17*$G$4,0) -> 0 | H17: =(E17+G17)*$H$4 -> 0 | I17: =+(E17+G17+H17)*$I$4 -> 0 | J17: =IF(C17="si",(E17+G17+H17+I17)*$J$4,0) -> 0 | K17: =E17+G17+H17+I17+J17 -> 0 | L17: =K17*$L$4 -> 0 | M17: =(K17+L17)*D17 -> 0 | N17: =(K17+L17)*$N$4/(1-$N$4) -> 0 | O17: =N17+K17+L17 -> 0 | P17: =O17*D17 -> 0
... C55: no | D55: 0 | E55: 0 | F55: =E55*D55 -> 0 | G55: =IF(C55="si",E55*$G$4,0) -> 0 | H55: =(E55+G55)*$H$4 -> 0 | I55: =+(E55+G55+H55)*$I$4 -> 0 | J55: =IF(C55="si",(E55+G55+H55+I55)*$J$4,0) -> 0 | K55: =E55+G55+H55+I55+J55 -> 0 | L55: =K55*$L$4 -> 0 | M55: =(K55+L55)*D55 -> 0 | N55: =(K55+L55)*$N$4/(1-$N$4) -> 0 | O55: =N55+K55+L55 -> 0 | P55: =O55*D55 -> 0
E57: Total FOB | F57: =SUM(F3:F55) -> 0 | K57: Costo Nac. | M57: =SUM(M6:M55) -> 0 | O57: Total Venta | P57: =SUM(P6:P55) -> 0
O58: UTILIDAD | P58: =P57-M57 -> 0
B60: IMPORTADO
B61: si
B62: no

Sheet Productos 2
A1: MATRIZ DE COSTO PROYECTO: | E1: =+Equipos!E1 -> 0
A3: Productos 2 | F3: Transporte | G3: Seguros | H3: IVA | I3: DAI | J3: Costo Untit | K3: Administración | L3: Costo total | M3: Margen GV | N3: Precio Venta | O3: Precio Venta | P3: Financ.
A4: Description | C4: Qty | D4: Costo Unit | E4: Costo Total | F4: 0.1 | G4: 0 | H4: 0.13 | I4: 0.14 | J4: Nacionalizado | K4: 0.03 | L4: Nacionaliado | M4: 0.3 | N4: Unitario | O4: Total
A5: Sección 1 | B5: IMPORTADO
B6: no | C6: 0 | D6: 0 | E6: =+D6*C6 -> 0 | F6: =IF(B6="si",D6*$F$4,0) -> 0 | G6: 0 | H6: =(D6+F6+G6)*$H$4 -> 0 | I6: =IF(B6="si",(D6+F6+G6+H6)*$I$4,0) -> 0 | J6: =D6+F6+G6+H6+I6 -> 0 | K6: =J6*$K$4 -> 0 | L6: =(J6+K6)*C6 -> 0 | M6: =(J6+K6)*$M$4/(1-$M$4) -> 0 | N6: =M6+J6+K6 -> 0 | O6: =N6*C6 -> 0
B7: no | C7: 0 | D7: 0 | E7: =+D7*C7 -> 0 | F7: =IF(B7="si",D7*$F$4,0) -> 0 | G7: =(D7+F7)*$G$4 -> 0 | H7: =(D7+F7+G7)*$H$4 -> 0 | I7: =IF(B7="si",(D7+F7+G7+H7)*$I$4,0) -> 0 | J7: =D7+F7+G7+H7+I7 -> 0 | K7: =J7*$K$4 -> 0 | L7: =(J7+K7)*C7 -> 0 | M7: =(J7+K7)*$M$4/(1-$M$4) -> 0 | N7: =M7+J7+K7 -> 0 | O7: =N7*C7 -> 0
B8: no | C8: 0 | D8: 0 | E8: =+D8*C8 -> 0 | F8: =IF(B8="si",D8*$F$4,0) -> 0 | G8: =(D8+F8)*$G$4 -> 0 | H8: =(D8+F8+G8)*$H$4 -> 0 | I8: =IF(B8="si",(D8+F8+G8+H8)*$I$4,0) -> 0 | J8: =D8+F8+G8+H8+I8 -> 0 | K8: =J8*$K$4 -> 0 | L8: =(J8+K8)*C8 -> 0 | M8: =(J8+K8)*$M$4/(1-$M$4) -> 0 | N8: =M8+J8+K8 -> 0 | O8: =N8*C8 -> 0
B9: no | C9: 0 | D9: 0 | E9: =+D9*C9 -> 0 | F9: =IF(B9="si",D9*$F$4,0) -> 0 | G9: =(D9+F9)*$G$4 -> 0 | H9: =(D9+F9+G9)*$H$4 -> 0 | I9: =IF(B9="si",(D9+F9+G9+H9)*$I$4,0) -> 0 | J9: =D9+F9+G9+H9+I9 -> 0 | K9: =J9*$K$4 -> 0 | L9: =(J9+K9)*C9 -> 0 | M9: =(J9+K9)*$M$4/(1-$M$4) -> 0 | N9: =M9+J9+K9 -> 0 | O9: =N9*C9 -> 0
B10: no | C10: 0 | D10: 0 | E10: =+D10*C10 -> 0 | F10: =IF(B10="si",D10*$F$4,0) -> 0 | G10: =(D10+F10)*$G$4 -> 0 | H10: =(D10+F10+G10)*$H$4 -> 0 | I10: =IF(B10="si",(D10+F10+G10+H10)*$I$4,0) -> 0 | J10: =D10+F10+G10+H10+I10 -> 0 | K10: =J10*$K$4 -> 0 | L10: =(J10+K10)*C10 -> 0 | M10: =(J10+K10)*$M$4/(1-$M$4) -> 0 | N10: =M10+J10+K10 -> 0 | O10: =N10*C10 -> 0
B11: no | C11: 0 | D11: 0 | E11: =+D11*C11 -> 0 | F11: =IF(B11="si",D11*$F$4,0) -> 0 | G11: =(D11+F11)*$G$4 -> 0 | H11: =(D11+F11+G11)*$H$4 -> 0 | I11: =IF(B11="si",(D11+F11+G11+H11)*$I$4,0) -> 0 | J11: =D11+F11+G11+H11+I11 -> 0 | K11: =J11*$K$4 -> 0 | L11: =(J11+K11)*C11 -> 0 | M11: =(J11+K11)*$M$4/(1-$M$4) -> 0 | N11: =M11+J11+K11 -> 0 | O11: =N11*C11 -> 0
B12: no | C12: 0 | D12: 0 | E12: =+D12*C12 -> 0 | F12: =IF(B12="si",D12*$F$4,0) -> 0 | G12: =(D12+F12)*$G$4 -> 0 | H12: =(D12+F12+G12)*$H$4 -> 0 | I12: =IF(B12="si",(D12+F12+G12+H12)*$I$4,0) -> 0 | J12: =D12+F12+G12+H12+I12 -> 0 | K12: =J12*$K$4 -> 0 | L12: =(J12+K12)*C12 -> 0 | M12: =(J12+K12)*$M$4/(1-$M$4) -> 0 | N12: =M12+J12+K12 -> 0 | O12: =N12*C12 -> 0
B13: no | C13: 0 | D13: 0 | E13: =+D13*C13 -> 0 | F13: =IF(B13="si",D13*$F$4,0) -> 0 | G13: =(D13+F13)*$G$4 -> 0 | H13: =(D13+F13+G13)*$H$4 -> 0 | I13: =IF(B13="si",(D13+F13+G13+H13)*$I$4,0) -> 0 | J13: =D13+F13+G13+H13+I13 -> 0 | K13: =J13*$K$4 -> 0 | L13: =(J13+K13)*C13 -> 0 | M13: =(J13+K13)*$M$4/(1-$M$4) -> 0 | N13: =M13+J13+K13 -> 0 | O13: =N13*C13 -> 0
B14: no | C14: 0 | D14: 0 | E14: =+D14*C14 -> 0 | F14: =IF(B14="si",D14*$F$4,0) -> 0 | G14: =(D14+F14)*$G$4 -> 0 | H14: =(D14+F14+G14)*$H$4 -> 0 | I14: =IF(B14="si",(D14+F14+G14+H14)*$I$4,0) -> 0 | J14: =D14+F14+G14+H14+I14 -> 0 | K14: =J14*$K$4 -> 0 | L14: =(J14+K14)*C14 -> 0 | M14: =(J14+K14)*$M$4/(1-$M$4) -> 0 | N14: =M14+J14+K14 -> 0 | O14: =N14*C14 -> 0
B15: no | C15: 0 | D15: 0 | E15: =+D15*C15 -> 0 | F15: =IF(B15="si",D15*$F$4,0) -> 0 | G15: =(D15+F15)*$G$4 -> 0 | H15: =(D15+F15+G15)*$H$4 -> 0 | I15: =IF(B15="si",(D15+F15+G15+H15)*$I$4,0) -> 0 | J15: =D15+F15+G15+H15+I15 -> 0 | K15: =J15*$K$4 -> 0 | L15: =(J15+K15)*C15 -> 0 | M15: =(J15+K15)*$M$4/(1-$M$4) -> 0 | N15: =M15+J15+K15 -> 0 | O15: =N15*C15 -> 0
D17: Total FOB | E17: =SUM(E6:E15) -> 0 | J17: Costo Nac. | L17: =SUM(L6:L15) -> 0 | N17: Total Venta | O17: =SUM(O6:O15) -> 0
N18: UTILIDAD | O18: =O17-L17 -> 0
A20: IMPORTADO
A21: si
A22: no

Sheet Productos 3
A1: MATRIZ DE COSTO PROYECTO: | E1: =+Equipos!E1 -> 0
A3: Productos 3 | F3: Transporte | G3: Seguros | H3: IVA | I3: DAI | J3: Costo Untit | K3: Administración | L3: Costo total | M3: Margen GV | N3: Precio Venta | O3: Precio Venta
A4: Description | C4: Qty | D4: Costo Unit | E4: Costo Total | F4: 0.1 | G4: 0 | H4: 0.13 | I4: 0.14 | J4: Nacionalizado | K4: 0.03 | L4: Nacionaliado | M4: 0.3 | N4: Unitario | O4: Total
A5: Licencias | B5: IMPORTADO
B6: no | C6: 0 | D6: 0 | E6: =+D6*C6 -> 0 | F6: =IF(B6="si",D6*$F$4,0) -> 0 | G6: 0 | H6: =(D6+F6+G6)*$H$4 -> 0 | I6: =IF(B6="si",(D6+F6+G6+H6)*$I$4,0) -> 0 | J6: =D6+F6+G6+H6+I6 -> 0 | K6: =J6*$K$4 -> 0 | L6: =(J6+K6)*C6 -> 0 | M6: =(J6+K6)*$M$4/(1-$M$4) -> 0 | N6: =M6+J6+K6 -> 0 | O6: =N6*C6 -> 0
B7: no | C7: 0 | D7: 0 | E7: =+D7*C7 -> 0 | F7: =IF(B7="si",D7*$F$4,0) -> 0 | G7: =(D7+F7)*$G$4 -> 0 | H7: =(D7+F7+G7)*$H$4 -> 0 | I7: =IF(B7="si",(D7+F7+G7+H7)*$I$4,0) -> 0 | J7: =D7+F7+G7+H7+I7 -> 0 | K7: =J7*$K$4 -> 0 | L7: =(J7+K7)*C7 -> 0 | M7: =(J7+K7)*$M$4/(1-$M$4) -> 0 | N7: =M7+J7+K7 -> 0 | O7: =N7*C7 -> 0
B8: no | C8: 0 | D8: 0 | E8: =+D8*C8 -> 0 | F8: =IF(B8="si",D8*$F$4,0) -> 0 | G8: =(D8+F8)*$G$4 -> 0 | H8: =(D8+F8+G8)*$H$4 -> 0 | I8: =IF(B8="si",(D8+F8+G8+H8)*$I$4,0) -> 0 | J8: =D8+F8+G8+H8+I8 -> 0 | K8: =J8*$K$4 -> 0 | L8: =(J8+K8)*C8 -> 0 | M8: =(J8+K8)*$M$4/(1-$M$4) -> 0 | N8: =M8+J8+K8 -> 0 | O8: =N8*C8 -> 0
B9: no | C9: 0 | D9: 0 | E9: =+D9*C9 -> 0 | F9: =IF(B9="si",D9*$F$4,0) -> 0 | G9: =(D9+F9)*$G$4 -> 0 | H9: =(D9+F9+G9)*$H$4 -> 0 | I9: =IF(B9="si",(D9+F9+G9+H9)*$I$4,0) -> 0 | J9: =D9+F9+G9+H9+I9 -> 0 | K9: =J9*$K$4 -> 0 | L9: =(J9+K9)*C9 -> 0 | M9: =(J9+K9)*$M$4/(1-$M$4) -> 0 | N9: =M9+J9+K9 -> 0 | O9: =N9*C9 -> 0
B10: no | C10: 0 | D10: 0 | E10: =+D10*C10 -> 0 | F10: =IF(B10="si",D10*$F$4,0) -> 0 | G10: =(D10+F10)*$G$4 -> 0 | H10: =(D10+F10+G10)*$H$4 -> 0 | I10: =IF(B10="si",(D10+F10+G10+H10)*$I$4,0) -> 0 | J10: =D10+F10+G10+H10+I10 -> 0 | K10: =J10*$K$4 -> 0 | L10: =(J10+K10)*C10 -> 0 | M10: =(J10+K10)*$M$4/(1-$M$4) -> 0 | N10: =M10+J10+K10 -> 0 | O10: =N10*C10 -> 0
B11: no | C11: 0 | D11: 0 | E11: =+D11*C11 -> 0 | F11: =IF(B11="si",D11*$F$4,0) -> 0 | G11: =(D11+F11)*$G$4 -> 0 | H11: =(D11+F11+G11)*$H$4 -> 0 | I11: =IF(B11="si",(D11+F11+G11+H11)*$I$4,0) -> 0 | J11: =D11+F11+G11+H11+I11 -> 0 | K11: =J11*$K$4 -> 0 | L11: =(J11+K11)*C11 -> 0 | M11: =(J11+K11)*$M$4/(1-$M$4) -> 0 | N11: =M11+J11+K11 -> 0 | O11: =N11*C11 -> 0
B12: no | C12: 0 | D12: 0 | E12: =+D12*C12 -> 0 | F12: =IF(B12="si",D12*$F$4,0) -> 0 | G12: =(D12+F12)*$G$4 -> 0 | H12: =(D12+F12+G12)*$H$4 -> 0 | I12: =IF(B12="si",(D12+F12+G12+H12)*$I$4,0) -> 0 | J12: =D12+F12+G12+H12+I12 -> 0 | K12: =J12*$K$4 -> 0 | L12: =(J12+K12)*C12 -> 0 | M12: =(J12+K12)*$M$4/(1-$M$4) -> 0 | N12: =M12+J12+K12 -> 0 | O12: =N12*C12 -> 0
A13: Servidores
B14: no | C14: 0 | D14: 0 | E14: =+C14*D14*(1-C23) -> 0 | F14: =IF(B14="si",D14*$F$4,0) -> 0 | G14: =(D14+F14)*$G$4 -> 0 | H14: =(D14+F14+G14)*$H$4 -> 0 | I14: =IF(B14="si",(D14+F14+G14+H14)*$I$4,0) -> 0 | J14: =D14+F14+G14+H14+I14 -> 0 | K14: =J14*$K$4 -> 0 | L14: =(J14+K14)*C14 -> 0 | M14: =(J14+K14)*$M$4/(1-$M$4) -> 0 | N14: =M14+J14+K14 -> 0 | O14: =N14*C14 -> 0
B15: no | C15: 0 | D15: 0 | E15: =+C15*D15 -> 0 | F15: =IF(B15="si",D15*$F$4,0) -> 0 | G15: =(D15+F15)*$G$4 -> 0 | H15: =(D15+F15+G15)*$H$4 -> 0 | I15: =IF(B15="si",(D15+F15+G15+H15)*$I$4,0) -> 0 | J15: =D15+F15+G15+H15+I15 -> 0 | K15: =J15*$K$4 -> 0 | L15: =(J15+K15)*C15 -> 0 | M15: =(J15+K15)*$M$4/(1-$M$4) -> 0 | N15: =M15+J15+K15 -> 0 | O15: =N15*C15 -> 0
B16: no | C16: 0 | D16: 0 | E16: =+C16*D16 -> 0 | F16: =IF(B16="si",D16*$F$4,0) -> 0 | G16: =(D16+F16)*$G$4 -> 0 | H16: =(D16+F16+G16)*$H$4 -> 0 | I16: =IF(B16="si",(D16+F16+G16+H16)*$I$4,0) -> 0 | J16: =D16+F16+G16+H16+I16 -> 0 | K16: =J16*$K$4 -> 0 | L16: =(J16+K16)*C16 -> 0 | M16: =(J16+K16)*$M$4/(1-$M$4) -> 0 | N16: =M16+J16+K16 -> 0 | O16: =N16*C16 -> 0
B17: no | C17: 0 | D17: 0 | E17: =+C17*D17 -> 0 | F17: =IF(B17="si",D17*$F$4,0) -> 0 | G17: =(D17+F17)*$G$4 -> 0 | H17: =(D17+F17+G17)*$H$4 -> 0 | I17: =IF(B17="si",(D17+F17+G17+H17)*$I$4,0) -> 0 | J17: =D17+F17+G17+H17+I17 -> 0 | K17: =J17*$K$4 -> 0 | L17: =(J17+K17)*C17 -> 0 | M17: =(J17+K17)*$M$4/(1-$M$4) -> 0 | N17: =M17+J17+K17 -> 0 | O17: =N17*C17 -> 0
B18: no | C18: 0 | D18: 0 | E18: =+C18*D18 -> 0 | F18: =IF(B18="si",D18*$F$4,0) -> 0 | G18: =(D18+F18)*$G$4 -> 0 | H18: =(D18+F18+G18)*$H$4 -> 0 | I18: =IF(B18="si",(D18+F18+G18+H18)*$I$4,0) -> 0 | J18: =D18+F18+G18+H18+I18 -> 0 | K18: =J18*$K$4 -> 0 | L18: =(J18+K18)*C18 -> 0 | M18: =(J18+K18)*$M$4/(1-$M$4) -> 0 | N18: =M18+J18+K18 -> 0 | O18: =N18*C18 -> 0
A19: Sección 3
B20: no | C20: 0 | D20: 0 | E20: =+C20*D20 -> 0 | F20: =IF(B20="si",D20*$F$4,0) -> 0 | G20: =(D20+F20)*$G$4 -> 0 | H20: =(D20+F20+G20)*$H$4 -> 0 | I20: =IF(B20="si",(D20+F20+G20+H20)*$I$4,0) -> 0 | J20: =D20+F20+G20+H20+I20 -> 0 | K20: =J20*$K$4 -> 0 | L20: =(J20+K20)*C20 -> 0 | M20: =(J20+K20)*$M$4/(1-$M$4) -> 0 | N20: =M20+J20+K20 -> 0 | O20: =N20*C20 -> 0
D22: Total FOB | E22: =SUM(E6:E20) -> 0 | J22: Costo Nac. | L22: =SUM(L6:L20) -> 0 | N22: Total Venta | O22: =SUM(O6:O20) -> 0
N23: UTILIDAD | O23: =O22-L22 -> 0
A25: IMPORTADO
A26: si
A27: no

Sheet Productos 4
A1: MATRIZ DE COSTO PROYECTO: | E1: =+Equipos!E1 -> 0
A3: Productos 4 | F3: Transporte | G3: Seguros | H3: IVA | I3: DAI | J3: Costo Untit | K3: Administración | L3: Costo total | M3: Margen GV | N3: Precio Venta | O3: Precio Venta
A4: Description | C4: Qty | D4: Costo Unit | E4: Costo Total | F4: 0.1 | G4: 0 | H4: 0.13 | I4: 0.14 | J4: Nacionalizado | K4: 0.03 | L4: Nacionaliado | M4: 0.3 | N4: Unitario | O4: Total
A5: Sección 1 | B5: IMPORTADO
B6: no | C6: 0 | D6: 0 | E6: =+D6*C6 -> 0 | F6: =IF(B6="si",D6*$F$4,0) -> 0 | G6: =(D6+F6)*$G$4 -> 0 | H6: =(D6+F6+G6)*$H$4 -> 0 | I6: =IF(B6="si",(D6+F6+G6+H6)*$I$4,0) -> 0 | J6: =D6+F6+G6+H6+I6 -> 0 | K6: =J6*$K$4 -> 0 | L6: =(J6+K6)*C6 -> 0 | M6: =(J6+K6)*$M$4/(1-$M$4) -> 0 | N6: =M6+J6+K6 -> 0 | O6: =N6*C6 -> 0
B7: no | C7: 0 | D7: 0 | E7: =+D7*C7 -> 0 | F7: =IF(B7="si",D7*$F$4,0) -> 0 | G7: =(D7+F7)*$G$4 -> 0 | H7: =(D7+F7+G7)*$H$4 -> 0 | I7: =IF(B7="si",(D7+F7+G7+H7)*$I$4,0) -> 0 | J7: =D7+F7+G7+H7+I7 -> 0 | K7: =J7*$K$4 -> 0 | L7: =(J7+K7)*C7 -> 0 | M7: =(J7+K7)*$M$4/(1-$M$4) -> 0 | N7: =M7+J7+K7 -> 0 | O7: =N7*C7 -> 0
B8: no | C8: 0 | D8: 0 | E8: =+D8*C8 -> 0 | F8: =IF(B8="si",D8*$F$4,0) -> 0 | G8: =(D8+F8)*$G$4 -> 0 | H8: =(D8+F8+G8)*$H$4 -> 0 | I8: =IF(B8="si",(D8+F8+G8+H8)*$I$4,0) -> 0 | J8: =D8+F8+G8+H8+I8 -> 0 | K8: =J8*$K$4 -> 0 | L8: =(J8+K8)*C8 -> 0 | M8: =(J8+K8)*$M$4/(1-$M$4) -> 0 | N8: =M8+J8+K8 -> 0 | O8: =N8*C8 -> 0
B9: no | C9: 0 | D9: 0 | E9: =+D9*C9 -> 0 | F9: =IF(B9="si",D9*$F$4,0) -> 0 | G9: =(D9+F9)*$G$4 -> 0 | H9: =(D9+F9+G9)*$H$4 -> 0 | I9: =IF(B9="si",(D9+F9+G9+H9)*$I$4,0) -> 0 | J9: =D9+F9+G9+H9+I9 -> 0 | K9: =J9*$K$4 -> 0 | L9: =(J9+K9)*C9 -> 0 | M9: =(J9+K9)*$M$4/(1-$M$4) -> 0 | N9: =M9+J9+K9 -> 0 | O9: =N9*C9 -> 0
B10: no | C10: 0 | D10: 0 | E10: =+D10*C10 -> 0 | F10: =IF(B10="si",D10*$F$4,0) -> 0 | G10: =(D10+F10)*$G$4 -> 0 | H10: =(D10+F10+G10)*$H$4 -> 0 | I10: =IF(B10="si",(D10+F10+G10+H10)*$I$4,0) -> 0 | J10: =D10+F10+G10+H10+I10 -> 0 | K10: =J10*$K$4 -> 0 | L10: =(J10+K10)*C10 -> 0 | M10: =(J10+K10)*$M$4/(1-$M$4) -> 0 | N10: =M10+J10+K10 -> 0 | O10: =N10*C10 -> 0
B11: no | C11: 0 | D11: 0 | E11: =+D11*C11 -> 0 | F11: =IF(B11="si",D11*$F$4,0) -> 0 | G11: =(D11+F11)*$G$4 -> 0 | H11: =(D11+F11+G11)*$H$4 -> 0 | I11: =IF(B11="si",(D11+F11+G11+H11)*$I$4,0) -> 0 | J11: =D11+F11+G11+H11+I11 -> 0 | K11: =J11*$K$4 -> 0 | L11: =(J11+K11)*C11 -> 0 | M11: =(J11+K11)*$M$4/(1-$M$4) -> 0 | N11: =M11+J11+K11 -> 0 | O11: =N11*C11 -> 0
A12: Sección 2
B13: no | C13: 0 | D13: 0 | E13: =+C13*D13*(1-C22) -> 0 | F13: =IF(B13="si",D13*$F$4,0) -> 0 | G13: =(D13+F13)*$G$4 -> 0 | H13: =(D13+F13+G13)*$H$4 -> 0 | I13: =IF(B13="si",(D13+F13+G13+H13)*$I$4,0) -> 0 | J13: =D13+F13+G13+H13+I13 -> 0 | K13: =J13*$K$4 -> 0 | L13: =(J13+K13)*C13 -> 0 | M13: =(J13+K13)*$M$4/(1-$M$4) -> 0 | N13: =M13+J13+K13 -> 0 | O13: =N13*C13 -> 0
B14: no | C14: 0 | D14: 0 | E14: =+C14*D14 -> 0 | F14: =IF(B14="si",D14*$F$4,0) -> 0 | G14: =(D14+F14)*$G$4 -> 0 | H14: =(D14+F14+G14)*$H$4 -> 0 | I14: =IF(B14="si",(D14+F14+G14+H14)*$I$4,0) -> 0 | J14: =D14+F14+G14+H14+I14 -> 0 | K14: =J14*$K$4 -> 0 | L14: =(J14+K14)*C14 -> 0 | M14: =(J14+K14)*$M$4/(1-$M$4) -> 0 | N14: =M14+J14+K14 -> 0 | O14: =N14*C14 -> 0
B15: no | C15: 0 | D15: 0 | E15: =+C15*D15 -> 0 | F15: =IF(B15="si",D15*$F$4,0) -> 0 | G15: =(D15+F15)*$G$4 -> 0 | H15: =(D15+F15+G15)*$H$4 -> 0 | I15: =IF(B15="si",(D15+F15+G15+H15)*$I$4,0) -> 0 | J15: =D15+F15+G15+H15+I15 -> 0 | K15: =J15*$K$4 -> 0 | L15: =(J15+K15)*C15 -> 0 | M15: =(J15+K15)*$M$4/(1-$M$4) -> 0 | N15: =M15+J15+K15 -> 0 | O15: =N15*C15 -> 0
B16: no | C16: 0 | D16: 0 | E16: =+C16*D16 -> 0 | F16: =IF(B16="si",D16*$F$4,0) -> 0 | G16: =(D16+F16)*$G$4 -> 0 | H16: =(D16+F16+G16)*$H$4 -> 0 | I16: =IF(B16="si",(D16+F16+G16+H16)*$I$4,0) -> 0 | J16: =D16+F16+G16+H16+I16 -> 0 | K16: =J16*$K$4 -> 0 | L16: =(J16+K16)*C16 -> 0 | M16: =(J16+K16)*$M$4/(1-$M$4) -> 0 | N16: =M16+J16+K16 -> 0 | O16: =N16*C16 -> 0
B17: no | C17: 0 | D17: 0 | E17: =+C17*D17 -> 0 | F17: =IF(B17="si",D17*$F$4,0) -> 0 | G17: =(D17+F17)*$G$4 -> 0 | H17: =(D17+F17+G17)*$H$4 -> 0 | I17: =IF(B17="si",(D17+F17+G17+H17)*$I$4,0) -> 0 | J17: =D17+F17+G17+H17+I17 -> 0 | K17: =J17*$K$4 -> 0 | L17: =(J17+K17)*C17 -> 0 | M17: =(J17+K17)*$M$4/(1-$M$4) -> 0 | N17: =M17+J17+K17 -> 0 | O17: =N17*C17 -> 0
A18: Sección 3
B19: no | C19: 0 | D19: 0 | E19: =+C19*D19 -> 0 | F19: =IF(B19="si",D19*$F$4,0) -> 0 | G19: =(D19+F19)*$G$4 -> 0 | H19: =(D19+F19+G19)*$H$4 -> 0 | I19: =IF(B19="si",(D19+F19+G19+H19)*$I$4,0) -> 0 | J19: =D19+F19+G19+H19+I19 -> 0 | K19: =J19*$K$4 -> 0 | L19: =(J19+K19)*C19 -> 0 | M19: =(J19+K19)*$M$4/(1-$M$4) -> 0 | N19: =M19+J19+K19 -> 0 | O19: =N19*C19 -> 0
D21: Total FOB | E21: =SUM(E6:E19) -> 0 | J21: Costo Nac. | L21: =SUM(L6:L19) -> 0 | N21: Total Venta | O21: =SUM(O6:O19) -> 0
N22: UTILIDAD | O22: =O21-L21 -> 0
A24: IMPORTADO
A25: si
A26: no

Sheet Productos 5
A1: MATRIZ DE COSTO PROYECTO: | E1: =+Equipos!E1 -> 0
A3: Productos 5 | F3: Transporte | G3: Seguros | H3: IVA | I3: DAI | J3: Costo Untit | K3: Administración | L3: Costo total | M3: Margen GV | N3: Precio Venta | O3: Precio Venta
A4: Description | C4: Qty | D4: Costo Unit | E4: Costo Total | F4: 0.1 | G4: 0 | H4: 0.13 | I4: 0.14 | J4: Nacionalizado | K4: 0.03 | L4: Nacionaliado | M4: 0.3 | N4: Unitario | O4: Total
A5: SERVERS | B5: IMPORTADO
B6: no | C6: 0 | D6: 0 | E6: =+D6*C6 -> 0 | F6: =IF(B6="si",D6*$F$4,0) -> 0 | G6: 0 | H6: =(D6+F6+G6)*$H$4 -> 0 | I6: =IF(B6="si",(D6+F6+G6+H6)*$I$4,0) -> 0 | J6: =D6+F6+G6+H6+I6 -> 0 | K6: =J6*$K$4 -> 0 | L6: =(J6+K6)*C6 -> 0 | M6: =(J6+K6)*$M$4/(1-$M$4) -> 0 | N6: =M6+J6+K6 -> 0 | O6: =N6*C6 -> 0
B7: no | C7: 0 | D7: 0 | E7: =+D7*C7 -> 0 | F7: =IF(B7="si",D7*$F$4,0) -> 0 | G7: =(D7+F7)*$G$4 -> 0 | H7: =(D7+F7+G7)*$H$4 -> 0 | I7: =IF(B7="si",(D7+F7+G7+H7)*$I$4,0) -> 0 | J7: =D7+F7+G7+H7+I7 -> 0 | K7: =J7*$K$4 -> 0 | L7: =(J7+K7)*C7 -> 0 | M7: =(J7+K7)*$M$4/(1-$M$4) -> 0 | N7: =M7+J7+K7 -> 0 | O7: =N7*C7 -> 0
B8: no | C8: 0 | D8: 0 | E8: =+D8*C8 -> 0 | F8: =IF(B8="si",D8*$F$4,0) -> 0 | G8: =(D8+F8)*$G$4 -> 0 | H8: =(D8+F8+G8)*$H$4 -> 0 | I8: =IF(B8="si",(D8+F8+G8+H8)*$I$4,0) -> 0 | J8: =D8+F8+G8+H8+I8 -> 0 | K8: =J8*$K$4 -> 0 | L8: =(J8+K8)*C8 -> 0 | M8: =(J8+K8)*$M$4/(1-$M$4) -> 0 | N8: =M8+J8+K8 -> 0 | O8: =N8*C8 -> 0
B9: no | C9: 0 | D9: 0 | E9: =+D9*C9 -> 0 | F9: =IF(B9="si",D9*$F$4,0) -> 0 | G9: =(D9+F9)*$G$4 -> 0 | H9: =(D9+F9+G9)*$H$4 -> 0 | I9: =IF(B9="si",(D9+F9+G9+H9)*$I$4,0) -> 0 | J9: =D9+F9+G9+H9+I9 -> 0 | K9: =J9*$K$4 -> 0 | L9: =(J9+K9)*C9 -> 0 | M9: =(J9+K9)*$M$4/(1-$M$4) -> 0 | N9: =M9+J9+K9 -> 0 | O9: =N9*C9 -> 0
B10: no | C10: 0 | D10: 0 | E10: =+D10*C10 -> 0 | F10: =IF(B10="si",D10*$F$4,0) -> 0 | G10: =(D10+F10)*$G$4 -> 0 | H10: =(D10+F10+G10)*$H$4 -> 0 | I10: =IF(B10="si",(D10+F10+G10+H10)*$I$4,0) -> 0 | J10: =D10+F10+G10+H10+I10 -> 0 | K10: =J10*$K$4 -> 0 | L10: =(J10+K10)*C10 -> 0 | M10: =(J10+K10)*$M$4/(1-$M$4) -> 0 | N10: =M10+J10+K10 -> 0 | O10: =N10*C10 -> 0
B11: no | C11: 0 | D11: 0 | E11: =+D11*C11 -> 0 | F11: =IF(B11="si",D11*$F$4,0) -> 0 | G11: =(D11+F11)*$G$4 -> 0 | H11: =(D11+F11+G11)*$H$4 -> 0 | I11: =IF(B11="si",(D11+F11+G11+H11)*$I$4,0) -> 0 | J11: =D11+F11+G11+H11+I11 -> 0 | K11: =J11*$K$4 -> 0 | L11: =(J11+K11)*C11 -> 0 | M11: =(J11+K11)*$M$4/(1-$M$4) -> 0 | N11: =M11+J11+K11 -> 0 | O11: =N11*C11 -> 0
A12: Sección 2
B13: no | C13: 0 | D13: 0 | E13: =+C13*D13 -> 0 | F13: =IF(B13="si",D13*$F$4,0) -> 0 | G13: =(D13+F13)*$G$4 -> 0 | H13: =(D13+F13+G13)*$H$4 -> 0 | I13: =IF(B13="si",(D13+F13+G13+H13)*$I$4,0) -> 0 | J13: =D13+F13+G13+H13+I13 -> 0 | K13: =J13*$K$4 -> 0 | L13: =(J13+K13)*C13 -> 0 | M13: =(J13+K13)*$M$4/(1-$M$4) -> 0 | N13: =M13+J13+K13 -> 0 | O13: =N13*C13 -> 0
B14: no | C14: 0 | D14: 0 | E14: =+C14*D14 -> 0 | F14: =IF(B14="si",D14*$F$4,0) -> 0 | G14: =(D14+F14)*$G$4 -> 0 | H14: =(D14+F14+G14)*$H$4 -> 0 | I14: =IF(B14="si",(D14+F14+G14+H14)*$I$4,0) -> 0 | J14: =D14+F14+G14+H14+I14 -> 0 | K14: =J14*$K$4 -> 0 | L14: =(J14+K14)*C14 -> 0 | M14: =(J14+K14)*$M$4/(1-$M$4) -> 0 | N14: =M14+J14+K14 -> 0 | O14: =N14*C14 -> 0
B15: no | C15: 0 | D15: 0 | E15: =+C15*D15 -> 0 | F15: =IF(B15="si",D15*$F$4,0) -> 0 | G15: =(D15+F15)*$G$4 -> 0 | H15: =(D15+F15+G15)*$H$4 -> 0 | I15: =IF(B15="si",(D15+F15+G15+H15)*$I$4,0) -> 0 | J15: =D15+F15+G15+H15+I15 -> 0 | K15: =J15*$K$4 -> 0 | L15: =(J15+K15)*C15 -> 0 | M15: =(J15+K15)*$M$4/(1-$M$4) -> 0 | N15: =M15+J15+K15 -> 0 | O15: =N15*C15 -> 0
B16: no | C16: 0 | D16: 0 | E16: =+C16*D16 -> 0 | F16: =IF(B16="si",D16*$F$4,0) -> 0 | G16: =(D16+F16)*$G$4 -> 0 | H16: =(D16+F16+G16)*$H$4 -> 0 | I16: =IF(B16="si",(D16+F16+G16+H16)*$I$4,0) -> 0 | J16: =D16+F16+G16+H16+I16 -> 0 | K16: =J16*$K$4 -> 0 | L16: =(J16+K16)*C16 -> 0 | M16: =(J16+K16)*$M$4/(1-$M$4) -> 0 | N16: =M16+J16+K16 -> 0 | O16: =N16*C16 -> 0
B17: no | C17: 0 | D17: 0 | E17: =+C17*D17 -> 0 | F17: =IF(B17="si",D17*$F$4,0) -> 0 | G17: =(D17+F17)*$G$4 -> 0 | H17: =(D17+F17+G17)*$H$4 -> 0 | I17: =IF(B17="si",(D17+F17+G17+H17)*$I$4,0) -> 0 | J17: =D17+F17+G17+H17+I17 -> 0 | K17: =J17*$K$4 -> 0 | L17: =(J17+K17)*C17 -> 0 | M17: =(J17+K17)*$M$4/(1-$M$4) -> 0 | N17: =M17+J17+K17 -> 0 | O17: =N17*C17 -> 0
B18: no | C18: 0 | D18: 0 | E18: =+C18*D18 -> 0 | F18: =IF(B18="si",D18*$F$4,0) -> 0 | G18: =(D18+F18)*$G$4 -> 0 | H18: =(D18+F18+G18)*$H$4 -> 0 | I18: =IF(B18="si",(D18+F18+G18+H18)*$I$4,0) -> 0 | J18: =D18+F18+G18+H18+I18 -> 0 | K18: =J18*$K$4 -> 0 | L18: =(J18+K18)*C18 -> 0 | M18: =(J18+K18)*$M$4/(1-$M$4) -> 0 | N18: =M18+J18+K18 -> 0 | O18: =N18*C18 -> 0
B19: no | C19: 0 | D19: 0 | E19: =+C19*D19 -> 0 | F19: =IF(B19="si",D19*$F$4,0) -> 0 | G19: =(D19+F19)*$G$4 -> 0 | H19: =(D19+F19+G19)*$H$4 -> 0 | I19: =IF(B19="si",(D19+F19+G19+H19)*$I$4,0) -> 0 | J19: =D19+F19+G19+H19+I19 -> 0 | K19: =J19*$K$4 -> 0 | L19: =(J19+K19)*C19 -> 0 | M19: =(J19+K19)*$M$4/(1-$M$4) -> 0 | N19: =M19+J19+K19 -> 0 | O19: =N19*C19 -> 0
B20: no | C20: 0 | D20: 0 | E20: =+C20*D20 -> 0 | F20: =IF(B20="si",D20*$F$4,0) -> 0 | G20: =(D20+F20)*$G$4 -> 0 | H20: =(D20+F20+G20)*$H$4 -> 0 | I20: =IF(B20="si",(D20+F20+G20+H20)*$I$4,0) -> 0 | J20: =D20+F20+G20+H20+I20 -> 0 | K20: =J20*$K$4 -> 0 | L20: =(J20+K20)*C20 -> 0 | M20: =(J20+K20)*$M$4/(1-$M$4) -> 0 | N20: =M20+J20+K20 -> 0 | O20: =N20*C20 -> 0
B21: no | C21: 0 | D21: 0 | E21: =+C21*D21 -> 0 | F21: =IF(B21="si",D21*$F$4,0) -> 0 | G21: =(D21+F21)*$G$4 -> 0 | H21: =(D21+F21+G21)*$H$4 -> 0 | I21: =IF(B21="si",(D21+F21+G21+H21)*$I$4,0) -> 0 | J21: =D21+F21+G21+H21+I21 -> 0 | K21: =J21*$K$4 -> 0 | L21: =(J21+K21)*C21 -> 0 | M21: =(J21+K21)*$M$4/(1-$M$4) -> 0 | N21: =M21+J21+K21 -> 0 | O21: =N21*C21 -> 0
A22: Sección 3
B23: no | C23: 0 | D23: 0 | E23: =+C23*D23 -> 0 | F23: =IF(B23="si",D23*$F$4,0) -> 0 | G23: =(D23+F23)*$G$4 -> 0 | H23: =(D23+F23+G23)*$H$4 -> 0 | I23: =IF(B23="si",(D23+F23+G23+H23)*$I$4,0) -> 0 | J23: =D23+F23+G23+H23+I23 -> 0 | K23: =J23*$K$4 -> 0 | L23: =(J23+K23)*C23 -> 0 | M23: =(J23+K23)*$M$4/(1-$M$4) -> 0 | N23: =M23+J23+K23 -> 0 | O23: =N23*C23 -> 0
D25: Total FOB | E25: =SUM(E6:E23) -> 0 | J25: Costo Nac. | L25: =SUM(L6:L23) -> 0 | N25: Total Venta | O25: =SUM(O6:O23) -> 0
N26: UTILIDAD | O26: =O25-L25 -> 0
A28: IMPORTADO
A29: si
A30: no

Sheet MATERIALES
A1: MATRIZ DE COSTO PROYECTO:
A3: Materiales | F3: Transporte | G3: Seguros | H3: IVA | I3: DAI | J3: Costo Untit | K3: Administración | L3: Costo total | M3: Margen GV | N3: Precio Venta | O3: Precio Venta | P3: Financ.
A4: Description | C4: Qty | D4: Costo Unit | E4: Costo Total | F4: 0.1 | G4: 0 | H4: 0.13 | I4: 0.14 | J4: Nacionalizado | K4: 0.03 | L4: Nacionaliado | M4: 0.3 | N4: Unitario | O4: Total
A5: Sección 1 | B5: IMPORTADO
A6: caja nema para SENSORES | B6: si | C6: 0 | D6: 0 | E6: =+D6*C6 -> 0 | F6: =IF(B6="si",D6*$F$4,0) -> 0 | G6: 0 | H6: =(D6+F6+G6)*$H$4 -> 0 | I6: =IF(B6="si",(D6+F6+G6+H6)*$I$4,0) -> 0 | J6: =D6+F6+G6+H6+I6 -> 0 | K6: =J6*$K$4 -> 0 | L6: =(J6+K6)*C6 -> 0 | M6: =(J6+K6)*$M$4/(1-$M$4) -> 0 | N6: =M6+J6+K6 -> 0 | O6: =N6*C6 -> 0
A7: Cable UTP cat6A Exteriores caja | B7: si | C7: 0 | D7: 0 | E7: =+D7*C7 -> 0 | F7: =IF(B7="si",D7*$F$4,0) -> 0 | G7: =(D7+F7)*$G$4 -> 0 | H7: =(D7+F7+G7)*$H$4 -> 0 | I7: =IF(B7="si",(D7+F7+G7+H7)*$I$4,0) -> 0 | J7: =D7+F7+G7+H7+I7 -> 0 | K7: =J7*$K$4 -> 0 | L7: =(J7+K7)*C7 -> 0 | M7: =(J7+K7)*$M$4/(1-$M$4) -> 0 | N7: =M7+J7+K7 -> 0 | O7: =N7*C7 -> 0
A8: Cable UTP cat6A Exteriores | B8: si | C8: 0 | D8: 0 | E8: =+D8*C8 -> 0 | F8: =IF(B8="si",D8*$F$4,0) -> 0 | G8: =(D8+F8)*$G$4 -> 0 | H8: =(D8+F8+G8)*$H$4 -> 0 | I8: =IF(B8="si",(D8+F8+G8+H8)*$I$4,0) -> 0 | J8: =D8+F8+G8+H8+I8 -> 0 | K8: =J8*$K$4 -> 0 | L8: =(J8+K8)*C8 -> 0 | M8: =(J8+K8)*$M$4/(1-$M$4) -> 0 | N8: =M8+J8+K8 -> 0 | O8: =N8*C8 -> 0
A9: conectores rj45 cat 6 | B9: si | C9: 0 | D9: 0 | E9: =+D9*C9 -> 0 | F9: =IF(B9="si",D9*$F$4,0) -> 0 | H9: =(D9+F9+G9)*$H$4 -> 0 | I9: =IF(B9="si",(D9+F9+G9+H9)*$I$4,0) -> 0 | J9: =D9+F9+G9+H9+I9 -> 0 | K9: =J9*$K$4 -> 0 | L9: =(J9+K9)*C9 -> 0 | M9: =(J9+K9)*$M$4/(1-$M$4) -> 0 | N9: =M9+J9+K9 -> 0 | O9: =N9*C9 -> 0
A10: cable electrico #12 rojo | B10: si | C10: 0 | D10: 0 | E10: =+D10*C10 -> 0 | F10: =IF(B10="si",D10*$F$4,0) -> 0 | G10: =(D10+F10)*$G$4 -> 0 | H10: =(D10+F10+G10)*$H$4 -> 0 | I10: =IF(B10="si",(D10+F10+G10+H10)*$I$4,0) -> 0 | J10: =D10+F10+G10+H10+I10 -> 0 | K10: =J10*$K$4 -> 0 | L10: =(J10+K10)*C10 -> 0 | M10: =(J10+K10)*$M$4/(1-$M$4) -> 0 | N10: =M10+J10+K10 -> 0 | O10: =N10*C10 -> 0
A11: cable electrico #12 blanco | B11: si | C11: 0 | D11: 0 | E11: =+D11*C11 -> 0 | F11: =IF(B11="si",D11*$F$4,0) -> 0 | G11: =(D11+F11)*$G$4 -> 0 | H11: =(D11+F11+G11)*$H$4 -> 0 | I11: =IF(B11="si",(D11+F11+G11+H11)*$I$4,0) -> 0 | J11: =D11+F11+G11+H11+I11 -> 0 | K11: =J11*$K$4 -> 0 | L11: =(J11+K11)*C11 -> 0 | M11: =(J11+K11)*$M$4/(1-$M$4) -> 0 | N11: =M11+J11+K11 -> 0 | O11: =N11*C11 -> 0
A12: cable electrico #12 verde | B12: si | C12: 0 | D12: 0 | E12: =+D12*C12 -> 0 | F12: =IF(B12="si",D12*$F$4,0) -> 0 | G12: =(D12+F12)*$G$4 -> 0 | H12: =(D12+F12+G12)*$H$4 -> 0 | I12: =IF(B12="si",(D12+F12+G12+H12)*$I$4,0) -> 0 | J12: =D12+F12+G12+H12+I12 -> 0 | K12: =J12*$K$4 -> 0 | L12: =(J12+K12)*C12 -> 0 | M12: =(J12+K12)*$M$4/(1-$M$4) -> 0 | N12: =M12+J12+K12 -> 0 | O12: =N12*C12 -> 0
A13: tomas de parche | B13: si | C13: 0 | D13: 0 | E13: =+D13*C13 -> 0 | F13: =IF(B13="si",D13*$F$4,0) -> 0 | G13: =(D13+F13)*$G$4 -> 0 | H13: =(D13+F13+G13)*$H$4 -> 0 | I13: =IF(B13="si",(D13+F13+G13+H13)*$I$4,0) -> 0 | J13: =D13+F13+G13+H13+I13 -> 0 | K13: =J13*$K$4 -> 0 | L13: =(J13+K13)*C13 -> 0 | M13: =(J13+K13)*$M$4/(1-$M$4) -> 0 | N13: =M13+J13+K13 -> 0 | O13: =N13*C13 -> 0
A14: tape 3m | B14: si | C14: 0 | D14: 0 | E14: =+D14*C14 -> 0 | F14: =IF(B14="si",D14*$F$4,0) -> 0 | G14: =(D14+F14)*$G$4 -> 0 | H14: =(D14+F14+G14)*$H$4 -> 0 | I14: =IF(B14="si",(D14+F14+G14+H14)*$I$4,0) -> 0 | J14: =D14+F14+G14+H14+I14 -> 0 | K14: =J14*$K$4 -> 0 | L14: =(J14+K14)*C14 -> 0 | M14: =(J14+K14)*$M$4/(1-$M$4) -> 0 | N14: =M14+J14+K14 -> 0 | O14: =N14*C14 -> 0
A15: regleta | B15: si | C15: 0 | D15: 0 | E15: =+D15*C15 -> 0 | F15: =IF(B15="si",D15*$F$4,0) -> 0 | G15: =(D15+F15)*$G$4 -> 0 | H15: =(D15+F15+G15)*$H$4 -> 0 | I15: =IF(B15="si",(D15+F15+G15+H15)*$I$4,0) -> 0 | J15: =D15+F15+G15+H15+I15 -> 0 | K15: =J15*$K$4 -> 0 | L15: =(J15+K15)*C15 -> 0 | M15: =(J15+K15)*$M$4/(1-$M$4) -> 0 | N15: =M15+J15+K15 -> 0 | O15: =N15*C15 -> 0
A16: Breaker 20A | B16: si | C16: 0 | D16: 0 | E16: =+D16*C16 -> 0 | F16: =IF(B16="si",D16*$F$4,0) -> 0 | G16: =(D16+F16)*$G$4 -> 0 | H16: =(D16+F16+G16)*$H$4 -> 0 | I16: =IF(B16="si",(D16+F16+G16+H16)*$I$4,0) -> 0 | J16: =D16+F16+G16+H16+I16 -> 0 | K16: =J16*$K$4 -> 0 | L16: =(J16+K16)*C16 -> 0 | M16: =(J16+K16)*$M$4/(1-$M$4) -> 0 | N16: =M16+J16+K16 -> 0 | O16: =N16*C16 -> 0
A17: Tubos conduit 3/4" UL | B17: si | C17: 0 | D17: 0 | E17: =+D17*C17 -> 0 | F17: =IF(B17="si",D17*$F$4,0) -> 0 | G17: =(D17+F17)*$G$4 -> 0 | H17: =(D17+F17+G17)*$H$4 -> 0 | I17: =IF(B17="si",(D17+F17+G17+H17)*$I$4,0) -> 0 | J17: =D17+F17+G17+H17+I17 -> 0 | K17: =J17*$K$4 -> 0 | L17: =(J17+K17)*C17 -> 0 | M17: =(J17+K17)*$M$4/(1-$M$4) -> 0 | N17: =M17+J17+K17 -> 0 | O17: =N17*C17 -> 0
A18: Uniones conduit de 3/4" | B18: si | C18: 0 | D18: 0 | E18: =+D18*C18 -> 0 | F18: =IF(B18="si",D18*$F$4,0) -> 0 | G18: =(D18+F18)*$G$4 -> 0 | H18: =(D18+F18+G18)*$H$4 -> 0 | I18: =IF(B18="si",(D18+F18+G18+H18)*$I$4,0) -> 0 | J18: =D18+F18+G18+H18+I18 -> 0 | K18: =J18*$K$4 -> 0 | L18: =(J18+K18)*C18 -> 0 | M18: =(J18+K18)*$M$4/(1-$M$4) -> 0 | N18: =M18+J18+K18 -> 0 | O18: =N18*C18 -> 0
A19: Conectores conduit de 3/4" | B19: si | C19: 0 | D19: 0 | E19: =+D19*C19 -> 0 | F19: =IF(B19="si",D19*$F$4,0) -> 0 | G19: =(D19+F19)*$G$4 -> 0 | H19: =(D19+F19+G19)*$H$4 -> 0 | I19: =IF(B19="si",(D19+F19+G19+H19)*$I$4,0) -> 0 | J19: =D19+F19+G19+H19+I19 -> 0 | K19: =J19*$K$4 -> 0 | L19: =(J19+K19)*C19 -> 0 | M19: =(J19+K19)*$M$4/(1-$M$4) -> 0 | N19: =M19+J19+K19 -> 0 | O19: =N19*C19 -> 0
A20: Gaza 1 ojo 3/4 | B20: si | C20: 0 | D20: 0 | E20: =+D20*C20 -> 0 | F20: =IF(B20="si",D20*$F$4,0) -> 0 | G20: =(D20+F20)*$G$4 -> 0 | H20: =(D20+F20+G20)*$H$4 -> 0 | I20: =IF(B20="si",(D20+F20+G20+H20)*$I$4,0) -> 0 | J20: =D20+F20+G20+H20+I20 -> 0 | K20: =J20*$K$4 -> 0 | L20: =(J20+K20)*C20 -> 0 | M20: =(J20+K20)*$M$4/(1-$M$4) -> 0 | N20: =M20+J20+K20 -> 0 | O20: =N20*C20 -> 0
A21: Cajas de paso 4x4 entradas 3/4" | B21: si | C21: 0 | D21: 0 | E21: =+D21*C21 -> 0 | F21: =IF(B21="si",D21*$F$4,0) -> 0 | G21: =(D21+F21)*$G$4 -> 0 | H21: =(D21+F21+G21)*$H$4 -> 0 | I21: =IF(B21="si",(D21+F21+G21+H21)*$I$4,0) -> 0 | J21: =D21+F21+G21+H21+I21 -> 0 | K21: =J21*$K$4 -> 0 | L21: =(J21+K21)*C21 -> 0 | M21: =(J21+K21)*$M$4/(1-$M$4) -> 0 | N21: =M21+J21+K21 -> 0 | O21: =N21*C21 -> 0
... A28: imp | B28: si | C28: 0 | D28: 0 | E28: =+D28*C28 -> 0 | F28: =IF(B28="si",D28*$F$4,0) -> 0 | G28: =(D28+F28)*$G$4 -> 0 | H28: =(D28+F28+G28)*$H$4 -> 0 | I28: =IF(B28="si",(D28+F28+G28+H28)*$I$4,0) -> 0 | J28: =D28+F28+G28+H28+I28 -> 0 | K28: =J28*$K$4 -> 0 | L28: =(J28+K28)*C28 -> 0 | M28: =(J28+K28)*$M$4/(1-$M$4) -> 0 | N28: =M28+J28+K28 -> 0 | O28: =N28*C28 -> 0
A29: viex | B29: si | C29: 0 | D29: 0 | E29: =+D29*C29 -> 0 | F29: =IF(B29="si",D29*$F$4,0) -> 0 | G29: 0 | H29: =(D29+F29+G29)*$H$4 -> 0 | I29: =IF(B29="si",(D29+F29+G29+H29)*$I$4,0) -> 0 | J29: =D29+F29+G29+H29+I29 -> 0 | K29: =J29*$K$4 -> 0 | L29: =(J29+K29)*C29 -> 0 | M29: =(J29+K29)*$M$4/(1-$M$4) -> 0 | N29: =M29+J29+K29 -> 0 | O29: =N29*C29 -> 0
A30: conector bx | B30: si | C30: 0 | D30: 0 | E30: =+D30*C30 -> 0 | F30: =IF(B30="si",D30*$F$4,0) -> 0 | G30: =(D30+F30)*$G$4 -> 0 | H30: =(D30+F30+G30)*$H$4 -> 0 | I30: =IF(B30="si",(D30+F30+G30+H30)*$I$4,0) -> 0 | J30: =D30+F30+G30+H30+I30 -> 0 | K30: =J30*$K$4 -> 0 | L30: =(J30+K30)*C30 -> 0 | M30: =(J30+K30)*$M$4/(1-$M$4) -> 0 | N30: =M30+J30+K30 -> 0 | O30: =N30*C30 -> 0
A31: alquiler andamios | B31: si | C31: 0 | D31: 0 | E31: =+D31*C31 -> 0 | F31: =IF(B31="si",D31*$F$4,0) -> 0 | G31: =(D31+F31)*$G$4 -> 0 | H31: =(D31+F31+G31)*$H$4 -> 0 | I31: =IF(B31="si",(D31+F31+G31+H31)*$I$4,0) -> 0 | J31: =D31+F31+G31+H31+I31 -> 0 | K31: =J31*$K$4 -> 0 | L31: =(J31+K31)*C31 -> 0 | M31: =(J31+K31)*$M$4/(1-$M$4) -> 0 | N31: =M31+J31+K31 -> 0 | O31: =N31*C31 -> 0
A32: Cable Honeywell 18x4, para magneto o control | B32: si | C32: 0 | D32: 0 | E32: =+D32*C32 -> 0 | F32: =IF(B32="si",D32*$F$4,0) -> 0 | G32: =(D32+F32)*$G$4 -> 0 | H32: =(D32+F32+G32)*$H$4 -> 0 | I32: =IF(B32="si",(D32+F32+G32+H32)*$I$4,0) -> 0 | J32: =D32+F32+G32+H32+I32 -> 0 | K32: =J32*$K$4 -> 0 | L32: =(J32+K32)*C32 -> 0 | M32: =(J32+K32)*$M$4/(1-$M$4) -> 0 | N32: =M32+J32+K32 -> 0 | O32: =N32*C32 -> 0
B33: si | C33: 0 | D33: 0 | E33: =+D33*C33 -> 0 | F33: =IF(B33="si",D33*$F$4,0) -> 0 | G33: =(D33+F33)*$G$4 -> 0 | H33: =(D33+F33+G33)*$H$4 -> 0 | I33: =IF(B33="si",(D33+F33+G33+H33)*$I$4,0) -> 0 | J33: =D33+F33+G33+H33+I33 -> 0 | K33: =J33*$K$4 -> 0 | L33: =(J33+K33)*C33 -> 0 | M33: =(J33+K33)*$M$4/(1-$M$4) -> 0 | N33: =M33+J33+K33 -> 0 | O33: =N33*C33 -> 0
B34: si | C34: 0 | D34: 0 | E34: =+D34*C34 -> 0 | F34: =IF(B34="si",D34*$F$4,0) -> 0 | G34: =(D34+F34)*$G$4 -> 0 | H34: =(D34+F34+G34)*$H$4 -> 0 | I34: =IF(B34="si",(D34+F34+G34+H34)*$I$4,0) -> 0 | J34: =D34+F34+G34+H34+I34 -> 0 | K34: =J34*$K$4 -> 0 | L34: =(J34+K34)*C34 -> 0 | M34: =(J34+K34)*$M$4/(1-$M$4) -> 0 | N34: =M34+J34+K34 -> 0 | O34: =N34*C34 -> 0
B35: si | C35: 0 | D35: 0 | E35: =+D35*C35 -> 0 | F35: =IF(B35="si",D35*$F$4,0) -> 0 | G35: =(D35+F35)*$G$4 -> 0 | H35: =(D35+F35+G35)*$H$4 -> 0 | I35: =IF(B35="si",(D35+F35+G35+H35)*$I$4,0) -> 0 | J35: =D35+F35+G35+H35+I35 -> 0 | K35: =J35*$K$4 -> 0 | L35: =(J35+K35)*C35 -> 0 | M35: =(J35+K35)*$M$4/(1-$M$4) -> 0 | N35: =M35+J35+K35 -> 0 | O35: =N35*C35 -> 0
B36: si | C36: 0 | D36: 0 | F36: =IF(B36="si",D36*$F$4,0) -> 0 | G36: =(D36+F36)*$G$4 -> 0 | H36: =(D36+F36+G36)*$H$4 -> 0 | I36: =IF(B36="si",(D36+F36+G36+H36)*$I$4,0) -> 0 | J36: =D36+F36+G36+H36+I36 -> 0 | K36: =J36*$K$4 -> 0 | L36: =(J36+K36)*C36 -> 0 | M36: =(J36+K36)*$M$4/(1-$M$4) -> 0 | N36: =M36+J36+K36 -> 0 | O36: =N36*C36 -> 0
A37: Sección 2
B38: si | C38: 0 | D38: 0 | E38: =+C38*D38*(1-C47) -> 0 | F38: =IF(B38="si",D38*$F$4,0) -> 0 | G38: =(D38+F38)*$G$4 -> 0 | H38: =(D38+F38+G38)*$H$4 -> 0 | I38: =IF(B38="si",(D38+F38+G38+H38)*$I$4,0) -> 0 | J38: =D38+F38+G38+H38+I38 -> 0 | K38: =J38*$K$4 -> 0 | L38: =(J38+K38)*C38 -> 0 | M38: =(J38+K38)*$M$4/(1-$M$4) -> 0 | N38: =M38+J38+K38 -> 0 | O38: =N38*C38 -> 0
B39: si | C39: 0 | D39: 0 | E39: =+C39*D39 -> 0 | F39: =IF(B39="si",D39*$F$4,0) -> 0 | G39: =(D39+F39)*$G$4 -> 0 | H39: =(D39+F39+G39)*$H$4 -> 0 | I39: =IF(B39="si",(D39+F39+G39+H39)*$I$4,0) -> 0 | J39: =D39+F39+G39+H39+I39 -> 0 | K39: =J39*$K$4 -> 0 | L39: =(J39+K39)*C39 -> 0 | M39: =(J39+K39)*$M$4/(1-$M$4) -> 0 | N39: =M39+J39+K39 -> 0 | O39: =N39*C39 -> 0
B40: si | C40: 0 | D40: 0 | E40: =+C40*D40 -> 0 | F40: =IF(B40="si",D40*$F$4,0) -> 0 | G40: =(D40+F40)*$G$4 -> 0 | H40: =(D40+F40+G40)*$H$4 -> 0 | I40: =IF(B40="si",(D40+F40+G40+H40)*$I$4,0) -> 0 | J40: =D40+F40+G40+H40+I40 -> 0 | K40: =J40*$K$4 -> 0 | L40: =(J40+K40)*C40 -> 0 | M40: =(J40+K40)*$M$4/(1-$M$4) -> 0 | N40: =M40+J40+K40 -> 0 | O40: =N40*C40 -> 0
B41: si | C41: 0 | D41: 0 | E41: =+C41*D41 -> 0 | F41: =IF(B41="si",D41*$F$4,0) -> 0 | G41: =(D41+F41)*$G$4 -> 0 | H41: =(D41+F41+G41)*$H$4 -> 0 | I41: =IF(B41="si",(D41+F41+G41+H41)*$I$4,0) -> 0 | J41: =D41+F41+G41+H41+I41 -> 0 | K41: =J41*$K$4 -> 0 | L41: =(J41+K41)*C41 -> 0 | M41: =(J41+K41)*$M$4/(1-$M$4) -> 0 | N41: =M41+J41+K41 -> 0 | O41: =N41*C41 -> 0
B42: si | C42: 0 | D42: 0 | E42: =+C42*D42 -> 0 | F42: =IF(B42="si",D42*$F$4,0) -> 0 | G42: =(D42+F42)*$G$4 -> 0 | H42: =(D42+F42+G42)*$H$4 -> 0 | I42: =IF(B42="si",(D42+F42+G42+H42)*$I$4,0) -> 0 | J42: =D42+F42+G42+H42+I42 -> 0 | K42: =J42*$K$4 -> 0 | L42: =(J42+K42)*C42 -> 0 | M42: =(J42+K42)*$M$4/(1-$M$4) -> 0 | N42: =M42+J42+K42 -> 0 | O42: =N42*C42 -> 0
A43: Sección 3
B44: si | C44: 0 | D44: 0 | E44: =+C44*D44 -> 0 | F44: =IF(B44="si",D44*$F$4,0) -> 0 | G44: =(D44+F44)*$G$4 -> 0 | H44: =(D44+F44+G44)*$H$4 -> 0 | I44: =IF(B44="si",(D44+F44+G44+H44)*$I$4,0) -> 0 | J44: =D44+F44+G44+H44+I44 -> 0 | K44: =J44*$K$4 -> 0 | L44: =(J44+K44)*C44 -> 0 | M44: =(J44+K44)*$M$4/(1-$M$4) -> 0 | N44: =M44+J44+K44 -> 0 | O44: =N44*C44 -> 0
D46: Total FOB | E46: =SUM(E34:E44) -> 0 | J46: Costo Nac. | L46: =SUM(L6:L44) -> 0 | N46: Total Venta | O46: =SUM(O6:O44) -> 0
N47: UTILIDAD | O47: =O46-L46 -> 0
A49: IMPORTADO
A50: si
A51: no

Sheet Financiamiento
A1: PROGRAMACION DE FINANCIAMIENTO POR LINEA (agregado automaticamente)
B2: Lineas de Equipos | H2: Lineas de Productos 2 | N2: Lineas de MATERIALES | T2: Lineas de OPEX GV
A3: 1 | B3: CUADRO COSTOS FINANCIEROS | G3: 1 | H3: CUADRO COSTOS FINANCIEROS | M3: 1 | N3: CUADRO COSTOS FINANCIEROS | S3: 1 | T3: CUADRO COSTOS FINANCIEROS
B4: Total Venta Proyecto | C4: =SUMIF(Equipos!$Q$6:$Q$55,A3,Equipos!$O$6:$O$55) -> 0 | D4: Interes Anual | E4: 0.11 | H4: Total Venta Proyecto | I4: =SUMIF('Productos 2'!$P$6:$P$15,G3,'Productos 2'!$N$6:$N$15) -> 0 | J4: Interes Anual | K4: 0.11 | N4: Total Venta Proyecto | O4: =SUMIF(MATERIALES!$P$6:$P$44,M3,MATERIALES!$N$6:$N$44) -> 0 | P4: Interes Anual | Q4: 0.11 | T4: Total Venta Proyecto | U4: =SUMIF('OPEX GV'!$P$6:$P$15,S3,'OPEX GV'!$N$6:$N$15) -> 0 | V4: Interes Anual | W4: 0.11
B5: Anticipos | C5: 0 | D5: Porcentaje de Prima | E5: 0 | H5: Anticipos | I5: 0 | J5: Porcentaje de Prima | K5: 0 | N5: Anticipos | O5: 0 | P5: Porcentaje de Prima | Q5: 0 | T5: Anticipos | U5: 0 | V5: Porcentaje de Prima | W5: 0
B6: Otros ingresos | C6: 0 | H6: Otros ingresos | I6: 0 | N6: Otros ingresos | O6: 0 | T6: Otros ingresos | U6: 0
B8: Total a Financiar | C8: =C4-C5-C6 -> 0 | H8: Total a Financiar | I8: =I4-I5-I6 -> 0 | N8: Total a Financiar | O8: =O4-O5-O6 -> 0 | T8: Total a Financiar | U8: =U4-U5-U6 -> 0
B9: Plazo (Anos) | C9: 4 | H9: Plazo (Anos) | I9: 4 | N9: Plazo (Anos) | O9: 4 | T9: Plazo (Anos) | U9: 4
B10: Plazo (Meses) | C10: =C9*12 -> 48 | H10: Plazo (Meses) | I10: =I9*12 -> 48 | N10: Plazo (Meses) | O10: =O9*12 -> 48 | T10: Plazo (Meses) | U10: =U9*12 -> 48
B12: Cuota mensual | C12: =-PMT(E4/12,C10,C8) -> 0 | D12: Cuota anual | E12: =C12*12 -> 0 | H12: Cuota mensual | I12: =-PMT(K4/12,I10,I8) -> 0 | J12: Cuota anual | K12: =I12*12 -> 0 | N12: Cuota mensual | O12: =-PMT(Q4/12,O10,O8) -> 0 | P12: Cuota anual | Q12: =O12*12 -> 0 | T12: Cuota mensual | U12: =-PMT(W4/12,U10,U8) -> 0 | V12: Cuota anual | W12: =U12*12 -> 0
B15: TIR | H15: TIR | N15: TIR | T15: TIR
B16: Total Cuotas c/financiamiento | C16: =C12*C10 -> 0 | H16: Total Cuotas c/financiamiento | I16: =I12*I10 -> 0 | N16: Total Cuotas c/financiamiento | O16: =O12*O10 -> 0 | T16: Total Cuotas c/financiamiento | U16: =U12*U10 -> 0
B18: Costo financiero | C18: =C16-C8 -> 0 | H18: Costo financiero | I18: =I16-I8 -> 0 | N18: Costo financiero | O18: =O16-O8 -> 0 | T18: Costo financiero | U18: =U16-U8 -> 0
A20: 2 | B20: CUADRO COSTOS FINANCIEROS | G20: 2 | H20: CUADRO COSTOS FINANCIEROS | M20: 2 | N20: CUADRO COSTOS FINANCIEROS | S20: 2 | T20: CUADRO COSTOS FINANCIEROS
B21: Total Venta Proyecto | C21: =SUMIF(Equipos!$Q$6:$Q$55,A20,Equipos!$O$6:$O$55) -> 0 | D21: Interes Anual | E21: 0.11 | H21: Total Venta Proyecto | I21: =SUMIF('Productos 2'!$P$6:$P$15,G20,'Productos 2'!$N$6:$N$15) -> 0 | J21: Interes Anual | K21: 0.11 | N21: Total Venta Proyecto | O21: =SUMIF(MATERIALES!$P$6:$P$44,M20,MATERIALES!$N$6:$N$44) -> 0 | P21: Interes Anual | Q21: 0.11 | T21: Total Venta Proyecto | U21: =SUMIF('OPEX GV'!$P$6:$P$15,S20,'OPEX GV'!$N$6:$N$15) -> 0 | V21: Interes Anual | W21: 0.11
B22: Anticipos | C22: 0 | D22: Porcentaje de Prima | E22: 0 | H22: Anticipos | I22: 0 | J22: Porcentaje de Prima | K22: 0 | N22: Anticipos | O22: 0 | P22: Porcentaje de Prima | Q22: 0 | T22: Anticipos | U22: 0 | V22: Porcentaje de Prima | W22: 0
B23: Otros ingresos | C23: 0 | H23: Otros ingresos | I23: 0 | N23: Otros ingresos | O23: 0 | T23: Otros ingresos | U23: 0
B25: Total a Financiar | C25: =C21-C22-C23 -> 0 | H25: Total a Financiar | I25: =I21-I22-I23 -> 0 | N25: Total a Financiar | O25: =O21-O22-O23 -> 0 | T25: Total a Financiar | U25: =U21-U22-U23 -> 0
B26: Plazo (Anos) | C26: 4 | H26: Plazo (Anos) | I26: 4 | N26: Plazo (Anos) | O26: 4 | T26: Plazo (Anos) | U26: 4
B27: Plazo (Meses) | C27: =C26*12 -> 48 | H27: Plazo (Meses) | I27: =I26*12 -> 48 | N27: Plazo (Meses) | O27: =O26*12 -> 48 | T27: Plazo (Meses) | U27: =U26*12 -> 48
B29: Cuota mensual | C29: =-PMT(E21/12,C27,C25) -> 0 | D29: Cuota anual | E29: =C29*12 -> 0 | H29: Cuota mensual | I29: =-PMT(K21/12,I27,I25) -> 0 | J29: Cuota anual | K29: =I29*12 -> 0 | N29: Cuota mensual | O29: =-PMT(Q21/12,O27,O25) -> 0 | P29: Cuota anual | Q29: =O29*12 -> 0 | T29: Cuota mensual | U29: =-PMT(W21/12,U27,U25) -> 0 | V29: Cuota anual | W29: =U29*12 -> 0
B32: TIR | H32: TIR | N32: TIR | T32: TIR
B33: Total Cuotas c/financiamiento | C33: =C29*C27 -> 0 | H33: Total Cuotas c/financiamiento | I33: =I29*I27 -> 0 | N33: Total Cuotas c/financiamiento | O33: =O29*O27 -> 0 | T33: Total Cuotas c/financiamiento | U33: =U29*U27 -> 0
B35: Costo financiero | C35: =C33-C25 -> 0 | H35: Costo financiero | I35: =I33-I25 -> 0 | N35: Costo financiero | O35: =O33-O25 -> 0 | T35: Costo financiero | U35: =U33-U25 -> 0
A37: 3 | B37: CUADRO COSTOS FINANCIEROS | G37: 3 | H37: CUADRO COSTOS FINANCIEROS | M37: 3 | N37: CUADRO COSTOS FINANCIEROS | S37: 3 | T37: CUADRO COSTOS FINANCIEROS
B38: Total Venta Proyecto | C38: =SUMIF(Equipos!$Q$6:$Q$55,A37,Equipos!$O$6:$O$55) -> 0 | D38: Interes Anual | E38: 0.11 | H38: Total Venta Proyecto | I38: =SUMIF('Productos 2'!$P$6:$P$15,G37,'Productos 2'!$N$6:$N$15) -> 0 | J38: Interes Anual | K38: 0.11 | N38: Total Venta Proyecto | O38: =SUMIF(MATERIALES!$P$6:$P$44,M37,MATERIALES!$N$6:$N$44) -> 0 | P38: Interes Anual | Q38: 0.11 | T38: Total Venta Proyecto | U38: =SUMIF('OPEX GV'!$P$6:$P$15,S37,'OPEX GV'!$N$6:$N$15) -> 0 | V38: Interes Anual | W38: 0.11
B39: Anticipos | C39: 0 | D39: Porcentaje de Prima | E39: 0 | H39: Anticipos | I39: 0 | J39: Porcentaje de Prima | K39: 0 | N39: Anticipos | O39: 0 | P39: Porcentaje de Prima | Q39: 0 | T39: Anticipos | U39: 0 | V39: Porcentaje de Prima | W39: 0
B40: Otros ingresos | C40: 0 | H40: Otros ingresos | I40: 0 | N40: Otros ingresos | O40: 0 | T40: Otros ingresos | U40: 0
B42: Total a Financiar | C42: =C38-C39-C40 -> 0 | H42: Total a Financiar | I42: =I38-I39-I40 -> 0 | N42: Total a Financiar | O42: =O38-O39-O40 -> 0 | T42: Total a Financiar | U42: =U38-U39-U40 -> 0
B43: Plazo (Anos) | C43: 4 | H43: Plazo (Anos) | I43: 4 | N43: Plazo (Anos) | O43: 4 | T43: Plazo (Anos) | U43: 4
B44: Plazo (Meses) | C44: =C43*12 -> 48 | H44: Plazo (Meses) | I44: =I43*12 -> 48 | N44: Plazo (Meses) | O44: =O43*12 -> 48 | T44: Plazo (Meses) | U44: =U43*12 -> 48
B46: Cuota mensual | C46: =-PMT(E38/12,C44,C42) -> 0 | D46: Cuota anual | E46: =C46*12 -> 0 | H46: Cuota mensual | I46: =-PMT(K38/12,I44,I42) -> 0 | J46: Cuota anual | K46: =I46*12 -> 0 | N46: Cuota mensual | O46: =-PMT(Q38/12,O44,O42) -> 0 | P46: Cuota anual | Q46: =O46*12 -> 0 | T46: Cuota mensual | U46: =-PMT(W38/12,U44,U42) -> 0 | V46: Cuota anual | W46: =U46*12 -> 0
B49: TIR | H49: TIR | N49: TIR | T49: TIR
B50: Total Cuotas c/financiamiento | C50: =C46*C44 -> 0 | H50: Total Cuotas c/financiamiento | I50: =I46*I44 -> 0 | N50: Total Cuotas c/financiamiento | O50: =O46*O44 -> 0 | T50: Total Cuotas c/financiamiento | U50: =U46*U44 -> 0
B52: Costo financiero | C52: =C50-C42 -> 0 | H52: Costo financiero | I52: =I50-I42 -> 0 | N52: Costo financiero | O52: =O50-O42 -> 0 | T52: Costo financiero | U52: =U50-U42 -> 0
A54: 4 | B54: CUADRO COSTOS FINANCIEROS | G54: 4 | H54: CUADRO COSTOS FINANCIEROS | M54: 4 | N54: CUADRO COSTOS FINANCIEROS | S54: 4 | T54: CUADRO COSTOS FINANCIEROS
B55: Total Venta Proyecto | C55: =SUMIF(Equipos!$Q$6:$Q$55,A54,Equipos!$O$6:$O$55) -> 0 | D55: Interes Anual | E55: 0.11 | H55: Total Venta Proyecto | I55: =SUMIF('Productos 2'!$P$6:$P$15,G54,'Productos 2'!$N$6:$N$15) -> 0 | J55: Interes Anual | K55: 0.11 | N55: Total Venta Proyecto | O55: =SUMIF(MATERIALES!$P$6:$P$44,M54,MATERIALES!$N$6:$N$44) -> 0 | P55: Interes Anual | Q55: 0.11 | T55: Total Venta Proyecto | U55: =SUMIF('OPEX GV'!$P$6:$P$15,S54,'OPEX GV'!$N$6:$N$15) -> 0 | V55: Interes Anual | W55: 0.11
B56: Anticipos | C56: 0 | D56: Porcentaje de Prima | E56: 0 | H56: Anticipos | I56: 0 | J56: Porcentaje de Prima | K56: 0 | N56: Anticipos | O56: 0 | P56: Porcentaje de Prima | Q56: 0 | T56: Anticipos | U56: 0 | V56: Porcentaje de Prima | W56: 0
B57: Otros ingresos | C57: 0 | H57: Otros ingresos | I57: 0 | N57: Otros ingresos | O57: 0 | T57: Otros ingresos | U57: 0
B59: Total a Financiar | C59: =C55-C56-C57 -> 0 | H59: Total a Financiar | I59: =I55-I56-I57 -> 0 | N59: Total a Financiar | O59: =O55-O56-O57 -> 0 | T59: Total a Financiar | U59: =U55-U56-U57 -> 0
B60: Plazo (Anos) | C60: 4 | H60: Plazo (Anos) | I60: 4 | N60: Plazo (Anos) | O60: 4 | T60: Plazo (Anos) | U60: 4
B61: Plazo (Meses) | C61: =C60*12 -> 48 | H61: Plazo (Meses) | I61: =I60*12 -> 48 | N61: Plazo (Meses) | O61: =O60*12 -> 48 | T61: Plazo (Meses) | U61: =U60*12 -> 48
B63: Cuota mensual | C63: =-PMT(E55/12,C61,C59) -> 0 | D63: Cuota anual | E63: =C63*12 -> 0 | H63: Cuota mensual | I63: =-PMT(K55/12,I61,I59) -> 0 | J63: Cuota anual | K63: =I63*12 -> 0 | N63: Cuota mensual | O63: =-PMT(Q55/12,O61,O59) -> 0 | P63: Cuota anual | Q63: =O63*12 -> 0 | T63: Cuota mensual | U63: =-PMT(W55/12,U61,U59) -> 0 | V63: Cuota anual | W63: =U63*12 -> 0
B66: TIR | H66: TIR | N66: TIR | T66: TIR
B67: Total Cuotas c/financiamiento | C67: =C63*C61 -> 0 | H67: Total Cuotas c/financiamiento | I67: =I63*I61 -> 0 | N67: Total Cuotas c/financiamiento | O67: =O63*O61 -> 0 | T67: Total Cuotas c/financiamiento | U67: =U63*U61 -> 0
B69: Costo financiero | C69: =C67-C59 -> 0 | H69: Costo financiero | I69: =I67-I59 -> 0 | N69: Costo financiero | O69: =O67-O59 -> 0 | T69: Costo financiero | U69: =U67-U59 -> 0
A71: 5 | B71: CUADRO COSTOS FINANCIEROS | G71: 5 | H71: CUADRO COSTOS FINANCIEROS | M71: 5 | N71: CUADRO COSTOS FINANCIEROS | S71: 5 | T71: CUADRO COSTOS FINANCIEROS
B72: Total Venta Proyecto | C72: =SUMIF(Equipos!$Q$6:$Q$55,A71,Equipos!$O$6:$O$55) -> 0 | D72: Interes Anual | E72: 0.11 | H72: Total Venta Proyecto | I72: =SUMIF('Productos 2'!$P$6:$P$15,G71,'Productos 2'!$N$6:$N$15) -> 0 | J72: Interes Anual | K72: 0.11 | N72: Total Venta Proyecto | O72: =SUMIF(MATERIALES!$P$6:$P$44,M71,MATERIALES!$N$6:$N$44) -> 0 | P72: Interes Anual | Q72: 0.11 | T72: Total Venta Proyecto | U72: =SUMIF('OPEX GV'!$P$6:$P$15,S71,'OPEX GV'!$N$6:$N$15) -> 0 | V72: Interes Anual | W72: 0.11
B73: Anticipos | C73: 0 | D73: Porcentaje de Prima | E73: 0 | H73: Anticipos | I73: 0 | J73: Porcentaje de Prima | K73: 0 | N73: Anticipos | O73: 0 | P73: Porcentaje de Prima | Q73: 0 | T73: Anticipos | U73: 0 | V73: Porcentaje de Prima | W73: 0
B74: Otros ingresos | C74: 0 | H74: Otros ingresos | I74: 0 | N74: Otros ingresos | O74: 0 | T74: Otros ingresos | U74: 0
B76: Total a Financiar | C76: =C72-C73-C74 -> 0 | H76: Total a Financiar | I76: =I72-I73-I74 -> 0 | N76: Total a Financiar | O76: =O72-O73-O74 -> 0 | T76: Total a Financiar | U76: =U72-U73-U74 -> 0
B77: Plazo (Anos) | C77: 4 | H77: Plazo (Anos) | I77: 4 | N77: Plazo (Anos) | O77: 4 | T77: Plazo (Anos) | U77: 4
B78: Plazo (Meses) | C78: =C77*12 -> 48 | H78: Plazo (Meses) | I78: =I77*12 -> 48 | N78: Plazo (Meses) | O78: =O77*12 -> 48 | T78: Plazo (Meses) | U78: =U77*12 -> 48
B80: Cuota mensual | C80: =-PMT(E72/12,C78,C76) -> 0 | D80: Cuota anual | E80: =C80*12 -> 0 | H80: Cuota mensual | I80: =-PMT(K72/12,I78,I76) -> 0 | J80: Cuota anual | K80: =I80*12 -> 0 | N80: Cuota mensual | O80: =-PMT(Q72/12,O78,O76) -> 0 | P80: Cuota anual | Q80: =O80*12 -> 0 | T80: Cuota mensual | U80: =-PMT(W72/12,U78,U76) -> 0 | V80: Cuota anual | W80: =U80*12 -> 0
B83: TIR | H83: TIR | N83: TIR | T83: TIR
B84: Total Cuotas c/financiamiento | C84: =C80*C78 -> 0 | H84: Total Cuotas c/financiamiento | I84: =I80*I78 -> 0 | N84: Total Cuotas c/financiamiento | O84: =O80*O78 -> 0 | T84: Total Cuotas c/financiamiento | U84: =U80*U78 -> 0
B86: Costo financiero | C86: =C84-C76 -> 0 | H86: Costo financiero | I86: =I84-I76 -> 0 | N86: Costo financiero | O86: =O84-O76 -> 0 | T86: Costo financiero | U86: =U84-U76 -> 0
A88: 6 | B88: CUADRO COSTOS FINANCIEROS | G88: 6 | H88: CUADRO COSTOS FINANCIEROS | M88: 6 | N88: CUADRO COSTOS FINANCIEROS | S88: 6 | T88: CUADRO COSTOS FINANCIEROS
B89: Total Venta Proyecto | C89: =SUMIF(Equipos!$Q$6:$Q$55,A88,Equipos!$O$6:$O$55) -> 0 | D89: Interes Anual | E89: 0.11 | H89: Total Venta Proyecto | I89: =SUMIF('Productos 2'!$P$6:$P$15,G88,'Productos 2'!$N$6:$N$15) -> 0 | J89: Interes Anual | K89: 0.11 | N89: Total Venta Proyecto | O89: =SUMIF(MATERIALES!$P$6:$P$44,M88,MATERIALES!$N$6:$N$44) -> 0 | P89: Interes Anual | Q89: 0.11 | T89: Total Venta Proyecto | U89: =SUMIF('OPEX GV'!$P$6:$P$15,S88,'OPEX GV'!$N$6:$N$15) -> 0 | V89: Interes Anual | W89: 0.11
B90: Anticipos | C90: 0 | D90: Porcentaje de Prima | E90: 0 | H90: Anticipos | I90: 0 | J90: Porcentaje de Prima | K90: 0 | N90: Anticipos | O90: 0 | P90: Porcentaje de Prima | Q90: 0 | T90: Anticipos | U90: 0 | V90: Porcentaje de Prima | W90: 0
B91: Otros ingresos | C91: 0 | H91: Otros ingresos | I91: 0 | N91: Otros ingresos | O91: 0 | T91: Otros ingresos | U91: 0
B93: Total a Financiar | C93: =C89-C90-C91 -> 0 | H93: Total a Financiar | I93: =I89-I90-I91 -> 0 | N93: Total a Financiar | O93: =O89-O90-O91 -> 0 | T93: Total a Financiar | U93: =U89-U90-U91 -> 0
B94: Plazo (Anos) | C94: 4 | H94: Plazo (Anos) | I94: 4 | N94: Plazo (Anos) | O94: 4 | T94: Plazo (Anos) | U94: 4
B95: Plazo (Meses) | C95: =C94*12 -> 48 | H95: Plazo (Meses) | I95: =I94*12 -> 48 | N95: Plazo (Meses) | O95: =O94*12 -> 48 | T95: Plazo (Meses) | U95: =U94*12 -> 48
B97: Cuota mensual | C97: =-PMT(E89/12,C95,C93) -> 0 | D97: Cuota anual | E97: =C97*12 -> 0 | H97: Cuota mensual | I97: =-PMT(K89/12,I95,I93) -> 0 | J97: Cuota anual | K97: =I97*12 -> 0 | N97: Cuota mensual | O97: =-PMT(Q89/12,O95,O93) -> 0 | P97: Cuota anual | Q97: =O97*12 -> 0 | T97: Cuota mensual | U97: =-PMT(W89/12,U95,U93) -> 0 | V97: Cuota anual | W97: =U97*12 -> 0
B100: TIR | H100: TIR | N100: TIR | T100: TIR
B101: Total Cuotas c/financiamiento | C101: =C97*C95 -> 0 | H101: Total Cuotas c/financiamiento | I101: =I97*I95 -> 0 | N101: Total Cuotas c/financiamiento | O101: =O97*O95 -> 0 | T101: Total Cuotas c/financiamiento | U101: =U97*U95 -> 0
B103: Costo financiero | C103: =C101-C93 -> 0 | H103: Costo financiero | I103: =I101-I93 -> 0 | N103: Costo financiero | O103: =O101-O93 -> 0 | T103: Costo financiero | U103: =U101-U93 -> 0
A105: 7 | B105: CUADRO COSTOS FINANCIEROS | G105: 7 | H105: CUADRO COSTOS FINANCIEROS | M105: 7 | N105: CUADRO COSTOS FINANCIEROS | S105: 7 | T105: CUADRO COSTOS FINANCIEROS
B106: Total Venta Proyecto | C106: =SUMIF(Equipos!$Q$6:$Q$55,A105,Equipos!$O$6:$O$55) -> 0 | D106: Interes Anual | E106: 0.11 | H106: Total Venta Proyecto | I106: =SUMIF('Productos 2'!$P$6:$P$15,G105,'Productos 2'!$N$6:$N$15) -> 0 | J106: Interes Anual | K106: 0.11 | N106: Total Venta Proyecto | O106: =SUMIF(MATERIALES!$P$6:$P$44,M105,MATERIALES!$N$6:$N$44) -> 0 | P106: Interes Anual | Q106: 0.11 | T106: Total Venta Proyecto | U106: =SUMIF('OPEX GV'!$P$6:$P$15,S105,'OPEX GV'!$N$6:$N$15) -> 0 | V106: Interes Anual | W106: 0.11
B107: Anticipos | C107: 0 | D107: Porcentaje de Prima | E107: 0 | H107: Anticipos | I107: 0 | J107: Porcentaje de Prima | K107: 0 | N107: Anticipos | O107: 0 | P107: Porcentaje de Prima | Q107: 0 | T107: Anticipos | U107: 0 | V107: Porcentaje de Prima | W107: 0
B108: Otros ingresos | C108: 0 | H108: Otros ingresos | I108: 0 | N108: Otros ingresos | O108: 0 | T108: Otros ingresos | U108: 0
B110: Total a Financiar | C110: =C106-C107-C108 -> 0 | H110: Total a Financiar | I110: =I106-I107-I108 -> 0 | N110: Total a Financiar | O110: =O106-O107-O108 -> 0 | T110: Total a Financiar | U110: =U106-U107-U108 -> 0
B111: Plazo (Anos) | C111: 4 | H111: Plazo (Anos) | I111: 4 | N111: Plazo (Anos) | O111: 4 | T111: Plazo (Anos) | U111: 4
B112: Plazo (Meses) | C112: =C111*12 -> 48 | H112: Plazo (Meses) | I112: =I111*12 -> 48 | N112: Plazo (Meses) | O112: =O111*12 -> 48 | T112: Plazo (Meses) | U112: =U111*12 -> 48
B114: Cuota mensual | C114: =-PMT(E106/12,C112,C110) -> 0 | D114: Cuota anual | E114: =C114*12 -> 0 | H114: Cuota mensual | I114: =-PMT(K106/12,I112,I110) -> 0 | J114: Cuota anual | K114: =I114*12 -> 0 | N114: Cuota mensual | O114: =-PMT(Q106/12,O112,O110) -> 0 | P114: Cuota anual | Q114: =O114*12 -> 0 | T114: Cuota mensual | U114: =-PMT(W106/12,U112,U110) -> 0 | V114: Cuota anual | W114: =U114*12 -> 0
B117: TIR | H117: TIR | N117: TIR | T117: TIR
B118: Total Cuotas c/financiamiento | C118: =C114*C112 -> 0 | H118: Total Cuotas c/financiamiento | I118: =I114*I112 -> 0 | N118: Total Cuotas c/financiamiento | O118: =O114*O112 -> 0 | T118: Total Cuotas c/financiamiento | U118: =U114*U112 -> 0
B120: Costo financiero | C120: =C118-C110 -> 0 | H120: Costo financiero | I120: =I118-I110 -> 0 | N120: Costo financiero | O120: =O118-O110 -> 0 | T120: Costo financiero | U120: =U118-U110 -> 0
A122: 8 | B122: CUADRO COSTOS FINANCIEROS | G122: 8 | H122: CUADRO COSTOS FINANCIEROS | M122: 8 | N122: CUADRO COSTOS FINANCIEROS | S122: 8 | T122: CUADRO COSTOS FINANCIEROS
B123: Total Venta Proyecto | C123: =SUMIF(Equipos!$Q$6:$Q$55,A122,Equipos!$O$6:$O$55) -> 0 | D123: Interes Anual | E123: 0.11 | H123: Total Venta Proyecto | I123: =SUMIF('Productos 2'!$P$6:$P$15,G122,'Productos 2'!$N$6:$N$15) -> 0 | J123: Interes Anual | K123: 0.11 | N123: Total Venta Proyecto | O123: =SUMIF(MATERIALES!$P$6:$P$44,M122,MATERIALES!$N$6:$N$44) -> 0 | P123: Interes Anual | Q123: 0.11 | T123: Total Venta Proyecto | U123: =SUMIF('OPEX GV'!$P$6:$P$15,S122,'OPEX GV'!$N$6:$N$15) -> 0 | V123: Interes Anual | W123: 0.11
B124: Anticipos | C124: 0 | D124: Porcentaje de Prima | E124: 0 | H124: Anticipos | I124: 0 | J124: Porcentaje de Prima | K124: 0 | N124: Anticipos | O124: 0 | P124: Porcentaje de Prima | Q124: 0 | T124: Anticipos | U124: 0 | V124: Porcentaje de Prima | W124: 0
B125: Otros ingresos | C125: 0 | H125: Otros ingresos | I125: 0 | N125: Otros ingresos | O125: 0 | T125: Otros ingresos | U125: 0
B127: Total a Financiar | C127: =C123-C124-C125 -> 0 | H127: Total a Financiar | I127: =I123-I124-I125 -> 0 | N127: Total a Financiar | O127: =O123-O124-O125 -> 0 | T127: Total a Financiar | U127: =U123-U124-U125 -> 0
B128: Plazo (Anos) | C128: 4 | H128: Plazo (Anos) | I128: 4 | N128: Plazo (Anos) | O128: 4 | T128: Plazo (Anos) | U128: 4
B129: Plazo (Meses) | C129: =C128*12 -> 48 | H129: Plazo (Meses) | I129: =I128*12 -> 48 | N129: Plazo (Meses) | O129: =O128*12 -> 48 | T129: Plazo (Meses) | U129: =U128*12 -> 48
B131: Cuota mensual | C131: =-PMT(E123/12,C129,C127) -> 0 | D131: Cuota anual | E131: =C131*12 -> 0 | H131: Cuota mensual | I131: =-PMT(K123/12,I129,I127) -> 0 | J131: Cuota anual | K131: =I131*12 -> 0 | N131: Cuota mensual | O131: =-PMT(Q123/12,O129,O127) -> 0 | P131: Cuota anual | Q131: =O131*12 -> 0 | T131: Cuota mensual | U131: =-PMT(W123/12,U129,U127) -> 0 | V131: Cuota anual | W131: =U131*12 -> 0
B134: TIR | H134: TIR | N134: TIR | T134: TIR
B135: Total Cuotas c/financiamiento | C135: =C131*C129 -> 0 | H135: Total Cuotas c/financiamiento | I135: =I131*I129 -> 0 | N135: Total Cuotas c/financiamiento | O135: =O131*O129 -> 0 | T135: Total Cuotas c/financiamiento | U135: =U131*U129 -> 0
B137: Costo financiero | C137: =C135-C127 -> 0 | H137: Costo financiero | I137: =I135-I127 -> 0 | N137: Costo financiero | O137: =O135-O127 -> 0 | T137: Costo financiero | U137: =U135-U127 -> 0
A139: 9 | B139: CUADRO COSTOS FINANCIEROS | G139: 9 | H139: CUADRO COSTOS FINANCIEROS | M139: 9 | N139: CUADRO COSTOS FINANCIEROS | S139: 9 | T139: CUADRO COSTOS FINANCIEROS
B140: Total Venta Proyecto | C140: =SUMIF(Equipos!$Q$6:$Q$55,A139,Equipos!$O$6:$O$55) -> 0 | D140: Interes Anual | E140: 0.11 | H140: Total Venta Proyecto | I140: =SUMIF('Productos 2'!$P$6:$P$15,G139,'Productos 2'!$N$6:$N$15) -> 0 | J140: Interes Anual | K140: 0.11 | N140: Total Venta Proyecto | O140: =SUMIF(MATERIALES!$P$6:$P$44,M139,MATERIALES!$N$6:$N$44) -> 0 | P140: Interes Anual | Q140: 0.11 | T140: Total Venta Proyecto | U140: =SUMIF('OPEX GV'!$P$6:$P$15,S139,'OPEX GV'!$N$6:$N$15) -> 0 | V140: Interes Anual | W140: 0.11
B141: Anticipos | C141: 0 | D141: Porcentaje de Prima | E141: 0 | H141: Anticipos | I141: 0 | J141: Porcentaje de Prima | K141: 0 | N141: Anticipos | O141: 0 | P141: Porcentaje de Prima | Q141: 0 | T141: Anticipos | U141: 0 | V141: Porcentaje de Prima | W141: 0
B142: Otros ingresos | C142: 0 | H142: Otros ingresos | I142: 0 | N142: Otros ingresos | O142: 0 | T142: Otros ingresos | U142: 0
B144: Total a Financiar | C144: =C140-C141-C142 -> 0 | H144: Total a Financiar | I144: =I140-I141-I142 -> 0 | N144: Total a Financiar | O144: =O140-O141-O142 -> 0 | T144: Total a Financiar | U144: =U140-U141-U142 -> 0
B145: Plazo (Anos) | C145: 4 | H145: Plazo (Anos) | I145: 4 | N145: Plazo (Anos) | O145: 4 | T145: Plazo (Anos) | U145: 4
B146: Plazo (Meses) | C146: =C145*12 -> 48 | H146: Plazo (Meses) | I146: =I145*12 -> 48 | N146: Plazo (Meses) | O146: =O145*12 -> 48 | T146: Plazo (Meses) | U146: =U145*12 -> 48
B148: Cuota mensual | C148: =-PMT(E140/12,C146,C144) -> 0 | D148: Cuota anual | E148: =C148*12 -> 0 | H148: Cuota mensual | I148: =-PMT(K140/12,I146,I144) -> 0 | J148: Cuota anual | K148: =I148*12 -> 0 | N148: Cuota mensual | O148: =-PMT(Q140/12,O146,O144) -> 0 | P148: Cuota anual | Q148: =O148*12 -> 0 | T148: Cuota mensual | U148: =-PMT(W140/12,U146,U144) -> 0 | V148: Cuota anual | W148: =U148*12 -> 0
B151: TIR | H151: TIR | N151: TIR | T151: TIR
B152: Total Cuotas c/financiamiento | C152: =C148*C146 -> 0 | H152: Total Cuotas c/financiamiento | I152: =I148*I146 -> 0 | N152: Total Cuotas c/financiamiento | O152: =O148*O146 -> 0 | T152: Total Cuotas c/financiamiento | U152: =U148*U146 -> 0
...

Sheet PTMO
A1: Programacion de la amortizacion para Financiamiento
B4: Especificar valores | I4: Resumen del prestamo
C5: Importe del prestamo | D5: 0 | I5: Pago programado | J5: =-PMT(D6/D8,D12,D5) -> 0
C6: Tasa de interes anual | D6: 0.11 | I6: Numero de pagos programado | J6: =D12 -> 48
C7: Plazo del prestamo en anos | D7: 4 | I7: Factor anualidad | J7: =D8 -> 12
C8: Numero de pagos al ano | D8: 12 | I8: Total de pagos anticipados | J8: =SUM(E19:E118) -> 0
C9: Fecha inicial del prestamo | D9: 46279 | I9: Interes total | J9: =SUM(H19:H118) -> 0
C10: Pagos adicionales opcionales (por periodo) | D10: 0
C11: Periodo de Gracia (meses sin pago) | D11: 0
C12: Periodos Totales | D12: =D7*D8 -> 48 | I12: Total valor requerido ya con financiamiento | K12: =D5+J9 -> 0
A17: N. Pago | B17: Fecha de pago | C17: Saldo inicial | D17: Pago programado | E17: Pago adicional | F17: Pago total | G17: Capital | H17: Interes | I17: Saldo final | J17: Interes acumulativo
A19: =IF(AND(N($D$5)>0,ROW()-19+1<=$D$12),ROW()-19+1,"") | B19: =IF($A19="","",EDATE($D$9,$A19)) | C19: =IF($A19="","",$D$5) | D19: =IF($A19="","",$J$5) | E19: =IF($A19="","",$D$10) | F19: =IF($A19="","",D19+E19) | G19: =IF($A19="","",MIN(F19-H19,C19)) | H19: =IF($A19="","",C19*($D$6/$D$8)) | I19: =IF($A19="","",C19-G19) | J19: =IF($A19="","",H19)
A20: =IF(AND(N($D$5)>0,ROW()-19+1<=$D$12),ROW()-19+1,"") | B20: =IF($A20="","",EDATE($D$9,$A20)) | C20: =IF($A20="","",I19) | D20: =IF($A20="","",$J$5) | E20: =IF($A20="","",$D$10) | F20: =IF($A20="","",D20+E20) | G20: =IF($A20="","",MIN(F20-H20,C20)) | H20: =IF($A20="","",C20*($D$6/$D$8)) | I20: =IF($A20="","",C20-G20) | J20: =IF($A20="","",J19+H20)
A21: =IF(AND(N($D$5)>0,ROW()-19+1<=$D$12),ROW()-19+1,"") | B21: =IF($A21="","",EDATE($D$9,$A21)) | C21: =IF($A21="","",I20) | D21: =IF($A21="","",$J$5) | E21: =IF($A21="","",$D$10) | F21: =IF($A21="","",D21+E21) | G21: =IF($A21="","",MIN(F21-H21,C21)) | H21: =IF($A21="","",C21*($D$6/$D$8)) | I21: =IF($A21="","",C21-G21) | J21: =IF($A21="","",J20+H21)
A22: =IF(AND(N($D$5)>0,ROW()-19+1<=$D$12),ROW()-19+1,"") | B22: =IF($A22="","",EDATE($D$9,$A22)) | C22: =IF($A22="","",I21) | D22: =IF($A22="","",$J$5) | E22: =IF($A22="","",$D$10) | F22: =IF($A22="","",D22+E22) | G22: =IF($A22="","",MIN(F22-H22,C22)) | H22: =IF($A22="","",C22*($D$6/$D$8)) | I22: =IF($A22="","",C22-G22) | J22: =IF($A22="","",J21+H22)
A23: =IF(AND(N($D$5)>0,ROW()-19+1<=$D$12),ROW()-19+1,"") | B23: =IF($A23="","",EDATE($D$9,$A23)) | C23: =IF($A23="","",I22) | D23: =IF($A23="","",$J$5) | E23: =IF($A23="","",$D$10) | F23: =IF($A23="","",D23+E23) | G23: =IF($A23="","",MIN(F23-H23,C23)) | H23: =IF($A23="","",C23*($D$6/$D$8)) | I23: =IF($A23="","",C23-G23) | J23: =IF($A23="","",J22+H23)
A24: =IF(AND(N($D$5)>0,ROW()-19+1<=$D$12),ROW()-19+1,"") | B24: =IF($A24="","",EDATE($D$9,$A24)) | C24: =IF($A24="","",I23) | D24: =IF($A24="","",$J$5) | E24: =IF($A24="","",$D$10) | F24: =IF($A24="","",D24+E24) | G24: =IF($A24="","",MIN(F24-H24,C24)) | H24: =IF($A24="","",C24*($D$6/$D$8)) | I24: =IF($A24="","",C24-G24) | J24: =IF($A24="","",J23+H24)
A25: =IF(AND(N($D$5)>0,ROW()-19+1<=$D$12),ROW()-19+1,"") | B25: =IF($A25="","",EDATE($D$9,$A25)) | C25: =IF($A25="","",I24) | D25: =IF($A25="","",$J$5) | E25: =IF($A25="","",$D$10) | F25: =IF($A25="","",D25+E25) | G25: =IF($A25="","",MIN(F25-H25,C25)) | H25: =IF($A25="","",C25*($D$6/$D$8)) | I25: =IF($A25="","",C25-G25) | J25: =IF($A25="","",J24+H25)
A26: =IF(AND(N($D$5)>0,ROW()-19+1<=$D$12),ROW()-19+1,"") | B26: =IF($A26="","",EDATE($D$9,$A26)) | C26: =IF($A26="","",I25) | D26: =IF($A26="","",$J$5) | E26: =IF($A26="","",$D$10) | F26: =IF($A26="","",D26+E26) | G26: =IF($A26="","",MIN(F26-H26,C26)) | H26: =IF($A26="","",C26*($D$6/$D$8)) | I26: =IF($A26="","",C26-G26) | J26: =IF($A26="","",J25+H26)
A27: =IF(AND(N($D$5)>0,ROW()-19+1<=$D$12),ROW()-19+1,"") | B27: =IF($A27="","",EDATE($D$9,$A27)) | C27: =IF($A27="","",I26) | D27: =IF($A27="","",$J$5) | E27: =IF($A27="","",$D$10) | F27: =IF($A27="","",D27+E27) | G27: =IF($A27="","",MIN(F27-H27,C27)) | H27: =IF($A27="","",C27*($D$6/$D$8)) | I27: =IF($A27="","",C27-G27) | J27: =IF($A27="","",J26+H27)
A28: =IF(AND(N($D$5)>0,ROW()-19+1<=$D$12),ROW()-19+1,"") | B28: =IF($A28="","",EDATE($D$9,$A28)) | C28: =IF($A28="","",I27) | D28: =IF($A28="","",$J$5) | E28: =IF($A28="","",$D$10) | F28: =IF($A28="","",D28+E28) | G28: =IF($A28="","",MIN(F28-H28,C28)) | H28: =IF($A28="","",C28*($D$6/$D$8)) | I28: =IF($A28="","",C28-G28) | J28: =IF($A28="","",J27+H28)
A29: =IF(AND(N($D$5)>0,ROW()-19+1<=$D$12),ROW()-19+1,"") | B29: =IF($A29="","",EDATE($D$9,$A29)) | C29: =IF($A29="","",I28) | D29: =IF($A29="","",$J$5) | E29: =IF($A29="","",$D$10) | F29: =IF($A29="","",D29+E29) | G29: =IF($A29="","",MIN(F29-H29,C29)) | H29: =IF($A29="","",C29*($D$6/$D$8)) | I29: =IF($A29="","",C29-G29) | J29: =IF($A29="","",J28+H29)
A30: =IF(AND(N($D$5)>0,ROW()-19+1<=$D$12),ROW()-19+1,"") | B30: =IF($A30="","",EDATE($D$9,$A30)) | C30: =IF($A30="","",I29) | D30: =IF($A30="","",$J$5) | E30: =IF($A30="","",$D$10) | F30: =IF($A30="","",D30+E30) | G30: =IF($A30="","",MIN(F30-H30,C30)) | H30: =IF($A30="","",C30*($D$6/$D$8)) | I30: =IF($A30="","",C30-G30) | J30: =IF($A30="","",J29+H30)
A31: =IF(AND(N($D$5)>0,ROW()-19+1<=$D$12),ROW()-19+1,"") | B31: =IF($A31="","",EDATE($D$9,$A31)) | C31: =IF($A31="","",I30) | D31: =IF($A31="","",$J$5) | E31: =IF($A31="","",$D$10) | F31: =IF($A31="","",D31+E31) | G31: =IF($A31="","",MIN(F31-H31,C31)) | H31: =IF($A31="","",C31*($D$6/$D$8)) | I31: =IF($A31="","",C31-G31) | J31: =IF($A31="","",J30+H31)
... A118: =IF(AND(N($D$5)>0,ROW()-19+1<=$D$12),ROW()-19+1,"") | B118: =IF($A118="","",EDATE($D$9,$A118)) | C118: =IF($A118="","",I117) | D118: =IF($A118="","",$J$5) | E118: =IF($A118="","",$D$10) | F118: =IF($A118="","",D118+E118) | G118: =IF($A118="","",MIN(F118-H118,C118)) | H118: =IF($A118="","",C118*($D$6/$D$8)) | I118: =IF($A118="","",C118-G118) | J118: =IF($A118="","",J117+H118)

Sheet PRODUCTO G
A1: MATRIZ DE COSTO PROYECTO: | E1: =+Equipos!E1 -> 0
A3: PRODUCTO G | F3: Transporte | G3: Seguros | H3: IVA | I3: DAI | J3: Costo Untit | K3: Administración | L3: Costo total | M3: Margen GV | N3: Precio Venta | O3: Precio Venta
A4: Description | C4: Qty | D4: Costo Unit | E4: Costo Total | F4: 0 | G4: 0 | H4: 0 | I4: 0 | J4: Nacionalizado | K4: 0.03 | L4: Nacionaliado | M4: 0.23 | N4: Unitario | O4: Total
A5: Sección 1 | B5: IMPORTADO
B6: no | C6: 0 | D6: 0 | E6: =+D6*C6 -> 0 | F6: =IF(B6="si",D6*$F$4,0) -> 0 | G6: 0 | H6: =(D6+F6+G6)*$H$4 -> 0 | I6: =IF(B6="si",(D6+F6+G6+H6)*$I$4,0) -> 0 | J6: =D6+F6+G6+H6+I6 -> 0 | K6: =J6*$K$4 -> 0 | L6: =J6*C6 -> 0 | M6: =(J6+K6)*$M$4/(1-$M$4) -> 0 | N6: =M6+J6+K6 -> 0 | O6: =N6*C6 -> 0
B7: no | C7: 0 | D7: 0 | E7: =+D7*C7 -> 0 | F7: =IF(B7="si",D7*$F$4,0) -> 0 | G7: =(D7+F7)*$G$4 -> 0 | H7: =(D7+F7+G7)*$H$4 -> 0 | I7: =IF(B7="si",(D7+F7+G7+H7)*$I$4,0) -> 0 | J7: =D7+F7+G7+H7+I7 -> 0 | K7: =J7*$K$4 -> 0 | L7: =J7*C7 -> 0 | M7: =J7*$M$4/(1-$M$4) -> 0 | N7: =M7+J7 -> 0 | O7: =N7*C7 -> 0
B8: no | C8: 0 | D8: 0 | E8: =+D8*C8 -> 0 | F8: =IF(B8="si",D8*$F$4,0) -> 0 | G8: =(D8+F8)*$G$4 -> 0 | H8: =(D8+F8+G8)*$H$4 -> 0 | I8: =IF(B8="si",(D8+F8+G8+H8)*$I$4,0) -> 0 | J8: =D8+F8+G8+H8+I8 -> 0 | K8: =J8*$K$4 -> 0 | L8: =J8*C8 -> 0 | M8: =J8*$M$4/(1-$M$4) -> 0 | N8: =M8+J8 -> 0 | O8: =N8*C8 -> 0
B9: no | D9: 0 | E9: =+D9*C9 -> 0 | F9: =IF(B9="si",D9*$F$4,0) -> 0 | G9: =(D9+F9)*$G$4 -> 0 | H9: =(D9+F9+G9)*$H$4 -> 0 | I9: =IF(B9="si",(D9+F9+G9+H9)*$I$4,0) -> 0 | J9: =D9+F9+G9+H9+I9 -> 0 | K9: =J9*$K$4 -> 0 | L9: =J9*C9 -> 0 | M9: =J9*$M$4/(1-$M$4) -> 0 | N9: =M9+J9 -> 0 | O9: =N9*C9 -> 0
B10: no | D10: 0 | E10: =+D10*C10 -> 0 | F10: =IF(B10="si",D10*$F$4,0) -> 0 | G10: =(D10+F10)*$G$4 -> 0 | H10: =(D10+F10+G10)*$H$4 -> 0 | I10: =IF(B10="si",(D10+F10+G10+H10)*$I$4,0) -> 0 | J10: =D10+F10+G10+H10+I10 -> 0 | K10: =J10*$K$4 -> 0 | L10: =J10*C10 -> 0 | M10: =J10*$M$4/(1-$M$4) -> 0 | N10: =M10+J10 -> 0 | O10: =N10*C10 -> 0
B11: no | D11: 0 | E11: =+D11*C11 -> 0 | F11: =IF(B11="si",D11*$F$4,0) -> 0 | G11: =(D11+F11)*$G$4 -> 0 | H11: =(D11+F11+G11)*$H$4 -> 0 | I11: =IF(B11="si",(D11+F11+G11+H11)*$I$4,0) -> 0 | J11: =D11+F11+G11+H11+I11 -> 0 | K11: =J11*$K$4 -> 0 | L11: =J11*C11 -> 0 | M11: =J11*$M$4/(1-$M$4) -> 0 | N11: =M11+J11 -> 0 | O11: =N11*C11 -> 0
B12: no | D12: 0 | E12: =+D12*C12 -> 0 | F12: =IF(B12="si",D12*$F$4,0) -> 0 | G12: =(D12+F12)*$G$4 -> 0 | H12: =(D12+F12+G12)*$H$4 -> 0 | I12: =IF(B12="si",(D12+F12+G12+H12)*$I$4,0) -> 0 | J12: =D12+F12+G12+H12+I12 -> 0 | K12: =J12*$K$4 -> 0 | L12: =J12*C12 -> 0 | M12: =J12*$M$4/(1-$M$4) -> 0 | N12: =M12+J12 -> 0 | O12: =N12*C12 -> 0
A13: Sección 2 | F13: =IF(B13="si",D13*$F$4,0) -> 0 | I13: =IF(B13="si",(D13+F13+G13+H13)*$I$4,0) -> 0
D14: 0 | E14: =+C14*D14*(1-C23) -> 0 | F14: =IF(B14="si",D14*$F$4,0) -> 0 | G14: =(D14+F14)*$G$4 -> 0 | H14: =(D14+F14+G14)*$H$4 -> 0 | I14: =IF(B14="si",(D14+F14+G14+H14)*$I$4,0) -> 0 | J14: =D14+F14+G14+H14+I14 -> 0 | K14: =J14*$K$4 -> 0 | L14: =J14*C14 -> 0 | M14: =J14*$M$4/(1-$M$4) -> 0 | N14: =M14+J14 -> 0 | O14: =N14*C14 -> 0
D15: 0 | E15: =+C15*D15 -> 0 | F15: =IF(B15="si",D15*$F$4,0) -> 0 | G15: =(D15+F15)*$G$4 -> 0 | H15: =(D15+F15+G15)*$H$4 -> 0 | I15: =IF(B15="si",(D15+F15+G15+H15)*$I$4,0) -> 0 | J15: =D15+F15+G15+H15+I15 -> 0 | K15: =J15*$K$4 -> 0 | L15: =J15*C15 -> 0 | M15: =J15*$M$4/(1-$M$4) -> 0 | N15: =M15+J15 -> 0 | O15: =N15*C15 -> 0
D16: 0 | E16: =+C16*D16 -> 0 | F16: =IF(B16="si",D16*$F$4,0) -> 0 | G16: =(D16+F16)*$G$4 -> 0 | H16: =(D16+F16+G16)*$H$4 -> 0 | I16: =IF(B16="si",(D16+F16+G16+H16)*$I$4,0) -> 0 | J16: =D16+F16+G16+H16+I16 -> 0 | K16: =J16*$K$4 -> 0 | L16: =J16*C16 -> 0 | M16: =J16*$M$4/(1-$M$4) -> 0 | N16: =M16+J16 -> 0 | O16: =N16*C16 -> 0
D17: 0 | E17: =+C17*D17 -> 0 | F17: =IF(B17="si",D17*$F$4,0) -> 0 | G17: =(D17+F17)*$G$4 -> 0 | H17: =(D17+F17+G17)*$H$4 -> 0 | I17: =IF(B17="si",(D17+F17+G17+H17)*$I$4,0) -> 0 | J17: =D17+F17+G17+H17+I17 -> 0 | K17: =J17*$K$4 -> 0 | L17: =J17*C17 -> 0 | M17: =J17*$M$4/(1-$M$4) -> 0 | N17: =M17+J17 -> 0 | O17: =N17*C17 -> 0
D18: 0 | E18: =+C18*D18 -> 0 | F18: =IF(B18="si",D18*$F$4,0) -> 0 | G18: =(D18+F18)*$G$4 -> 0 | H18: =(D18+F18+G18)*$H$4 -> 0 | I18: =IF(B18="si",(D18+F18+G18+H18)*$I$4,0) -> 0 | J18: =D18+F18+G18+H18+I18 -> 0 | K18: =J18*$K$4 -> 0 | L18: =J18*C18 -> 0 | M18: =J18*$M$4/(1-$M$4) -> 0 | N18: =M18+J18 -> 0 | O18: =N18*C18 -> 0
A19: Sección 3 | F19: =IF(B19="si",D19*$F$4,0) -> 0 | I19: =IF(B19="si",(D19+F19+G19+H19)*$I$4,0) -> 0
D20: 0 | E20: =+C20*D20 -> 0 | F20: =IF(B20="si",D20*$F$4,0) -> 0 | G20: =(D20+F20)*$G$4 -> 0 | H20: =(D20+F20+G20)*$H$4 -> 0 | I20: =IF(B20="si",(D20+F20+G20+H20)*$I$4,0) -> 0 | J20: =D20+F20+G20+H20+I20 -> 0 | K20: =J20*$K$4 -> 0 | L20: =J20*C20 -> 0 | M20: =J20*$M$4/(1-$M$4) -> 0 | N20: =M20+J20 -> 0 | O20: =N20*C20 -> 0
D22: Total FOB | E22: =SUM(E6:E20) -> 0 | J22: Costo Nac. | L22: =SUM(L6:L20) -> 0 | N22: Total Venta | O22: =SUM(O6:O20) -> 0
N23: UTILIDAD | O23: =O22-L22 -> 0
A25: IMPORTADO
A26: si
A27: no

Sheet PRODUCTO H
A1: MATRIZ DE COSTO PROYECTO: | E1: =+Equipos!E1 -> 0
A3: PRODUCTO H | F3: Transporte | G3: Seguros | H3: IVA | I3: DAI | J3: Costo Untit | K3: Administración | L3: Costo total | M3: Margen GV | N3: Precio Venta | O3: Precio Venta
A4: Description | C4: Qty | D4: Costo Unit | E4: Costo Total | F4: 0 | G4: 0 | H4: 0 | I4: 0 | J4: Nacionalizado | K4: 0.03 | L4: Nacionaliado | M4: 0.23 | N4: Unitario | O4: Total
A5: Sección 1 | B5: IMPORTADO
B6: no | C6: 0 | D6: 0 | E6: =+D6*C6 -> 0 | F6: =IF(B6="si",D6*$F$4,0) -> 0 | G6: 0 | H6: =(D6+F6+G6)*$H$4 -> 0 | I6: =IF(B6="si",(D6+F6+G6+H6)*$I$4,0) -> 0 | J6: =D6+F6+G6+H6+I6 -> 0 | K6: =J6*$K$4 -> 0 | L6: =J6*C6 -> 0 | M6: =(J6+K6)*$M$4/(1-$M$4) -> 0 | N6: =M6+J6+K6 -> 0 | O6: =N6*C6 -> 0
B7: no | C7: 0 | D7: 0 | E7: =+D7*C7 -> 0 | F7: =IF(B7="si",D7*$F$4,0) -> 0 | G7: =(D7+F7)*$G$4 -> 0 | H7: =(D7+F7+G7)*$H$4 -> 0 | I7: =IF(B7="si",(D7+F7+G7+H7)*$I$4,0) -> 0 | J7: =D7+F7+G7+H7+I7 -> 0 | K7: =J7*$K$4 -> 0 | L7: =J7*C7 -> 0 | M7: =J7*$M$4/(1-$M$4) -> 0 | N7: =M7+J7 -> 0 | O7: =N7*C7 -> 0
B8: no | C8: 0 | D8: 0 | E8: =+D8*C8 -> 0 | F8: =IF(B8="si",D8*$F$4,0) -> 0 | G8: =(D8+F8)*$G$4 -> 0 | H8: =(D8+F8+G8)*$H$4 -> 0 | I8: =IF(B8="si",(D8+F8+G8+H8)*$I$4,0) -> 0 | J8: =D8+F8+G8+H8+I8 -> 0 | K8: =J8*$K$4 -> 0 | L8: =J8*C8 -> 0 | M8: =J8*$M$4/(1-$M$4) -> 0 | N8: =M8+J8 -> 0 | O8: =N8*C8 -> 0
B9: no | D9: 0 | E9: =+D9*C9 -> 0 | F9: =IF(B9="si",D9*$F$4,0) -> 0 | G9: =(D9+F9)*$G$4 -> 0 | H9: =(D9+F9+G9)*$H$4 -> 0 | I9: =IF(B9="si",(D9+F9+G9+H9)*$I$4,0) -> 0 | J9: =D9+F9+G9+H9+I9 -> 0 | K9: =J9*$K$4 -> 0 | L9: =J9*C9 -> 0 | M9: =J9*$M$4/(1-$M$4) -> 0 | N9: =M9+J9 -> 0 | O9: =N9*C9 -> 0
B10: no | D10: 0 | E10: =+D10*C10 -> 0 | F10: =IF(B10="si",D10*$F$4,0) -> 0 | G10: =(D10+F10)*$G$4 -> 0 | H10: =(D10+F10+G10)*$H$4 -> 0 | I10: =IF(B10="si",(D10+F10+G10+H10)*$I$4,0) -> 0 | J10: =D10+F10+G10+H10+I10 -> 0 | K10: =J10*$K$4 -> 0 | L10: =J10*C10 -> 0 | M10: =J10*$M$4/(1-$M$4) -> 0 | N10: =M10+J10 -> 0 | O10: =N10*C10 -> 0
B11: no | D11: 0 | E11: =+D11*C11 -> 0 | F11: =IF(B11="si",D11*$F$4,0) -> 0 | G11: =(D11+F11)*$G$4 -> 0 | H11: =(D11+F11+G11)*$H$4 -> 0 | I11: =IF(B11="si",(D11+F11+G11+H11)*$I$4,0) -> 0 | J11: =D11+F11+G11+H11+I11 -> 0 | K11: =J11*$K$4 -> 0 | L11: =J11*C11 -> 0 | M11: =J11*$M$4/(1-$M$4) -> 0 | N11: =M11+J11 -> 0 | O11: =N11*C11 -> 0
B12: no | D12: 0 | E12: =+D12*C12 -> 0 | F12: =IF(B12="si",D12*$F$4,0) -> 0 | G12: =(D12+F12)*$G$4 -> 0 | H12: =(D12+F12+G12)*$H$4 -> 0 | I12: =IF(B12="si",(D12+F12+G12+H12)*$I$4,0) -> 0 | J12: =D12+F12+G12+H12+I12 -> 0 | K12: =J12*$K$4 -> 0 | L12: =J12*C12 -> 0 | M12: =J12*$M$4/(1-$M$4) -> 0 | N12: =M12+J12 -> 0 | O12: =N12*C12 -> 0
A13: Sección 2 | F13: =IF(B13="si",D13*$F$4,0) -> 0 | I13: =IF(B13="si",(D13+F13+G13+H13)*$I$4,0) -> 0
D14: 0 | E14: =+C14*D14*(1-C23) -> 0 | F14: =IF(B14="si",D14*$F$4,0) -> 0 | G14: =(D14+F14)*$G$4 -> 0 | H14: =(D14+F14+G14)*$H$4 -> 0 | I14: =IF(B14="si",(D14+F14+G14+H14)*$I$4,0) -> 0 | J14: =D14+F14+G14+H14+I14 -> 0 | K14: =J14*$K$4 -> 0 | L14: =J14*C14 -> 0 | M14: =J14*$M$4/(1-$M$4) -> 0 | N14: =M14+J14 -> 0 | O14: =N14*C14 -> 0
D15: 0 | E15: =+C15*D15 -> 0 | F15: =IF(B15="si",D15*$F$4,0) -> 0 | G15: =(D15+F15)*$G$4 -> 0 | H15: =(D15+F15+G15)*$H$4 -> 0 | I15: =IF(B15="si",(D15+F15+G15+H15)*$I$4,0) -> 0 | J15: =D15+F15+G15+H15+I15 -> 0 | K15: =J15*$K$4 -> 0 | L15: =J15*C15 -> 0 | M15: =J15*$M$4/(1-$M$4) -> 0 | N15: =M15+J15 -> 0 | O15: =N15*C15 -> 0
D16: 0 | E16: =+C16*D16 -> 0 | F16: =IF(B16="si",D16*$F$4,0) -> 0 | G16: =(D16+F16)*$G$4 -> 0 | H16: =(D16+F16+G16)*$H$4 -> 0 | I16: =IF(B16="si",(D16+F16+G16+H16)*$I$4,0) -> 0 | J16: =D16+F16+G16+H16+I16 -> 0 | K16: =J16*$K$4 -> 0 | L16: =J16*C16 -> 0 | M16: =J16*$M$4/(1-$M$4) -> 0 | N16: =M16+J16 -> 0 | O16: =N16*C16 -> 0
D17: 0 | E17: =+C17*D17 -> 0 | F17: =IF(B17="si",D17*$F$4,0) -> 0 | G17: =(D17+F17)*$G$4 -> 0 | H17: =(D17+F17+G17)*$H$4 -> 0 | I17: =IF(B17="si",(D17+F17+G17+H17)*$I$4,0) -> 0 | J17: =D17+F17+G17+H17+I17 -> 0 | K17: =J17*$K$4 -> 0 | L17: =J17*C17 -> 0 | M17: =J17*$M$4/(1-$M$4) -> 0 | N17: =M17+J17 -> 0 | O17: =N17*C17 -> 0
D18: 0 | E18: =+C18*D18 -> 0 | F18: =IF(B18="si",D18*$F$4,0) -> 0 | G18: =(D18+F18)*$G$4 -> 0 | H18: =(D18+F18+G18)*$H$4 -> 0 | I18: =IF(B18="si",(D18+F18+G18+H18)*$I$4,0) -> 0 | J18: =D18+F18+G18+H18+I18 -> 0 | K18: =J18*$K$4 -> 0 | L18: =J18*C18 -> 0 | M18: =J18*$M$4/(1-$M$4) -> 0 | N18: =M18+J18 -> 0 | O18: =N18*C18 -> 0
A19: Sección 3 | F19: =IF(B19="si",D19*$F$4,0) -> 0 | I19: =IF(B19="si",(D19+F19+G19+H19)*$I$4,0) -> 0
D20: 0 | E20: =+C20*D20 -> 0 | F20: =IF(B20="si",D20*$F$4,0) -> 0 | G20: =(D20+F20)*$G$4 -> 0 | H20: =(D20+F20+G20)*$H$4 -> 0 | I20: =IF(B20="si",(D20+F20+G20+H20)*$I$4,0) -> 0 | J20: =D20+F20+G20+H20+I20 -> 0 | K20: =J20*$K$4 -> 0 | L20: =J20*C20 -> 0 | M20: =J20*$M$4/(1-$M$4) -> 0 | N20: =M20+J20 -> 0 | O20: =N20*C20 -> 0
D22: Total FOB | E22: =SUM(E6:E20) -> 0 | J22: Costo Nac. | L22: =SUM(L6:L20) -> 0 | N22: Total Venta | O22: =SUM(O6:O20) -> 0
N23: UTILIDAD | O23: =O22-L22 -> 0
A25: IMPORTADO
A26: si
A27: no

Sheet PRODUCTO I
A1: MATRIZ DE COSTO PROYECTO: | E1: =+Equipos!E1 -> 0
A3: PRODUCTO I | F3: Transporte | G3: Seguros | H3: IVA | I3: DAI | J3: Costo Untit | K3: Administración | L3: Costo total | M3: Margen GV | N3: Precio Venta | O3: Precio Venta
A4: Description | C4: Qty | D4: Costo Unit | E4: Costo Total | F4: 0 | G4: 0 | H4: 0 | I4: 0 | J4: Nacionalizado | K4: 0.03 | L4: Nacionaliado | M4: 0.23 | N4: Unitario | O4: Total
A5: Sección 1 | B5: IMPORTADO
B6: no | C6: 0 | D6: 0 | E6: =+D6*C6 -> 0 | F6: =IF(B6="si",D6*$F$4,0) -> 0 | G6: 0 | H6: =(D6+F6+G6)*$H$4 -> 0 | I6: =IF(B6="si",(D6+F6+G6+H6)*$I$4,0) -> 0 | J6: =D6+F6+G6+H6+I6 -> 0 | K6: =J6*$K$4 -> 0 | L6: =J6*C6 -> 0 | M6: =(J6+K6)*$M$4/(1-$M$4) -> 0 | N6: =M6+J6+K6 -> 0 | O6: =N6*C6 -> 0
B7: no | C7: 0 | D7: 0 | E7: =+D7*C7 -> 0 | F7: =IF(B7="si",D7*$F$4,0) -> 0 | G7: =(D7+F7)*$G$4 -> 0 | H7: =(D7+F7+G7)*$H$4 -> 0 | I7: =IF(B7="si",(D7+F7+G7+H7)*$I$4,0) -> 0 | J7: =D7+F7+G7+H7+I7 -> 0 | K7: =J7*$K$4 -> 0 | L7: =J7*C7 -> 0 | M7: =J7*$M$4/(1-$M$4) -> 0 | N7: =M7+J7 -> 0 | O7: =N7*C7 -> 0
B8: no | C8: 0 | D8: 0 | E8: =+D8*C8 -> 0 | F8: =IF(B8="si",D8*$F$4,0) -> 0 | G8: =(D8+F8)*$G$4 -> 0 | H8: =(D8+F8+G8)*$H$4 -> 0 | I8: =IF(B8="si",(D8+F8+G8+H8)*$I$4,0) -> 0 | J8: =D8+F8+G8+H8+I8 -> 0 | K8: =J8*$K$4 -> 0 | L8: =J8*C8 -> 0 | M8: =J8*$M$4/(1-$M$4) -> 0 | N8: =M8+J8 -> 0 | O8: =N8*C8 -> 0
B9: no | D9: 0 | E9: =+D9*C9 -> 0 | F9: =IF(B9="si",D9*$F$4,0) -> 0 | G9: =(D9+F9)*$G$4 -> 0 | H9: =(D9+F9+G9)*$H$4 -> 0 | I9: =IF(B9="si",(D9+F9+G9+H9)*$I$4,0) -> 0 | J9: =D9+F9+G9+H9+I9 -> 0 | K9: =J9*$K$4 -> 0 | L9: =J9*C9 -> 0 | M9: =J9*$M$4/(1-$M$4) -> 0 | N9: =M9+J9 -> 0 | O9: =N9*C9 -> 0
B10: no | D10: 0 | E10: =+D10*C10 -> 0 | F10: =IF(B10="si",D10*$F$4,0) -> 0 | G10: =(D10+F10)*$G$4 -> 0 | H10: =(D10+F10+G10)*$H$4 -> 0 | I10: =IF(B10="si",(D10+F10+G10+H10)*$I$4,0) -> 0 | J10: =D10+F10+G10+H10+I10 -> 0 | K10: =J10*$K$4 -> 0 | L10: =J10*C10 -> 0 | M10: =J10*$M$4/(1-$M$4) -> 0 | N10: =M10+J10 -> 0 | O10: =N10*C10 -> 0
B11: no | D11: 0 | E11: =+D11*C11 -> 0 | F11: =IF(B11="si",D11*$F$4,0) -> 0 | G11: =(D11+F11)*$G$4 -> 0 | H11: =(D11+F11+G11)*$H$4 -> 0 | I11: =IF(B11="si",(D11+F11+G11+H11)*$I$4,0) -> 0 | J11: =D11+F11+G11+H11+I11 -> 0 | K11: =J11*$K$4 -> 0 | L11: =J11*C11 -> 0 | M11: =J11*$M$4/(1-$M$4) -> 0 | N11: =M11+J11 -> 0 | O11: =N11*C11 -> 0
B12: no | D12: 0 | E12: =+D12*C12 -> 0 | F12: =IF(B12="si",D12*$F$4,0) -> 0 | G12: =(D12+F12)*$G$4 -> 0 | H12: =(D12+F12+G12)*$H$4 -> 0 | I12: =IF(B12="si",(D12+F12+G12+H12)*$I$4,0) -> 0 | J12: =D12+F12+G12+H12+I12 -> 0 | K12: =J12*$K$4 -> 0 | L12: =J12*C12 -> 0 | M12: =J12*$M$4/(1-$M$4) -> 0 | N12: =M12+J12 -> 0 | O12: =N12*C12 -> 0
A13: Sección 2 | F13: =IF(B13="si",D13*$F$4,0) -> 0 | I13: =IF(B13="si",(D13+F13+G13+H13)*$I$4,0) -> 0
D14: 0 | E14: =+C14*D14*(1-C23) -> 0 | F14: =IF(B14="si",D14*$F$4,0) -> 0 | G14: =(D14+F14)*$G$4 -> 0 | H14: =(D14+F14+G14)*$H$4 -> 0 | I14: =IF(B14="si",(D14+F14+G14+H14)*$I$4,0) -> 0 | J14: =D14+F14+G14+H14+I14 -> 0 | K14: =J14*$K$4 -> 0 | L14: =J14*C14 -> 0 | M14: =J14*$M$4/(1-$M$4) -> 0 | N14: =M14+J14 -> 0 | O14: =N14*C14 -> 0
D15: 0 | E15: =+C15*D15 -> 0 | F15: =IF(B15="si",D15*$F$4,0) -> 0 | G15: =(D15+F15)*$G$4 -> 0 | H15: =(D15+F15+G15)*$H$4 -> 0 | I15: =IF(B15="si",(D15+F15+G15+H15)*$I$4,0) -> 0 | J15: =D15+F15+G15+H15+I15 -> 0 | K15: =J15*$K$4 -> 0 | L15: =J15*C15 -> 0 | M15: =J15*$M$4/(1-$M$4) -> 0 | N15: =M15+J15 -> 0 | O15: =N15*C15 -> 0
D16: 0 | E16: =+C16*D16 -> 0 | F16: =IF(B16="si",D16*$F$4,0) -> 0 | G16: =(D16+F16)*$G$4 -> 0 | H16: =(D16+F16+G16)*$H$4 -> 0 | I16: =IF(B16="si",(D16+F16+G16+H16)*$I$4,0) -> 0 | J16: =D16+F16+G16+H16+I16 -> 0 | K16: =J16*$K$4 -> 0 | L16: =J16*C16 -> 0 | M16: =J16*$M$4/(1-$M$4) -> 0 | N16: =M16+J16 -> 0 | O16: =N16*C16 -> 0
D17: 0 | E17: =+C17*D17 -> 0 | F17: =IF(B17="si",D17*$F$4,0) -> 0 | G17: =(D17+F17)*$G$4 -> 0 | H17: =(D17+F17+G17)*$H$4 -> 0 | I17: =IF(B17="si",(D17+F17+G17+H17)*$I$4,0) -> 0 | J17: =D17+F17+G17+H17+I17 -> 0 | K17: =J17*$K$4 -> 0 | L17: =J17*C17 -> 0 | M17: =J17*$M$4/(1-$M$4) -> 0 | N17: =M17+J17 -> 0 | O17: =N17*C17 -> 0
D18: 0 | E18: =+C18*D18 -> 0 | F18: =IF(B18="si",D18*$F$4,0) -> 0 | G18: =(D18+F18)*$G$4 -> 0 | H18: =(D18+F18+G18)*$H$4 -> 0 | I18: =IF(B18="si",(D18+F18+G18+H18)*$I$4,0) -> 0 | J18: =D18+F18+G18+H18+I18 -> 0 | K18: =J18*$K$4 -> 0 | L18: =J18*C18 -> 0 | M18: =J18*$M$4/(1-$M$4) -> 0 | N18: =M18+J18 -> 0 | O18: =N18*C18 -> 0
A19: Sección 3 | F19: =IF(B19="si",D19*$F$4,0) -> 0 | I19: =IF(B19="si",(D19+F19+G19+H19)*$I$4,0) -> 0
D20: 0 | E20: =+C20*D20 -> 0 | F20: =IF(B20="si",D20*$F$4,0) -> 0 | G20: =(D20+F20)*$G$4 -> 0 | H20: =(D20+F20+G20)*$H$4 -> 0 | I20: =IF(B20="si",(D20+F20+G20+H20)*$I$4,0) -> 0 | J20: =D20+F20+G20+H20+I20 -> 0 | K20: =J20*$K$4 -> 0 | L20: =J20*C20 -> 0 | M20: =J20*$M$4/(1-$M$4) -> 0 | N20: =M20+J20 -> 0 | O20: =N20*C20 -> 0
D22: Total FOB | E22: =SUM(E6:E20) -> 0 | J22: Costo Nac. | L22: =SUM(L6:L20) -> 0 | N22: Total Venta | O22: =SUM(O6:O20) -> 0
N23: UTILIDAD | O23: =O22-L22 -> 0
A25: IMPORTADO
A26: si
A27: no

Sheet PRODUCTO J
A1: MATRIZ DE COSTO PROYECTO: | E1: =+Equipos!E1 -> 0
A3: PRODUCTO J | F3: Transporte | G3: Seguros | H3: IVA | I3: DAI | J3: Costo Untit | K3: Administración | L3: Costo total | M3: Margen GV | N3: Precio Venta | O3: Precio Venta
A4: Description | C4: Qty | D4: Costo Unit | E4: Costo Total | F4: 0 | G4: 0 | H4: 0 | I4: 0 | J4: Nacionalizado | K4: 0.03 | L4: Nacionaliado | M4: 0.23 | N4: Unitario | O4: Total
A5: Sección 1 | B5: IMPORTADO
B6: no | C6: 0 | D6: 0 | E6: =+D6*C6 -> 0 | F6: =IF(B6="si",D6*$F$4,0) -> 0 | G6: 0 | H6: =(D6+F6+G6)*$H$4 -> 0 | I6: =IF(B6="si",(D6+F6+G6+H6)*$I$4,0) -> 0 | J6: =D6+F6+G6+H6+I6 -> 0 | K6: =J6*$K$4 -> 0 | L6: =J6*C6 -> 0 | M6: =(J6+K6)*$M$4/(1-$M$4) -> 0 | N6: =M6+J6+K6 -> 0 | O6: =N6*C6 -> 0
B7: no | C7: 0 | D7: 0 | E7: =+D7*C7 -> 0 | F7: =IF(B7="si",D7*$F$4,0) -> 0 | G7: =(D7+F7)*$G$4 -> 0 | H7: =(D7+F7+G7)*$H$4 -> 0 | I7: =IF(B7="si",(D7+F7+G7+H7)*$I$4,0) -> 0 | J7: =D7+F7+G7+H7+I7 -> 0 | K7: =J7*$K$4 -> 0 | L7: =J7*C7 -> 0 | M7: =J7*$M$4/(1-$M$4) -> 0 | N7: =M7+J7 -> 0 | O7: =N7*C7 -> 0
B8: no | C8: 0 | D8: 0 | E8: =+D8*C8 -> 0 | F8: =IF(B8="si",D8*$F$4,0) -> 0 | G8: =(D8+F8)*$G$4 -> 0 | H8: =(D8+F8+G8)*$H$4 -> 0 | I8: =IF(B8="si",(D8+F8+G8+H8)*$I$4,0) -> 0 | J8: =D8+F8+G8+H8+I8 -> 0 | K8: =J8*$K$4 -> 0 | L8: =J8*C8 -> 0 | M8: =J8*$M$4/(1-$M$4) -> 0 | N8: =M8+J8 -> 0 | O8: =N8*C8 -> 0
B9: no | D9: 0 | E9: =+D9*C9 -> 0 | F9: =IF(B9="si",D9*$F$4,0) -> 0 | G9: =(D9+F9)*$G$4 -> 0 | H9: =(D9+F9+G9)*$H$4 -> 0 | I9: =IF(B9="si",(D9+F9+G9+H9)*$I$4,0) -> 0 | J9: =D9+F9+G9+H9+I9 -> 0 | K9: =J9*$K$4 -> 0 | L9: =J9*C9 -> 0 | M9: =J9*$M$4/(1-$M$4) -> 0 | N9: =M9+J9 -> 0 | O9: =N9*C9 -> 0
B10: no | D10: 0 | E10: =+D10*C10 -> 0 | F10: =IF(B10="si",D10*$F$4,0) -> 0 | G10: =(D10+F10)*$G$4 -> 0 | H10: =(D10+F10+G10)*$H$4 -> 0 | I10: =IF(B10="si",(D10+F10+G10+H10)*$I$4,0) -> 0 | J10: =D10+F10+G10+H10+I10 -> 0 | K10: =J10*$K$4 -> 0 | L10: =J10*C10 -> 0 | M10: =J10*$M$4/(1-$M$4) -> 0 | N10: =M10+J10 -> 0 | O10: =N10*C10 -> 0
B11: no | D11: 0 | E11: =+D11*C11 -> 0 | F11: =IF(B11="si",D11*$F$4,0) -> 0 | G11: =(D11+F11)*$G$4 -> 0 | H11: =(D11+F11+G11)*$H$4 -> 0 | I11: =IF(B11="si",(D11+F11+G11+H11)*$I$4,0) -> 0 | J11: =D11+F11+G11+H11+I11 -> 0 | K11: =J11*$K$4 -> 0 | L11: =J11*C11 -> 0 | M11: =J11*$M$4/(1-$M$4) -> 0 | N11: =M11+J11 -> 0 | O11: =N11*C11 -> 0
B12: no | D12: 0 | E12: =+D12*C12 -> 0 | F12: =IF(B12="si",D12*$F$4,0) -> 0 | G12: =(D12+F12)*$G$4 -> 0 | H12: =(D12+F12+G12)*$H$4 -> 0 | I12: =IF(B12="si",(D12+F12+G12+H12)*$I$4,0) -> 0 | J12: =D12+F12+G12+H12+I12 -> 0 | K12: =J12*$K$4 -> 0 | L12: =J12*C12 -> 0 | M12: =J12*$M$4/(1-$M$4) -> 0 | N12: =M12+J12 -> 0 | O12: =N12*C12 -> 0
A13: Sección 2 | F13: =IF(B13="si",D13*$F$4,0) -> 0 | I13: =IF(B13="si",(D13+F13+G13+H13)*$I$4,0) -> 0
D14: 0 | E14: =+C14*D14*(1-C23) -> 0 | F14: =IF(B14="si",D14*$F$4,0) -> 0 | G14: =(D14+F14)*$G$4 -> 0 | H14: =(D14+F14+G14)*$H$4 -> 0 | I14: =IF(B14="si",(D14+F14+G14+H14)*$I$4,0) -> 0 | J14: =D14+F14+G14+H14+I14 -> 0 | K14: =J14*$K$4 -> 0 | L14: =J14*C14 -> 0 | M14: =J14*$M$4/(1-$M$4) -> 0 | N14: =M14+J14 -> 0 | O14: =N14*C14 -> 0
D15: 0 | E15: =+C15*D15 -> 0 | F15: =IF(B15="si",D15*$F$4,0) -> 0 | G15: =(D15+F15)*$G$4 -> 0 | H15: =(D15+F15+G15)*$H$4 -> 0 | I15: =IF(B15="si",(D15+F15+G15+H15)*$I$4,0) -> 0 | J15: =D15+F15+G15+H15+I15 -> 0 | K15: =J15*$K$4 -> 0 | L15: =J15*C15 -> 0 | M15: =J15*$M$4/(1-$M$4) -> 0 | N15: =M15+J15 -> 0 | O15: =N15*C15 -> 0
D16: 0 | E16: =+C16*D16 -> 0 | F16: =IF(B16="si",D16*$F$4,0) -> 0 | G16: =(D16+F16)*$G$4 -> 0 | H16: =(D16+F16+G16)*$H$4 -> 0 | I16: =IF(B16="si",(D16+F16+G16+H16)*$I$4,0) -> 0 | J16: =D16+F16+G16+H16+I16 -> 0 | K16: =J16*$K$4 -> 0 | L16: =J16*C16 -> 0 | M16: =J16*$M$4/(1-$M$4) -> 0 | N16: =M16+J16 -> 0 | O16: =N16*C16 -> 0
D17: 0 | E17: =+C17*D17 -> 0 | F17: =IF(B17="si",D17*$F$4,0) -> 0 | G17: =(D17+F17)*$G$4 -> 0 | H17: =(D17+F17+G17)*$H$4 -> 0 | I17: =IF(B17="si",(D17+F17+G17+H17)*$I$4,0) -> 0 | J17: =D17+F17+G17+H17+I17 -> 0 | K17: =J17*$K$4 -> 0 | L17: =J17*C17 -> 0 | M17: =J17*$M$4/(1-$M$4) -> 0 | N17: =M17+J17 -> 0 | O17: =N17*C17 -> 0
D18: 0 | E18: =+C18*D18 -> 0 | F18: =IF(B18="si",D18*$F$4,0) -> 0 | G18: =(D18+F18)*$G$4 -> 0 | H18: =(D18+F18+G18)*$H$4 -> 0 | I18: =IF(B18="si",(D18+F18+G18+H18)*$I$4,0) -> 0 | J18: =D18+F18+G18+H18+I18 -> 0 | K18: =J18*$K$4 -> 0 | L18: =J18*C18 -> 0 | M18: =J18*$M$4/(1-$M$4) -> 0 | N18: =M18+J18 -> 0 | O18: =N18*C18 -> 0
A19: Sección 3 | F19: =IF(B19="si",D19*$F$4,0) -> 0 | I19: =IF(B19="si",(D19+F19+G19+H19)*$I$4,0) -> 0
D20: 0 | E20: =+C20*D20 -> 0 | F20: =IF(B20="si",D20*$F$4,0) -> 0 | G20: =(D20+F20)*$G$4 -> 0 | H20: =(D20+F20+G20)*$H$4 -> 0 | I20: =IF(B20="si",(D20+F20+G20+H20)*$I$4,0) -> 0 | J20: =D20+F20+G20+H20+I20 -> 0 | K20: =J20*$K$4 -> 0 | L20: =J20*C20 -> 0 | M20: =J20*$M$4/(1-$M$4) -> 0 | N20: =M20+J20 -> 0 | O20: =N20*C20 -> 0
D22: Total FOB | E22: =SUM(E6:E20) -> 0 | J22: Costo Nac. | L22: =SUM(L6:L20) -> 0 | N22: Total Venta | O22: =SUM(O6:O20) -> 0
N23: UTILIDAD | O23: =O22-L22 -> 0
A25: IMPORTADO
A26: si
A27: no

Sheet PRODUCTO K
A1: MATRIZ DE COSTO PROYECTO: | E1: =+Equipos!E1 -> 0
A3: PRODUCTO K | F3: Transporte | G3: Seguros | H3: IVA | I3: DAI | J3: Costo Untit | K3: Administración | L3: Costo total | M3: Margen GV | N3: Precio Venta | O3: Precio Venta
A4: Description | C4: Qty | D4: Costo Unit | E4: Costo Total | F4: 0 | G4: 0 | H4: 0 | I4: 0 | J4: Nacionalizado | K4: 0.03 | L4: Nacionaliado | M4: 0.23 | N4: Unitario | O4: Total
A5: Sección 1 | B5: IMPORTADO
B6: no | C6: 0 | D6: 0 | E6: =+D6*C6 -> 0 | F6: =IF(B6="si",D6*$F$4,0) -> 0 | G6: 0 | H6: =(D6+F6+G6)*$H$4 -> 0 | I6: =IF(B6="si",(D6+F6+G6+H6)*$I$4,0) -> 0 | J6: =D6+F6+G6+H6+I6 -> 0 | K6: =J6*$K$4 -> 0 | L6: =J6*C6 -> 0 | M6: =(J6+K6)*$M$4/(1-$M$4) -> 0 | N6: =M6+J6+K6 -> 0 | O6: =N6*C6 -> 0
B7: no | C7: 0 | D7: 0 | E7: =+D7*C7 -> 0 | F7: =IF(B7="si",D7*$F$4,0) -> 0 | G7: =(D7+F7)*$G$4 -> 0 | H7: =(D7+F7+G7)*$H$4 -> 0 | I7: =IF(B7="si",(D7+F7+G7+H7)*$I$4,0) -> 0 | J7: =D7+F7+G7+H7+I7 -> 0 | K7: =J7*$K$4 -> 0 | L7: =J7*C7 -> 0 | M7: =J7*$M$4/(1-$M$4) -> 0 | N7: =M7+J7 -> 0 | O7: =N7*C7 -> 0
B8: no | C8: 0 | D8: 0 | E8: =+D8*C8 -> 0 | F8: =IF(B8="si",D8*$F$4,0) -> 0 | G8: =(D8+F8)*$G$4 -> 0 | H8: =(D8+F8+G8)*$H$4 -> 0 | I8: =IF(B8="si",(D8+F8+G8+H8)*$I$4,0) -> 0 | J8: =D8+F8+G8+H8+I8 -> 0 | K8: =J8*$K$4 -> 0 | L8: =J8*C8 -> 0 | M8: =J8*$M$4/(1-$M$4) -> 0 | N8: =M8+J8 -> 0 | O8: =N8*C8 -> 0
B9: no | D9: 0 | E9: =+D9*C9 -> 0 | F9: =IF(B9="si",D9*$F$4,0) -> 0 | G9: =(D9+F9)*$G$4 -> 0 | H9: =(D9+F9+G9)*$H$4 -> 0 | I9: =IF(B9="si",(D9+F9+G9+H9)*$I$4,0) -> 0 | J9: =D9+F9+G9+H9+I9 -> 0 | K9: =J9*$K$4 -> 0 | L9: =J9*C9 -> 0 | M9: =J9*$M$4/(1-$M$4) -> 0 | N9: =M9+J9 -> 0 | O9: =N9*C9 -> 0
B10: no | D10: 0 | E10: =+D10*C10 -> 0 | F10: =IF(B10="si",D10*$F$4,0) -> 0 | G10: =(D10+F10)*$G$4 -> 0 | H10: =(D10+F10+G10)*$H$4 -> 0 | I10: =IF(B10="si",(D10+F10+G10+H10)*$I$4,0) -> 0 | J10: =D10+F10+G10+H10+I10 -> 0 | K10: =J10*$K$4 -> 0 | L10: =J10*C10 -> 0 | M10: =J10*$M$4/(1-$M$4) -> 0 | N10: =M10+J10 -> 0 | O10: =N10*C10 -> 0
B11: no | D11: 0 | E11: =+D11*C11 -> 0 | F11: =IF(B11="si",D11*$F$4,0) -> 0 | G11: =(D11+F11)*$G$4 -> 0 | H11: =(D11+F11+G11)*$H$4 -> 0 | I11: =IF(B11="si",(D11+F11+G11+H11)*$I$4,0) -> 0 | J11: =D11+F11+G11+H11+I11 -> 0 | K11: =J11*$K$4 -> 0 | L11: =J11*C11 -> 0 | M11: =J11*$M$4/(1-$M$4) -> 0 | N11: =M11+J11 -> 0 | O11: =N11*C11 -> 0
B12: no | D12: 0 | E12: =+D12*C12 -> 0 | F12: =IF(B12="si",D12*$F$4,0) -> 0 | G12: =(D12+F12)*$G$4 -> 0 | H12: =(D12+F12+G12)*$H$4 -> 0 | I12: =IF(B12="si",(D12+F12+G12+H12)*$I$4,0) -> 0 | J12: =D12+F12+G12+H12+I12 -> 0 | K12: =J12*$K$4 -> 0 | L12: =J12*C12 -> 0 | M12: =J12*$M$4/(1-$M$4) -> 0 | N12: =M12+J12 -> 0 | O12: =N12*C12 -> 0
A13: Sección 2 | F13: =IF(B13="si",D13*$F$4,0) -> 0 | I13: =IF(B13="si",(D13+F13+G13+H13)*$I$4,0) -> 0
D14: 0 | E14: =+C14*D14*(1-C23) -> 0 | F14: =IF(B14="si",D14*$F$4,0) -> 0 | G14: =(D14+F14)*$G$4 -> 0 | H14: =(D14+F14+G14)*$H$4 -> 0 | I14: =IF(B14="si",(D14+F14+G14+H14)*$I$4,0) -> 0 | J14: =D14+F14+G14+H14+I14 -> 0 | K14: =J14*$K$4 -> 0 | L14: =J14*C14 -> 0 | M14: =J14*$M$4/(1-$M$4) -> 0 | N14: =M14+J14 -> 0 | O14: =N14*C14 -> 0
D15: 0 | E15: =+C15*D15 -> 0 | F15: =IF(B15="si",D15*$F$4,0) -> 0 | G15: =(D15+F15)*$G$4 -> 0 | H15: =(D15+F15+G15)*$H$4 -> 0 | I15: =IF(B15="si",(D15+F15+G15+H15)*$I$4,0) -> 0 | J15: =D15+F15+G15+H15+I15 -> 0 | K15: =J15*$K$4 -> 0 | L15: =J15*C15 -> 0 | M15: =J15*$M$4/(1-$M$4) -> 0 | N15: =M15+J15 -> 0 | O15: =N15*C15 -> 0
D16: 0 | E16: =+C16*D16 -> 0 | F16: =IF(B16="si",D16*$F$4,0) -> 0 | G16: =(D16+F16)*$G$4 -> 0 | H16: =(D16+F16+G16)*$H$4 -> 0 | I16: =IF(B16="si",(D16+F16+G16+H16)*$I$4,0) -> 0 | J16: =D16+F16+G16+H16+I16 -> 0 | K16: =J16*$K$4 -> 0 | L16: =J16*C16 -> 0 | M16: =J16*$M$4/(1-$M$4) -> 0 | N16: =M16+J16 -> 0 | O16: =N16*C16 -> 0
D17: 0 | E17: =+C17*D17 -> 0 | F17: =IF(B17="si",D17*$F$4,0) -> 0 | G17: =(D17+F17)*$G$4 -> 0 | H17: =(D17+F17+G17)*$H$4 -> 0 | I17: =IF(B17="si",(D17+F17+G17+H17)*$I$4,0) -> 0 | J17: =D17+F17+G17+H17+I17 -> 0 | K17: =J17*$K$4 -> 0 | L17: =J17*C17 -> 0 | M17: =J17*$M$4/(1-$M$4) -> 0 | N17: =M17+J17 -> 0 | O17: =N17*C17 -> 0
D18: 0 | E18: =+C18*D18 -> 0 | F18: =IF(B18="si",D18*$F$4,0) -> 0 | G18: =(D18+F18)*$G$4 -> 0 | H18: =(D18+F18+G18)*$H$4 -> 0 | I18: =IF(B18="si",(D18+F18+G18+H18)*$I$4,0) -> 0 | J18: =D18+F18+G18+H18+I18 -> 0 | K18: =J18*$K$4 -> 0 | L18: =J18*C18 -> 0 | M18: =J18*$M$4/(1-$M$4) -> 0 | N18: =M18+J18 -> 0 | O18: =N18*C18 -> 0
A19: Sección 3 | F19: =IF(B19="si",D19*$F$4,0) -> 0 | I19: =IF(B19="si",(D19+F19+G19+H19)*$I$4,0) -> 0
D20: 0 | E20: =+C20*D20 -> 0 | F20: =IF(B20="si",D20*$F$4,0) -> 0 | G20: =(D20+F20)*$G$4 -> 0 | H20: =(D20+F20+G20)*$H$4 -> 0 | I20: =IF(B20="si",(D20+F20+G20+H20)*$I$4,0) -> 0 | J20: =D20+F20+G20+H20+I20 -> 0 | K20: =J20*$K$4 -> 0 | L20: =J20*C20 -> 0 | M20: =J20*$M$4/(1-$M$4) -> 0 | N20: =M20+J20 -> 0 | O20: =N20*C20 -> 0
D22: Total FOB | E22: =SUM(E6:E20) -> 0 | J22: Costo Nac. | L22: =SUM(L6:L20) -> 0 | N22: Total Venta | O22: =SUM(O6:O20) -> 0
N23: UTILIDAD | O23: =O22-L22 -> 0
A25: IMPORTADO
A26: si
A27: no

Sheet PRODUCTO L
A1: MATRIZ DE COSTO PROYECTO: | E1: =+Equipos!E1 -> 0
A3: PRODUCTO L | F3: Transporte | G3: Seguros | H3: IVA | I3: DAI | J3: Costo Untit | K3: Administración | L3: Costo total | M3: Margen GV | N3: Precio Venta | O3: Precio Venta
A4: Description | C4: Qty | D4: Costo Unit | E4: Costo Total | F4: 0 | G4: 0 | H4: 0 | I4: 0 | J4: Nacionalizado | K4: 0.03 | L4: Nacionaliado | M4: 0.23 | N4: Unitario | O4: Total
A5: Sección 1 | B5: IMPORTADO
B6: no | C6: 0 | D6: 0 | E6: =+D6*C6 -> 0 | F6: =IF(B6="si",D6*$F$4,0) -> 0 | G6: 0 | H6: =(D6+F6+G6)*$H$4 -> 0 | I6: =IF(B6="si",(D6+F6+G6+H6)*$I$4,0) -> 0 | J6: =D6+F6+G6+H6+I6 -> 0 | K6: =J6*$K$4 -> 0 | L6: =J6*C6 -> 0 | M6: =(J6+K6)*$M$4/(1-$M$4) -> 0 | N6: =M6+J6+K6 -> 0 | O6: =N6*C6 -> 0
B7: no | C7: 0 | D7: 0 | E7: =+D7*C7 -> 0 | F7: =IF(B7="si",D7*$F$4,0) -> 0 | G7: =(D7+F7)*$G$4 -> 0 | H7: =(D7+F7+G7)*$H$4 -> 0 | I7: =IF(B7="si",(D7+F7+G7+H7)*$I$4,0) -> 0 | J7: =D7+F7+G7+H7+I7 -> 0 | K7: =J7*$K$4 -> 0 | L7: =J7*C7 -> 0 | M7: =J7*$M$4/(1-$M$4) -> 0 | N7: =M7+J7 -> 0 | O7: =N7*C7 -> 0
B8: no | C8: 0 | D8: 0 | E8: =+D8*C8 -> 0 | F8: =IF(B8="si",D8*$F$4,0) -> 0 | G8: =(D8+F8)*$G$4 -> 0 | H8: =(D8+F8+G8)*$H$4 -> 0 | I8: =IF(B8="si",(D8+F8+G8+H8)*$I$4,0) -> 0 | J8: =D8+F8+G8+H8+I8 -> 0 | K8: =J8*$K$4 -> 0 | L8: =J8*C8 -> 0 | M8: =J8*$M$4/(1-$M$4) -> 0 | N8: =M8+J8 -> 0 | O8: =N8*C8 -> 0
B9: no | D9: 0 | E9: =+D9*C9 -> 0 | F9: =IF(B9="si",D9*$F$4,0) -> 0 | G9: =(D9+F9)*$G$4 -> 0 | H9: =(D9+F9+G9)*$H$4 -> 0 | I9: =IF(B9="si",(D9+F9+G9+H9)*$I$4,0) -> 0 | J9: =D9+F9+G9+H9+I9 -> 0 | K9: =J9*$K$4 -> 0 | L9: =J9*C9 -> 0 | M9: =J9*$M$4/(1-$M$4) -> 0 | N9: =M9+J9 -> 0 | O9: =N9*C9 -> 0
B10: no | D10: 0 | E10: =+D10*C10 -> 0 | F10: =IF(B10="si",D10*$F$4,0) -> 0 | G10: =(D10+F10)*$G$4 -> 0 | H10: =(D10+F10+G10)*$H$4 -> 0 | I10: =IF(B10="si",(D10+F10+G10+H10)*$I$4,0) -> 0 | J10: =D10+F10+G10+H10+I10 -> 0 | K10: =J10*$K$4 -> 0 | L10: =J10*C10 -> 0 | M10: =J10*$M$4/(1-$M$4) -> 0 | N10: =M10+J10 -> 0 | O10: =N10*C10 -> 0
B11: no | D11: 0 | E11: =+D11*C11 -> 0 | F11: =IF(B11="si",D11*$F$4,0) -> 0 | G11: =(D11+F11)*$G$4 -> 0 | H11: =(D11+F11+G11)*$H$4 -> 0 | I11: =IF(B11="si",(D11+F11+G11+H11)*$I$4,0) -> 0 | J11: =D11+F11+G11+H11+I11 -> 0 | K11: =J11*$K$4 -> 0 | L11: =J11*C11 -> 0 | M11: =J11*$M$4/(1-$M$4) -> 0 | N11: =M11+J11 -> 0 | O11: =N11*C11 -> 0
B12: no | D12: 0 | E12: =+D12*C12 -> 0 | F12: =IF(B12="si",D12*$F$4,0) -> 0 | G12: =(D12+F12)*$G$4 -> 0 | H12: =(D12+F12+G12)*$H$4 -> 0 | I12: =IF(B12="si",(D12+F12+G12+H12)*$I$4,0) -> 0 | J12: =D12+F12+G12+H12+I12 -> 0 | K12: =J12*$K$4 -> 0 | L12: =J12*C12 -> 0 | M12: =J12*$M$4/(1-$M$4) -> 0 | N12: =M12+J12 -> 0 | O12: =N12*C12 -> 0
A13: Sección 2 | F13: =IF(B13="si",D13*$F$4,0) -> 0 | I13: =IF(B13="si",(D13+F13+G13+H13)*$I$4,0) -> 0
D14: 0 | E14: =+C14*D14*(1-C23) -> 0 | F14: =IF(B14="si",D14*$F$4,0) -> 0 | G14: =(D14+F14)*$G$4 -> 0 | H14: =(D14+F14+G14)*$H$4 -> 0 | I14: =IF(B14="si",(D14+F14+G14+H14)*$I$4,0) -> 0 | J14: =D14+F14+G14+H14+I14 -> 0 | K14: =J14*$K$4 -> 0 | L14: =J14*C14 -> 0 | M14: =J14*$M$4/(1-$M$4) -> 0 | N14: =M14+J14 -> 0 | O14: =N14*C14 -> 0
D15: 0 | E15: =+C15*D15 -> 0 | F15: =IF(B15="si",D15*$F$4,0) -> 0 | G15: =(D15+F15)*$G$4 -> 0 | H15: =(D15+F15+G15)*$H$4 -> 0 | I15: =IF(B15="si",(D15+F15+G15+H15)*$I$4,0) -> 0 | J15: =D15+F15+G15+H15+I15 -> 0 | K15: =J15*$K$4 -> 0 | L15: =J15*C15 -> 0 | M15: =J15*$M$4/(1-$M$4) -> 0 | N15: =M15+J15 -> 0 | O15: =N15*C15 -> 0
D16: 0 | E16: =+C16*D16 -> 0 | F16: =IF(B16="si",D16*$F$4,0) -> 0 | G16: =(D16+F16)*$G$4 -> 0 | H16: =(D16+F16+G16)*$H$4 -> 0 | I16: =IF(B16="si",(D16+F16+G16+H16)*$I$4,0) -> 0 | J16: =D16+F16+G16+H16+I16 -> 0 | K16: =J16*$K$4 -> 0 | L16: =J16*C16 -> 0 | M16: =J16*$M$4/(1-$M$4) -> 0 | N16: =M16+J16 -> 0 | O16: =N16*C16 -> 0
D17: 0 | E17: =+C17*D17 -> 0 | F17: =IF(B17="si",D17*$F$4,0) -> 0 | G17: =(D17+F17)*$G$4 -> 0 | H17: =(D17+F17+G17)*$H$4 -> 0 | I17: =IF(B17="si",(D17+F17+G17+H17)*$I$4,0) -> 0 | J17: =D17+F17+G17+H17+I17 -> 0 | K17: =J17*$K$4 -> 0 | L17: =J17*C17 -> 0 | M17: =J17*$M$4/(1-$M$4) -> 0 | N17: =M17+J17 -> 0 | O17: =N17*C17 -> 0
D18: 0 | E18: =+C18*D18 -> 0 | F18: =IF(B18="si",D18*$F$4,0) -> 0 | G18: =(D18+F18)*$G$4 -> 0 | H18: =(D18+F18+G18)*$H$4 -> 0 | I18: =IF(B18="si",(D18+F18+G18+H18)*$I$4,0) -> 0 | J18: =D18+F18+G18+H18+I18 -> 0 | K18: =J18*$K$4 -> 0 | L18: =J18*C18 -> 0 | M18: =J18*$M$4/(1-$M$4) -> 0 | N18: =M18+J18 -> 0 | O18: =N18*C18 -> 0
A19: Sección 3 | F19: =IF(B19="si",D19*$F$4,0) -> 0 | I19: =IF(B19="si",(D19+F19+G19+H19)*$I$4,0) -> 0
D20: 0 | E20: =+C20*D20 -> 0 | F20: =IF(B20="si",D20*$F$4,0) -> 0 | G20: =(D20+F20)*$G$4 -> 0 | H20: =(D20+F20+G20)*$H$4 -> 0 | I20: =IF(B20="si",(D20+F20+G20+H20)*$I$4,0) -> 0 | J20: =D20+F20+G20+H20+I20 -> 0 | K20: =J20*$K$4 -> 0 | L20: =J20*C20 -> 0 | M20: =J20*$M$4/(1-$M$4) -> 0 | N20: =M20+J20 -> 0 | O20: =N20*C20 -> 0
D22: Total FOB | E22: =SUM(E6:E20) -> 0 | J22: Costo Nac. | L22: =SUM(L6:L20) -> 0 | N22: Total Venta | O22: =SUM(O6:O20) -> 0
N23: UTILIDAD | O23: =O22-L22 -> 0
A25: IMPORTADO
A26: si
A27: no

Sheet PRODUCTO M
A1: MATRIZ DE COSTO PROYECTO: | E1: =+Equipos!E1 -> 0
A3: PRODUCTO M | F3: Transporte | G3: Seguros | H3: IVA | I3: DAI | J3: Costo Untit | K3: Administración | L3: Costo total | M3: Margen GV | N3: Precio Venta | O3: Precio Venta
A4: Description | C4: Qty | D4: Costo Unit | E4: Costo Total | F4: 0 | G4: 0 | H4: 0 | I4: 0 | J4: Nacionalizado | K4: 0.03 | L4: Nacionaliado | M4: 0.23 | N4: Unitario | O4: Total
A5: Sección 1 | B5: IMPORTADO
B6: no | C6: 0 | D6: 0 | E6: =+D6*C6 -> 0 | F6: =IF(B6="si",D6*$F$4,0) -> 0 | G6: 0 | H6: =(D6+F6+G6)*$H$4 -> 0 | I6: =IF(B6="si",(D6+F6+G6+H6)*$I$4,0) -> 0 | J6: =D6+F6+G6+H6+I6 -> 0 | K6: =J6*$K$4 -> 0 | L6: =J6*C6 -> 0 | M6: =(J6+K6)*$M$4/(1-$M$4) -> 0 | N6: =M6+J6+K6 -> 0 | O6: =N6*C6 -> 0
B7: no | C7: 0 | D7: 0 | E7: =+D7*C7 -> 0 | F7: =IF(B7="si",D7*$F$4,0) -> 0 | G7: =(D7+F7)*$G$4 -> 0 | H7: =(D7+F7+G7)*$H$4 -> 0 | I7: =IF(B7="si",(D7+F7+G7+H7)*$I$4,0) -> 0 | J7: =D7+F7+G7+H7+I7 -> 0 | K7: =J7*$K$4 -> 0 | L7: =J7*C7 -> 0 | M7: =J7*$M$4/(1-$M$4) -> 0 | N7: =M7+J7 -> 0 | O7: =N7*C7 -> 0
B8: no | C8: 0 | D8: 0 | E8: =+D8*C8 -> 0 | F8: =IF(B8="si",D8*$F$4,0) -> 0 | G8: =(D8+F8)*$G$4 -> 0 | H8: =(D8+F8+G8)*$H$4 -> 0 | I8: =IF(B8="si",(D8+F8+G8+H8)*$I$4,0) -> 0 | J8: =D8+F8+G8+H8+I8 -> 0 | K8: =J8*$K$4 -> 0 | L8: =J8*C8 -> 0 | M8: =J8*$M$4/(1-$M$4) -> 0 | N8: =M8+J8 -> 0 | O8: =N8*C8 -> 0
B9: no | D9: 0 | E9: =+D9*C9 -> 0 | F9: =IF(B9="si",D9*$F$4,0) -> 0 | G9: =(D9+F9)*$G$4 -> 0 | H9: =(D9+F9+G9)*$H$4 -> 0 | I9: =IF(B9="si",(D9+F9+G9+H9)*$I$4,0) -> 0 | J9: =D9+F9+G9+H9+I9 -> 0 | K9: =J9*$K$4 -> 0 | L9: =J9*C9 -> 0 | M9: =J9*$M$4/(1-$M$4) -> 0 | N9: =M9+J9 -> 0 | O9: =N9*C9 -> 0
B10: no | D10: 0 | E10: =+D10*C10 -> 0 | F10: =IF(B10="si",D10*$F$4,0) -> 0 | G10: =(D10+F10)*$G$4 -> 0 | H10: =(D10+F10+G10)*$H$4 -> 0 | I10: =IF(B10="si",(D10+F10+G10+H10)*$I$4,0) -> 0 | J10: =D10+F10+G10+H10+I10 -> 0 | K10: =J10*$K$4 -> 0 | L10: =J10*C10 -> 0 | M10: =J10*$M$4/(1-$M$4) -> 0 | N10: =M10+J10 -> 0 | O10: =N10*C10 -> 0
B11: no | D11: 0 | E11: =+D11*C11 -> 0 | F11: =IF(B11="si",D11*$F$4,0) -> 0 | G11: =(D11+F11)*$G$4 -> 0 | H11: =(D11+F11+G11)*$H$4 -> 0 | I11: =IF(B11="si",(D11+F11+G11+H11)*$I$4,0) -> 0 | J11: =D11+F11+G11+H11+I11 -> 0 | K11: =J11*$K$4 -> 0 | L11: =J11*C11 -> 0 | M11: =J11*$M$4/(1-$M$4) -> 0 | N11: =M11+J11 -> 0 | O11: =N11*C11 -> 0
B12: no | D12: 0 | E12: =+D12*C12 -> 0 | F12: =IF(B12="si",D12*$F$4,0) -> 0 | G12: =(D12+F12)*$G$4 -> 0 | H12: =(D12+F12+G12)*$H$4 -> 0 | I12: =IF(B12="si",(D12+F12+G12+H12)*$I$4,0) -> 0 | J12: =D12+F12+G12+H12+I12 -> 0 | K12: =J12*$K$4 -> 0 | L12: =J12*C12 -> 0 | M12: =J12*$M$4/(1-$M$4) -> 0 | N12: =M12+J12 -> 0 | O12: =N12*C12 -> 0
A13: Sección 2 | F13: =IF(B13="si",D13*$F$4,0) -> 0 | I13: =IF(B13="si",(D13+F13+G13+H13)*$I$4,0) -> 0
D14: 0 | E14: =+C14*D14*(1-C23) -> 0 | F14: =IF(B14="si",D14*$F$4,0) -> 0 | G14: =(D14+F14)*$G$4 -> 0 | H14: =(D14+F14+G14)*$H$4 -> 0 | I14: =IF(B14="si",(D14+F14+G14+H14)*$I$4,0) -> 0 | J14: =D14+F14+G14+H14+I14 -> 0 | K14: =J14*$K$4 -> 0 | L14: =J14*C14 -> 0 | M14: =J14*$M$4/(1-$M$4) -> 0 | N14: =M14+J14 -> 0 | O14: =N14*C14 -> 0
D15: 0 | E15: =+C15*D15 -> 0 | F15: =IF(B15="si",D15*$F$4,0) -> 0 | G15: =(D15+F15)*$G$4 -> 0 | H15: =(D15+F15+G15)*$H$4 -> 0 | I15: =IF(B15="si",(D15+F15+G15+H15)*$I$4,0) -> 0 | J15: =D15+F15+G15+H15+I15 -> 0 | K15: =J15*$K$4 -> 0 | L15: =J15*C15 -> 0 | M15: =J15*$M$4/(1-$M$4) -> 0 | N15: =M15+J15 -> 0 | O15: =N15*C15 -> 0
D16: 0 | E16: =+C16*D16 -> 0 | F16: =IF(B16="si",D16*$F$4,0) -> 0 | G16: =(D16+F16)*$G$4 -> 0 | H16: =(D16+F16+G16)*$H$4 -> 0 | I16: =IF(B16="si",(D16+F16+G16+H16)*$I$4,0) -> 0 | J16: =D16+F16+G16+H16+I16 -> 0 | K16: =J16*$K$4 -> 0 | L16: =J16*C16 -> 0 | M16: =J16*$M$4/(1-$M$4) -> 0 | N16: =M16+J16 -> 0 | O16: =N16*C16 -> 0
D17: 0 | E17: =+C17*D17 -> 0 | F17: =IF(B17="si",D17*$F$4,0) -> 0 | G17: =(D17+F17)*$G$4 -> 0 | H17: =(D17+F17+G17)*$H$4 -> 0 | I17: =IF(B17="si",(D17+F17+G17+H17)*$I$4,0) -> 0 | J17: =D17+F17+G17+H17+I17 -> 0 | K17: =J17*$K$4 -> 0 | L17: =J17*C17 -> 0 | M17: =J17*$M$4/(1-$M$4) -> 0 | N17: =M17+J17 -> 0 | O17: =N17*C17 -> 0
D18: 0 | E18: =+C18*D18 -> 0 | F18: =IF(B18="si",D18*$F$4,0) -> 0 | G18: =(D18+F18)*$G$4 -> 0 | H18: =(D18+F18+G18)*$H$4 -> 0 | I18: =IF(B18="si",(D18+F18+G18+H18)*$I$4,0) -> 0 | J18: =D18+F18+G18+H18+I18 -> 0 | K18: =J18*$K$4 -> 0 | L18: =J18*C18 -> 0 | M18: =J18*$M$4/(1-$M$4) -> 0 | N18: =M18+J18 -> 0 | O18: =N18*C18 -> 0
A19: Sección 3 | F19: =IF(B19="si",D19*$F$4,0) -> 0 | I19: =IF(B19="si",(D19+F19+G19+H19)*$I$4,0) -> 0
D20: 0 | E20: =+C20*D20 -> 0 | F20: =IF(B20="si",D20*$F$4,0) -> 0 | G20: =(D20+F20)*$G$4 -> 0 | H20: =(D20+F20+G20)*$H$4 -> 0 | I20: =IF(B20="si",(D20+F20+G20+H20)*$I$4,0) -> 0 | J20: =D20+F20+G20+H20+I20 -> 0 | K20: =J20*$K$4 -> 0 | L20: =J20*C20 -> 0 | M20: =J20*$M$4/(1-$M$4) -> 0 | N20: =M20+J20 -> 0 | O20: =N20*C20 -> 0
D22: Total FOB | E22: =SUM(E6:E20) -> 0 | J22: Costo Nac. | L22: =SUM(L6:L20) -> 0 | N22: Total Venta | O22: =SUM(O6:O20) -> 0
N23: UTILIDAD | O23: =O22-L22 -> 0
A25: IMPORTADO
A26: si
A27: no

Sheet PRODUCTO N
A1: MATRIZ DE COSTO PROYECTO: | E1: =+Equipos!E1 -> 0
A3: PRODUCTO N | F3: Transporte | G3: Seguros | H3: IVA | I3: DAI | J3: Costo Untit | K3: Administración | L3: Costo total | M3: Margen GV | N3: Precio Venta | O3: Precio Venta
A4: Description | C4: Qty | D4: Costo Unit | E4: Costo Total | F4: 0 | G4: 0 | H4: 0 | I4: 0 | J4: Nacionalizado | K4: 0.03 | L4: Nacionaliado | M4: 0.23 | N4: Unitario | O4: Total
A5: Sección 1 | B5: IMPORTADO
B6: no | C6: 0 | D6: 0 | E6: =+D6*C6 -> 0 | F6: =IF(B6="si",D6*$F$4,0) -> 0 | G6: 0 | H6: =(D6+F6+G6)*$H$4 -> 0 | I6: =IF(B6="si",(D6+F6+G6+H6)*$I$4,0) -> 0 | J6: =D6+F6+G6+H6+I6 -> 0 | K6: =J6*$K$4 -> 0 | L6: =J6*C6 -> 0 | M6: =(J6+K6)*$M$4/(1-$M$4) -> 0 | N6: =M6+J6+K6 -> 0 | O6: =N6*C6 -> 0
B7: no | C7: 0 | D7: 0 | E7: =+D7*C7 -> 0 | F7: =IF(B7="si",D7*$F$4,0) -> 0 | G7: =(D7+F7)*$G$4 -> 0 | H7: =(D7+F7+G7)*$H$4 -> 0 | I7: =IF(B7="si",(D7+F7+G7+H7)*$I$4,0) -> 0 | J7: =D7+F7+G7+H7+I7 -> 0 | K7: =J7*$K$4 -> 0 | L7: =J7*C7 -> 0 | M7: =J7*$M$4/(1-$M$4) -> 0 | N7: =M7+J7 -> 0 | O7: =N7*C7 -> 0
B8: no | C8: 0 | D8: 0 | E8: =+D8*C8 -> 0 | F8: =IF(B8="si",D8*$F$4,0) -> 0 | G8: =(D8+F8)*$G$4 -> 0 | H8: =(D8+F8+G8)*$H$4 -> 0 | I8: =IF(B8="si",(D8+F8+G8+H8)*$I$4,0) -> 0 | J8: =D8+F8+G8+H8+I8 -> 0 | K8: =J8*$K$4 -> 0 | L8: =J8*C8 -> 0 | M8: =J8*$M$4/(1-$M$4) -> 0 | N8: =M8+J8 -> 0 | O8: =N8*C8 -> 0
B9: no | D9: 0 | E9: =+D9*C9 -> 0 | F9: =IF(B9="si",D9*$F$4,0) -> 0 | G9: =(D9+F9)*$G$4 -> 0 | H9: =(D9+F9+G9)*$H$4 -> 0 | I9: =IF(B9="si",(D9+F9+G9+H9)*$I$4,0) -> 0 | J9: =D9+F9+G9+H9+I9 -> 0 | K9: =J9*$K$4 -> 0 | L9: =J9*C9 -> 0 | M9: =J9*$M$4/(1-$M$4) -> 0 | N9: =M9+J9 -> 0 | O9: =N9*C9 -> 0
B10: no | D10: 0 | E10: =+D10*C10 -> 0 | F10: =IF(B10="si",D10*$F$4,0) -> 0 | G10: =(D10+F10)*$G$4 -> 0 | H10: =(D10+F10+G10)*$H$4 -> 0 | I10: =IF(B10="si",(D10+F10+G10+H10)*$I$4,0) -> 0 | J10: =D10+F10+G10+H10+I10 -> 0 | K10: =J10*$K$4 -> 0 | L10: =J10*C10 -> 0 | M10: =J10*$M$4/(1-$M$4) -> 0 | N10: =M10+J10 -> 0 | O10: =N10*C10 -> 0
B11: no | D11: 0 | E11: =+D11*C11 -> 0 | F11: =IF(B11="si",D11*$F$4,0) -> 0 | G11: =(D11+F11)*$G$4 -> 0 | H11: =(D11+F11+G11)*$H$4 -> 0 | I11: =IF(B11="si",(D11+F11+G11+H11)*$I$4,0) -> 0 | J11: =D11+F11+G11+H11+I11 -> 0 | K11: =J11*$K$4 -> 0 | L11: =J11*C11 -> 0 | M11: =J11*$M$4/(1-$M$4) -> 0 | N11: =M11+J11 -> 0 | O11: =N11*C11 -> 0
B12: no | D12: 0 | E12: =+D12*C12 -> 0 | F12: =IF(B12="si",D12*$F$4,0) -> 0 | G12: =(D12+F12)*$G$4 -> 0 | H12: =(D12+F12+G12)*$H$4 -> 0 | I12: =IF(B12="si",(D12+F12+G12+H12)*$I$4,0) -> 0 | J12: =D12+F12+G12+H12+I12 -> 0 | K12: =J12*$K$4 -> 0 | L12: =J12*C12 -> 0 | M12: =J12*$M$4/(1-$M$4) -> 0 | N12: =M12+J12 -> 0 | O12: =N12*C12 -> 0
A13: Sección 2 | F13: =IF(B13="si",D13*$F$4,0) -> 0 | I13: =IF(B13="si",(D13+F13+G13+H13)*$I$4,0) -> 0
D14: 0 | E14: =+C14*D14*(1-C23) -> 0 | F14: =IF(B14="si",D14*$F$4,0) -> 0 | G14: =(D14+F14)*$G$4 -> 0 | H14: =(D14+F14+G14)*$H$4 -> 0 | I14: =IF(B14="si",(D14+F14+G14+H14)*$I$4,0) -> 0 | J14: =D14+F14+G14+H14+I14 -> 0 | K14: =J14*$K$4 -> 0 | L14: =J14*C14 -> 0 | M14: =J14*$M$4/(1-$M$4) -> 0 | N14: =M14+J14 -> 0 | O14: =N14*C14 -> 0
D15: 0 | E15: =+C15*D15 -> 0 | F15: =IF(B15="si",D15*$F$4,0) -> 0 | G15: =(D15+F15)*$G$4 -> 0 | H15: =(D15+F15+G15)*$H$4 -> 0 | I15: =IF(B15="si",(D15+F15+G15+H15)*$I$4,0) -> 0 | J15: =D15+F15+G15+H15+I15 -> 0 | K15: =J15*$K$4 -> 0 | L15: =J15*C15 -> 0 | M15: =J15*$M$4/(1-$M$4) -> 0 | N15: =M15+J15 -> 0 | O15: =N15*C15 -> 0
D16: 0 | E16: =+C16*D16 -> 0 | F16: =IF(B16="si",D16*$F$4,0) -> 0 | G16: =(D16+F16)*$G$4 -> 0 | H16: =(D16+F16+G16)*$H$4 -> 0 | I16: =IF(B16="si",(D16+F16+G16+H16)*$I$4,0) -> 0 | J16: =D16+F16+G16+H16+I16 -> 0 | K16: =J16*$K$4 -> 0 | L16: =J16*C16 -> 0 | M16: =J16*$M$4/(1-$M$4) -> 0 | N16: =M16+J16 -> 0 | O16: =N16*C16 -> 0
D17: 0 | E17: =+C17*D17 -> 0 | F17: =IF(B17="si",D17*$F$4,0) -> 0 | G17: =(D17+F17)*$G$4 -> 0 | H17: =(D17+F17+G17)*$H$4 -> 0 | I17: =IF(B17="si",(D17+F17+G17+H17)*$I$4,0) -> 0 | J17: =D17+F17+G17+H17+I17 -> 0 | K17: =J17*$K$4 -> 0 | L17: =J17*C17 -> 0 | M17: =J17*$M$4/(1-$M$4) -> 0 | N17: =M17+J17 -> 0 | O17: =N17*C17 -> 0
D18: 0 | E18: =+C18*D18 -> 0 | F18: =IF(B18="si",D18*$F$4,0) -> 0 | G18: =(D18+F18)*$G$4 -> 0 | H18: =(D18+F18+G18)*$H$4 -> 0 | I18: =IF(B18="si",(D18+F18+G18+H18)*$I$4,0) -> 0 | J18: =D18+F18+G18+H18+I18 -> 0 | K18: =J18*$K$4 -> 0 | L18: =J18*C18 -> 0 | M18: =J18*$M$4/(1-$M$4) -> 0 | N18: =M18+J18 -> 0 | O18: =N18*C18 -> 0
A19: Sección 3 | F19: =IF(B19="si",D19*$F$4,0) -> 0 | I19: =IF(B19="si",(D19+F19+G19+H19)*$I$4,0) -> 0
D20: 0 | E20: =+C20*D20 -> 0 | F20: =IF(B20="si",D20*$F$4,0) -> 0 | G20: =(D20+F20)*$G$4 -> 0 | H20: =(D20+F20+G20)*$H$4 -> 0 | I20: =IF(B20="si",(D20+F20+G20+H20)*$I$4,0) -> 0 | J20: =D20+F20+G20+H20+I20 -> 0 | K20: =J20*$K$4 -> 0 | L20: =J20*C20 -> 0 | M20: =J20*$M$4/(1-$M$4) -> 0 | N20: =M20+J20 -> 0 | O20: =N20*C20 -> 0
D22: Total FOB | E22: =SUM(E6:E20) -> 0 | J22: Costo Nac. | L22: =SUM(L6:L20) -> 0 | N22: Total Venta | O22: =SUM(O6:O20) -> 0
N23: UTILIDAD | O23: =O22-L22 -> 0
A25: IMPORTADO
A26: si
A27: no

Sheet PRODUCTO O
A1: MATRIZ DE COSTO PROYECTO: | E1: =+Equipos!E1 -> 0
A3: PRODUCTO O | F3: Transporte | G3: Seguros | H3: IVA | I3: DAI | J3: Costo Untit | K3: Administración | L3: Costo total | M3: Margen GV | N3: Precio Venta | O3: Precio Venta
A4: Description | C4: Qty | D4: Costo Unit | E4: Costo Total | F4: 0 | G4: 0 | H4: 0 | I4: 0 | J4: Nacionalizado | K4: 0.03 | L4: Nacionaliado | M4: 0.23 | N4: Unitario | O4: Total
A5: Sección 1 | B5: IMPORTADO
B6: no | C6: 0 | D6: 0 | E6: =+D6*C6 -> 0 | F6: =IF(B6="si",D6*$F$4,0) -> 0 | G6: 0 | H6: =(D6+F6+G6)*$H$4 -> 0 | I6: =IF(B6="si",(D6+F6+G6+H6)*$I$4,0) -> 0 | J6: =D6+F6+G6+H6+I6 -> 0 | K6: =J6*$K$4 -> 0 | L6: =J6*C6 -> 0 | M6: =(J6+K6)*$M$4/(1-$M$4) -> 0 | N6: =M6+J6+K6 -> 0 | O6: =N6*C6 -> 0
B7: no | C7: 0 | D7: 0 | E7: =+D7*C7 -> 0 | F7: =IF(B7="si",D7*$F$4,0) -> 0 | G7: =(D7+F7)*$G$4 -> 0 | H7: =(D7+F7+G7)*$H$4 -> 0 | I7: =IF(B7="si",(D7+F7+G7+H7)*$I$4,0) -> 0 | J7: =D7+F7+G7+H7+I7 -> 0 | K7: =J7*$K$4 -> 0 | L7: =J7*C7 -> 0 | M7: =J7*$M$4/(1-$M$4) -> 0 | N7: =M7+J7 -> 0 | O7: =N7*C7 -> 0
B8: no | C8: 0 | D8: 0 | E8: =+D8*C8 -> 0 | F8: =IF(B8="si",D8*$F$4,0) -> 0 | G8: =(D8+F8)*$G$4 -> 0 | H8: =(D8+F8+G8)*$H$4 -> 0 | I8: =IF(B8="si",(D8+F8+G8+H8)*$I$4,0) -> 0 | J8: =D8+F8+G8+H8+I8 -> 0 | K8: =J8*$K$4 -> 0 | L8: =J8*C8 -> 0 | M8: =J8*$M$4/(1-$M$4) -> 0 | N8: =M8+J8 -> 0 | O8: =N8*C8 -> 0
B9: no | D9: 0 | E9: =+D9*C9 -> 0 | F9: =IF(B9="si",D9*$F$4,0) -> 0 | G9: =(D9+F9)*$G$4 -> 0 | H9: =(D9+F9+G9)*$H$4 -> 0 | I9: =IF(B9="si",(D9+F9+G9+H9)*$I$4,0) -> 0 | J9: =D9+F9+G9+H9+I9 -> 0 | K9: =J9*$K$4 -> 0 | L9: =J9*C9 -> 0 | M9: =J9*$M$4/(1-$M$4) -> 0 | N9: =M9+J9 -> 0 | O9: =N9*C9 -> 0
B10: no | D10: 0 | E10: =+D10*C10 -> 0 | F10: =IF(B10="si",D10*$F$4,0) -> 0 | G10: =(D10+F10)*$G$4 -> 0 | H10: =(D10+F10+G10)*$H$4 -> 0 | I10: =IF(B10="si",(D10+F10+G10+H10)*$I$4,0) -> 0 | J10: =D10+F10+G10+H10+I10 -> 0 | K10: =J10*$K$4 -> 0 | L10: =J10*C10 -> 0 | M10: =J10*$M$4/(1-$M$4) -> 0 | N10: =M10+J10 -> 0 | O10: =N10*C10 -> 0
B11: no | D11: 0 | E11: =+D11*C11 -> 0 | F11: =IF(B11="si",D11*$F$4,0) -> 0 | G11: =(D11+F11)*$G$4 -> 0 | H11: =(D11+F11+G11)*$H$4 -> 0 | I11: =IF(B11="si",(D11+F11+G11+H11)*$I$4,0) -> 0 | J11: =D11+F11+G11+H11+I11 -> 0 | K11: =J11*$K$4 -> 0 | L11: =J11*C11 -> 0 | M11: =J11*$M$4/(1-$M$4) -> 0 | N11: =M11+J11 -> 0 | O11: =N11*C11 -> 0
B12: no | D12: 0 | E12: =+D12*C12 -> 0 | F12: =IF(B12="si",D12*$F$4,0) -> 0 | G12: =(D12+F12)*$G$4 -> 0 | H12: =(D12+F12+G12)*$H$4 -> 0 | I12: =IF(B12="si",(D12+F12+G12+H12)*$I$4,0) -> 0 | J12: =D12+F12+G12+H12+I12 -> 0 | K12: =J12*$K$4 -> 0 | L12: =J12*C12 -> 0 | M12: =J12*$M$4/(1-$M$4) -> 0 | N12: =M12+J12 -> 0 | O12: =N12*C12 -> 0
A13: Sección 2 | F13: =IF(B13="si",D13*$F$4,0) -> 0 | I13: =IF(B13="si",(D13+F13+G13+H13)*$I$4,0) -> 0
D14: 0 | E14: =+C14*D14*(1-C23) -> 0 | F14: =IF(B14="si",D14*$F$4,0) -> 0 | G14: =(D14+F14)*$G$4 -> 0 | H14: =(D14+F14+G14)*$H$4 -> 0 | I14: =IF(B14="si",(D14+F14+G14+H14)*$I$4,0) -> 0 | J14: =D14+F14+G14+H14+I14 -> 0 | K14: =J14*$K$4 -> 0 | L14: =J14*C14 -> 0 | M14: =J14*$M$4/(1-$M$4) -> 0 | N14: =M14+J14 -> 0 | O14: =N14*C14 -> 0
D15: 0 | E15: =+C15*D15 -> 0 | F15: =IF(B15="si",D15*$F$4,0) -> 0 | G15: =(D15+F15)*$G$4 -> 0 | H15: =(D15+F15+G15)*$H$4 -> 0 | I15: =IF(B15="si",(D15+F15+G15+H15)*$I$4,0) -> 0 | J15: =D15+F15+G15+H15+I15 -> 0 | K15: =J15*$K$4 -> 0 | L15: =J15*C15 -> 0 | M15: =J15*$M$4/(1-$M$4) -> 0 | N15: =M15+J15 -> 0 | O15: =N15*C15 -> 0
D16: 0 | E16: =+C16*D16 -> 0 | F16: =IF(B16="si",D16*$F$4,0) -> 0 | G16: =(D16+F16)*$G$4 -> 0 | H16: =(D16+F16+G16)*$H$4 -> 0 | I16: =IF(B16="si",(D16+F16+G16+H16)*$I$4,0) -> 0 | J16: =D16+F16+G16+H16+I16 -> 0 | K16: =J16*$K$4 -> 0 | L16: =J16*C16 -> 0 | M16: =J16*$M$4/(1-$M$4) -> 0 | N16: =M16+J16 -> 0 | O16: =N16*C16 -> 0
D17: 0 | E17: =+C17*D17 -> 0 | F17: =IF(B17="si",D17*$F$4,0) -> 0 | G17: =(D17+F17)*$G$4 -> 0 | H17: =(D17+F17+G17)*$H$4 -> 0 | I17: =IF(B17="si",(D17+F17+G17+H17)*$I$4,0) -> 0 | J17: =D17+F17+G17+H17+I17 -> 0 | K17: =J17*$K$4 -> 0 | L17: =J17*C17 -> 0 | M17: =J17*$M$4/(1-$M$4) -> 0 | N17: =M17+J17 -> 0 | O17: =N17*C17 -> 0
D18: 0 | E18: =+C18*D18 -> 0 | F18: =IF(B18="si",D18*$F$4,0) -> 0 | G18: =(D18+F18)*$G$4 -> 0 | H18: =(D18+F18+G18)*$H$4 -> 0 | I18: =IF(B18="si",(D18+F18+G18+H18)*$I$4,0) -> 0 | J18: =D18+F18+G18+H18+I18 -> 0 | K18: =J18*$K$4 -> 0 | L18: =J18*C18 -> 0 | M18: =J18*$M$4/(1-$M$4) -> 0 | N18: =M18+J18 -> 0 | O18: =N18*C18 -> 0
A19: Sección 3 | F19: =IF(B19="si",D19*$F$4,0) -> 0 | I19: =IF(B19="si",(D19+F19+G19+H19)*$I$4,0) -> 0
D20: 0 | E20: =+C20*D20 -> 0 | F20: =IF(B20="si",D20*$F$4,0) -> 0 | G20: =(D20+F20)*$G$4 -> 0 | H20: =(D20+F20+G20)*$H$4 -> 0 | I20: =IF(B20="si",(D20+F20+G20+H20)*$I$4,0) -> 0 | J20: =D20+F20+G20+H20+I20 -> 0 | K20: =J20*$K$4 -> 0 | L20: =J20*C20 -> 0 | M20: =J20*$M$4/(1-$M$4) -> 0 | N20: =M20+J20 -> 0 | O20: =N20*C20 -> 0
D22: Total FOB | E22: =SUM(E6:E20) -> 0 | J22: Costo Nac. | L22: =SUM(L6:L20) -> 0 | N22: Total Venta | O22: =SUM(O6:O20) -> 0
N23: UTILIDAD | O23: =O22-L22 -> 0
A25: IMPORTADO
A26: si
A27: no

Sheet RESUMEN (OPEX)
B1: Resumen de Costos por Componente | F1: Tasa $ | G1: 25
B2: RESUMEN DE PROYECTO - CCTV
B3: Resumen del Proyecto | C3: Costo | D3: % del costo | E3: % de venta | F3: P. Venta | G3: Margen X Componente
A4: CCTV | B4: =Equipos!B3 -> Productos 1 | C4: 0 | D4: =IFERROR(C4/$C$12,"") | E4: =+Equipos!N4 -> 0.274 | F4: =Tabla24[[#This Row],[Costo]]/(1-Tabla24[[#This Row],[% de venta]]) -> 0 | G4: =+Tabla24[[#This Row],[P. Venta ]]-Tabla24[[#This Row],[Costo]] -> 0
B5: =+'Productos 2'!A3 -> Productos 2 | C5: =+'Productos 2'!L17 -> 0 | D5: =IFERROR(C5/$C$12,"") | E5: =+'Productos 2'!M4 -> 0.3 | F5: =Tabla24[[#This Row],[Costo]]/(1-Tabla24[[#This Row],[% de venta]]) -> 0 | G5: =+Tabla24[[#This Row],[P. Venta ]]-Tabla24[[#This Row],[Costo]] -> 0
B6: =+'Productos 3'!A3 -> Productos 3 | C6: =+'Productos 3'!L22 -> 0 | D6: =IFERROR(C6/$C$12,"") | E6: =+'Productos 3'!M4 -> 0.3 | F6: =Tabla24[[#This Row],[Costo]]/(1-Tabla24[[#This Row],[% de venta]]) -> 0 | G6: =+Tabla24[[#This Row],[P. Venta ]]-Tabla24[[#This Row],[Costo]] -> 0
B7: =+'Productos 4'!A3 -> Productos 4 | C7: =+'Productos 4'!L21 -> 0 | D7: =IFERROR(C7/$C$12,"") | E7: =+'Productos 4'!M4 -> 0.3 | F7: =Tabla24[[#This Row],[Costo]]/(1-Tabla24[[#This Row],[% de venta]]) -> 0 | G7: =+Tabla24[[#This Row],[P. Venta ]]-Tabla24[[#This Row],[Costo]] -> 0
B8: =+'Productos 5'!A3 -> Productos 5 | C8: =+'Productos 5'!L25 -> 0 | D8: =IFERROR(C8/$C$12,"") | E8: =+'Productos 5'!M4 -> 0.3 | F8: =Tabla24[[#This Row],[Costo]]/(1-Tabla24[[#This Row],[% de venta]]) -> 0 | G8: =+Tabla24[[#This Row],[P. Venta ]]-Tabla24[[#This Row],[Costo]] -> 0
A9: Materiales/otros | B9: =+MATERIALES!A3 -> Materiales | C9: =+MATERIALES!L46 -> 0 | D9: =IFERROR(C9/$C$12,"") | E9: =+MATERIALES!M4 -> 0.3 | F9: =Tabla24[[#This Row],[Costo]]/(1-Tabla24[[#This Row],[% de venta]]) -> 0 | G9: =+Tabla24[[#This Row],[P. Venta ]]-Tabla24[[#This Row],[Costo]] -> 0
B10: =+'OPEX GV'!A3 -> OPEX GV | C10: =+'OPEX GV'!L17 -> 0 | D10: =IFERROR(C10/$C$12,"") | E10: =+'OPEX GV'!M4 -> 0.274 | F10: =Tabla24[[#This Row],[Costo]]/(1-Tabla24[[#This Row],[% de venta]]) -> 0 | G10: =+Tabla24[[#This Row],[P. Venta ]]-Tabla24[[#This Row],[Costo]] -> 0
A11: OPEX | B11: =+'OPEX Proyecto'!A3 -> OPEX | C11: =+'OPEX Proyecto'!L24 -> 0 | D11: =IFERROR(C11/$C$12,"") | E11: =+'OPEX Proyecto'!M4 -> 0.3 | F11: =Tabla24[[#This Row],[Costo]]/(1-Tabla24[[#This Row],[% de venta]]) -> 0 | G11: =+Tabla24[[#This Row],[P. Venta ]]-Tabla24[[#This Row],[Costo]] -> 0
B12: TOTALES | C12: =SUBTOTAL(109,C4:C11) -> 0 | D12: =SUBTOTAL(109,D4:D11) -> 0 | E12: =+AVERAGE(E4:E11) -> 0.2935 | F12: =SUBTOTAL(109,F4:F11) -> 0 | G12: =SUBTOTAL(109,G4:G11) -> 0
H14: OPCIÓN DE SERVICIOS POR 4 AÑOS
B15: Ingresos | C15: =F12 -> 0 | H15: Monto | I15: =+F12 -> 0 | J15: Int.s | K15: 0.1
B16: Costos | C16: =C12 -> 0 | H16: Plazo | I16: 48
B17: Margen bruto | C17: =C15-C16 -> 0 | H17: Cuota | I17: =PMT(K15/12,I16,-I15) -> 0
B18: Opex | C18: =C11 -> 0 | H18: TIR | I18: =IFERROR('Evaluacion TIR-VAN'!F45,"")
B19: Opex administrativo | D19: 6530.4621 | H19: Utilidad Neta del Ejercicio | J19: ='Evaluacion TIR-VAN'!H47 -> 0 | K19: =IFERROR(J19/I15,"")
B20: Comisiones | C20: =C15*3% -> 0
B21: Utilidad Operativa | C21: =+C17-SUM(C18:C20) -> 0
B22: Fianzas | C22: 0
B23: Costo financiero | C23: 0 | I23: =I17*574 -> 0
B24: Utilidad antes de ISR | C24: =C21-C22-C23 -> 0
B25: ISR | C25: =C24*Tabla24[[#This Row],[% del costo]] -> 0 | D25: =_xlfn.IFS(C24<=D34,C34,C24<=D35,C35,C24>D36,C36) -> 0.1
B26: Utilidad neta | C26: =C24-C25 -> 0 | D26: =IFERROR(Tabla24[[#This Row],[Costo]]/F12,"")
B29: Utilidad Neta del Ejercicio | C29: =C26 -> 0 | D29: =IFERROR(+C29/F12,"")
A32: Hasta | B32: IMPUESTO SOBRE LA RENTA COSTA RICA
A33: Hasta | B33: Ingresos brutos | C33: Tarifa(Se aplica sobre renta neta total) | D33: Ingresos Brutos $
A34: Mayor de | B34: 54303000 | C34: 0.1 | D34: =B34/565 -> 96111.504
B35: 109228000 | C35: 0.2 | D35: =B35/565 -> 193323.89 | F35: =_xlfn.IFS(C14<=D34,C34,C14<=D35,C35,C14>D36,C36) -> 0.1
B36: 109228000 | C36: 0.3 | D36: =B36/565 -> 193323.89

Sheet OPEX GV
A1: MATRIZ DE COSTO PROYECTO: | E1: =+Equipos!E1 -> 0
A3: OPEX GV | F3: Transporte | G3: Imprevistos | H3: IVA | I3: DAI | J3: Costo Untit | K3: Administración | L3: Costo total | M3: Margen GV | N3: Precio Venta | O3: Precio Venta | P3: Financ.
A4: Description | C4: Qty | D4: Costo Unit | E4: Costo Total | F4: 0.1 | G4: 0.03 | H4: 0 | I4: 0.14 | J4: Nacionalizado | K4: 0.03 | L4: Nacionaliado | M4: =+Equipos!N4 -> 0.274 | N4: Unitario | O4: Total
A5: Sección 1 | B5: IMPORTADO
A6: GVCR configuración del sistema - Días | B6: no | C6: 0 | D6: =+'MANO DE OBRA '!G9+'MANO DE OBRA '!K9 -> 0 | E6: =+D6*C6 -> 0 | F6: =IF(B6="si",D6*$F$4,0) -> 0 | G6: =(D6+F6)*$G$4 -> 0 | H6: =(D6+F6+G6)*$H$4 -> 0 | I6: =IF(B6="si",(D6+F6+G6+H6)*$I$4,0) -> 0 | J6: =D6+F6+G6+H6+I6 -> 0 | K6: =J6*$K$4 -> 0 | L6: =(J6+K6)*C6 -> 0 | M6: =(J6+K6)*$M$4/(1-$M$4) -> 0 | N6: =M6+J6+K6 -> 0 | O6: =N6*C6 -> 0
A7: Instalación de equipos MO | B7: no | C7: 0 | D7: 100 | E7: =+D7*C7 -> 0 | F7: =IF(B7="si",D7*$F$4,0) -> 0 | G7: =(D7+F7)*$G$4 -> 3 | H7: =(D7+F7+G7)*$H$4 -> 0 | I7: =IF(B7="si",(D7+F7+G7+H7)*$I$4,0) -> 0 | J7: =D7+F7+G7+H7+I7 -> 103 | K7: =J7*$K$4 -> 3.09 | L7: =(J7+K7)*C7 -> 0 | M7: =(J7+K7)*$M$4/(1-$M$4) -> 40.039477 | N7: =M7+J7+K7 -> 146.12948 | O7: =N7*C7 -> 0
A8: Mano de obra contratista | B8: no | C8: 0 | D8: 100 | E8: =+D8*C8 -> 0 | F8: =IF(B8="si",D8*$F$4,0) -> 0 | G8: =(D8+F8)*$G$4 -> 3 | H8: =(D8+F8+G8)*$H$4 -> 0 | I8: =IF(B8="si",(D8+F8+G8+H8)*$I$4,0) -> 0 | J8: =D8+F8+G8+H8+I8 -> 103 | K8: =J8*$K$4 -> 3.09 | L8: =(J8+K8)*C8 -> 0 | M8: =(J8+K8)*$M$4/(1-$M$4) -> 40.039477 | N8: =M8+J8+K8 -> 146.12948 | O8: =N8*C8 -> 0
A9: Imprevistos | B9: no | C9: 0 | D9: 100 | E9: =+D9*C9 -> 0 | F9: =IF(B9="si",D9*$F$4,0) -> 0 | G9: =(D9+F9)*$G$4 -> 3 | H9: =(D9+F9+G9)*$H$4 -> 0 | I9: =IF(B9="si",(D9+F9+G9+H9)*$I$4,0) -> 0 | J9: =D9+F9+G9+H9+I9 -> 103 | K9: =J9*$K$4 -> 3.09 | L9: =(J9+K9)*C9 -> 0 | M9: =(J9+K9)*$M$4/(1-$M$4) -> 40.039477 | N9: =M9+J9+K9 -> 146.12948 | O9: =N9*C9 -> 0
A10: Materiales | B10: no | C10: 0 | D10: 100 | E10: =+D10*C10 -> 0 | F10: =IF(B10="si",D10*$F$4,0) -> 0 | G10: =(D10+F10)*$G$4 -> 3 | H10: =(D10+F10+G10)*$H$4 -> 0 | I10: =IF(B10="si",(D10+F10+G10+H10)*$I$4,0) -> 0 | J10: =D10+F10+G10+H10+I10 -> 103 | K10: =J10*$K$4 -> 3.09 | L10: =(J10+K10)*C10 -> 0 | M10: =(J10+K10)*$M$4/(1-$M$4) -> 40.039477 | N10: =M10+J10+K10 -> 146.12948 | O10: =N10*C10 -> 0
B11: no | C11: 0 | D11: 100 | E11: =+C11*D11*(1-C18) -> 0 | F11: =IF(B11="si",D11*$F$4,0) -> 0 | G11: =(D11+F11)*$G$4 -> 3 | H11: =(D11+F11+G11)*$H$4 -> 0 | I11: =IF(B11="si",(D11+F11+G11+H11)*$I$4,0) -> 0 | J11: =D11+F11+G11+H11+I11 -> 103 | K11: =J11*$K$4 -> 3.09 | L11: =(J11+K11)*C11 -> 0 | M11: =(J11+K11)*$M$4/(1-$M$4) -> 40.039477 | N11: =M11+J11+K11 -> 146.12948 | O11: =N11*C11 -> 0
B12: no | C12: 0 | D12: 100 | E12: =+C12*D12 -> 0 | F12: =IF(B12="si",D12*$F$4,0) -> 0 | G12: =(D12+F12)*$G$4 -> 3 | H12: =(D12+F12+G12)*$H$4 -> 0 | I12: =IF(B12="si",(D12+F12+G12+H12)*$I$4,0) -> 0 | J12: =D12+F12+G12+H12+I12 -> 103 | K12: =J12*$K$4 -> 3.09 | L12: =(J12+K12)*C12 -> 0 | M12: =(J12+K12)*$M$4/(1-$M$4) -> 40.039477 | N12: =M12+J12+K12 -> 146.12948 | O12: =N12*C12 -> 0
B13: no | C13: 0 | D13: 100 | E13: =+C13*D13 -> 0 | F13: =IF(B13="si",D13*$F$4,0) -> 0 | G13: =(D13+F13)*$G$4 -> 3 | H13: =(D13+F13+G13)*$H$4 -> 0 | I13: =IF(B13="si",(D13+F13+G13+H13)*$I$4,0) -> 0 | J13: =D13+F13+G13+H13+I13 -> 103 | K13: =J13*$K$4 -> 3.09 | L13: =(J13+K13)*C13 -> 0 | M13: =(J13+K13)*$M$4/(1-$M$4) -> 40.039477 | N13: =M13+J13+K13 -> 146.12948 | O13: =N13*C13 -> 0
B14: no | C14: 0 | D14: 100 | E14: =+C14*D14 -> 0 | F14: =IF(B14="si",D14*$F$4,0) -> 0 | G14: =(D14+F14)*$G$4 -> 3 | H14: =(D14+F14+G14)*$H$4 -> 0 | I14: =IF(B14="si",(D14+F14+G14+H14)*$I$4,0) -> 0 | J14: =D14+F14+G14+H14+I14 -> 103 | K14: =J14*$K$4 -> 3.09 | L14: =(J14+K14)*C14 -> 0 | M14: =(J14+K14)*$M$4/(1-$M$4) -> 40.039477 | N14: =M14+J14+K14 -> 146.12948 | O14: =N14*C14 -> 0
B15: no | C15: 0 | D15: 100 | E15: =+C15*D15 -> 0 | F15: =IF(B15="si",D15*$F$4,0) -> 0 | G15: =(D15+F15)*$G$4 -> 3 | H15: =(D15+F15+G15)*$H$4 -> 0 | I15: =IF(B15="si",(D15+F15+G15+H15)*$I$4,0) -> 0 | J15: =D15+F15+G15+H15+I15 -> 103 | K15: =J15*$K$4 -> 3.09 | L15: =(J15+K15)*C15 -> 0 | M15: =(J15+K15)*$M$4/(1-$M$4) -> 40.039477 | N15: =M15+J15+K15 -> 146.12948 | O15: =N15*C15 -> 0
D17: Total FOB | E17: =SUM(E6:E15) -> 0 | J17: Costo Nac. | L17: =SUM(L6:L15) -> 0 | N17: Total Venta | O17: =SUM(O6:O15) -> 0
N18: UTILIDAD | O18: =O17-L17 -> 0
A20: IMPORTADO
A21: si
A22: no | E22: =E17/3 -> 0
A30: Salario mensual Ing GV | B30: x hora | C30: X DÍA
A31: =E45 -> 2130 | B31: =A31/240 -> 8.875 | C31: =B31*8 -> 71
A32: Salario Mensual Técnico GV
A33: =D45 -> 1420 | B33: =A33/240 -> 5.9166667 | C33: =B33*8 -> 47.333333
A35: Costo x hora Técnico | B35: =B33 -> 5.9166667
A36: Costo x hora Ingeniero | B36: =B31 -> 8.875
C38: =1420/240 -> 5.9166667
D39: Técmico GV | E39: Ing GV
C40: Salario Bruto | D40: 1000 | E40: 1500
C41: CCSS 26,50% | D41: =D40*0.265 -> 265 | E41: =E40*0.265 -> 397.5
C42: Aguinaldo 8,33% | D42: =D40*8.33% -> 83.3 | E42: =E40*8.33% -> 124.95
C43: Vacaciones 4,17% | D43: =D40*4.17% -> 41.7 | E43: =E40*4.17% -> 62.55
C44: Poliza 3% | D44: =D40*3% -> 30 | E44: =E40*3% -> 45
C45: Total | D45: =SUM(D40:D44) -> 1420 | E45: =SUM(E40:E44) -> 2130

Sheet MANO DE OBRA 
B2: MANO DE OBRA PROYECTO | M2: Referencia Cálculo Anterior
B3: Colaborador | C3: Mano de Obra | H3: Viáticos | M3: Mano de Obra | N3: 237600
C4: Hora Hombre | D4: Precio por Día | E4: Días | F4: Personas | G4: Total | H4: Alimentación | I4: Combustible | J4: Hospedaje | K4: Total | M4: Viáticos | N4: 0
B5: Configurador (Implementación) | C5: 8.9 | D5: 48 | E5: 0 | F5: 0 | G5: =E5*D5*F5 -> 0 | H5: 12 | I5: =+Transporte!I3 -> 21.6 | J5: 0 | K5: =(H5*E5*F5) + (I5*E5)+(J5*E5) -> 0 | M5: Total | N5: =SUM(N3:N4) -> 237600
B6: Supervisor (Coordinador de Implementación) | C6: 0 | D6: =C6*8 -> 0 | E6: 0 | F6: 0 | G6: =E6*D6*F6 -> 0 | H6: 0 | I6: 0 | J6: 0 | K6: =(H6*E6*F6)+(I6*E6)+(J6*E6) -> 0 | M6: Diferencia | N6: =N5-(G10+K10) -> 237600
B7: Project Manager | C7: 0 | D7: =C7*8 -> 0 | E7: 0 | F7: 0 | G7: =E7*D7*F7 -> 0 | H7: 0 | I7: 0 | J7: 0 | K7: =(H7*E7*F7)+(I7*E7)+(J7*E7) -> 0
B8: Diseño (Ingeniero de Diseño) | C8: 0 | D8: =C8*8 -> 0 | E8: 0 | F8: 0 | G8: =E8*D8*F8 -> 0 | H8: 0 | I8: 0 | J8: 0 | K8: =(H8*E8*F8)+(I8*E8)+(J8*E8) -> 0 | M8: OJO: el hospedaje (col. J) se multiplica solo por dias, no por personas. Si dos tecnicos duermen fuera se esta cobrando una sola habitacion. Pendiente de confirmar con preventa.
G9: =SUM(G5:G8) -> 0 | K9: =SUM(K5:K8) -> 0
M10: TARIFAS DE REFERENCIA (medidas sobre 649 cotizaciones reales, 2025-2026)
B11: Actividad | C11: Días | D11: Semanas | M11: Hora hombre ,90 - se uso en el 99% de las cotizaciones
B12: Tiempo de Planificación de Proyecto (GV) | C12: 0 | D12: =C12/5 -> 0 | M12: Precio por dia - confirmado por preventa
B13: Tiempo de Configuracion (Planta telefonica) | C13: 0 | D13: =C13/5 -> 0 | M13: Alimentacion por dia y persona - el 88% de los casos
B14: Tiempo de Configuración de Sistema (GV) | C14: 0 | D14: =C14/5 -> 0 | M14: Costo por kilometro ,60 - el 99% de los casos (va en la pestana Transporte)
B15: Tiempo de Cierre de Proyecto (GV) | C15: 0 | D15: =C15/5 -> 0 | M15: Hospedaje: se deja en CERO. Solo el 12% de las cotizaciones lo cobra, porque la mayoria de los trabajos no requieren quedarse.
B16: Tiempo Total del Proyecto | C16: =SUM(C12:C15) -> 0 | D16: =SUM(D12:D15) -> 0 | M16: Cuando SI aplica, la tarifa mas usada es por noche (37 de 58 casos). Se escribe a mano en la columna J.
M17: Todos estos son valores por defecto, no fijos: se cambian aca mismo si el proyecto lo amerita.
B18: MO | M18: Referencia Cálculo Anterior
B19: Colaborador | C19: Mano de Obra | H19: Viáticos | M19: Mano de Obra | N19: 79200
C20: Hora Hombre | D20: Precio por Día | E20: Días | F20: Personas | G20: Total | H20: Alimentación | I20: Combustible | J20: Hospedaje | K20: Total | M20: Viáticos | N20: 157500
B21: Configurador (Implementación) | C21: 0 | D21: =C21*8 -> 0 | E21: 0 | F21: 0 | G21: =E21*D21*F21 -> 0 | H21: 0 | I21: 0 | J21: 0 | K21: =(H21*F21*E21)+(I21*E21)+(J21*(E21-1))*F21 -> 0 | M21: Total | N21: =SUM(N19:N20) -> 236700
B22: Supervisor (Coordinador de Implementación) | C22: 0 | D22: =C22*8 -> 0 | E22: 0 | F22: 0 | G22: =E22*D22*F22 -> 0 | H22: 0 | I22: 0 | J22: 0 | K22: =(H22*F22*E22)+(I22*E22)+(J22*(E22-1))*F22 -> 0 | M22: Diferencia | N22: =N21-(G26+K26) -> 236700
B23: Project Manager | C23: 0 | D23: =C23*8 -> 0 | E23: 0 | F23: 0 | G23: =E23*D23*F23 -> 0 | H23: 0 | I23: 0 | J23: 0 | K23: =(H23*F23*E23)+(I23*E23)+(J23*(E23-1))*F23 -> 0
B24: Diseño (Ingeniero de Diseño) | C24: 0 | D24: =C24*8 -> 0 | E24: 0 | F24: 0 | G24: =E24*D24*F24 -> 0 | H24: 0 | I24: 0 | J24: 0 | M24: Diferencia Neta | N24: =N22+N6 -> 474300
G25: =SUM(G21:G24) -> 0 | K25: =SUM(K21:K24) -> 0
B27: Actividad | C27: Días | D27: Semanas
B28: Tiempo de Planificación de Proyecto (GV) | C28: 0 | D28: =C28/5 -> 0
B29: Tiempo de Configuracion (Planta telefonica) | C29: 0 | D29: =C29/5 -> 0
B30: Tiempo de Configuración de Sistema (GV) | C30: 0 | D30: =C30/5 -> 0
B31: Tiempo de Cierre de Proyecto (GV) | C31: 0 | D31: =C31/5 -> 0
B32: Tiempo Total del Proyecto | C32: =SUM(C28:C31) -> 0 | D32: =SUM(D28:D31) -> 0
B34: MO | M34: Referencia Cálculo Anterior
B35: Colaborador | C35: Mano de Obra | H35: Viáticos | M35: Mano de Obra | N35: 237600
C36: Hora Hombre | D36: Precio por Día | E36: Días | F36: Personas | G36: Total | H36: Alimentación | I36: Combustible | J36: Hospedaje | K36: Traslado | L36: Total | M36: Viáticos | N36: 0
B37: Configurador (Implementación) | C37: 0 | D37: =C37*8 -> 0 | E37: 0 | F37: 0 | G37: =E37*D37*F37 -> 0 | H37: 0 | I37: 0 | J37: 0 | K37: 0 | L37: =(H37*F37*E37)+(I37*E37)+(J37*(E37-1))*F37+K37*2*F37 -> 0 | M37: Total | N37: =SUM(N35:N36) -> 237600
B38: Supervisor (Coordinador de Implementación) | C38: 0 | D38: =C38*8 -> 0 | E38: 0 | F38: 0 | G38: =E38*D38*F38 -> 0 | H38: 0 | I38: 0 | J38: 0 | K38: 0 | L38: =(H38*F38*E38)+(I38*E38)+(J38*(E38-1))*F38+K38*2*F38 -> 0 | M38: Diferencia | N38: =N37-(G42+L42) -> 237600
B39: Project Manager | C39: 0 | D39: =C39*8 -> 0 | E39: 0 | F39: 0 | G39: =E39*D39*F39 -> 0 | H39: 0 | I39: 0 | J39: 0 | K39: 0 | L39: =(H39*F39*E39)+(I39*E39)+(J39*(E39-1))*F39+K39*2*F39 -> 0
B40: Diseño (Ingeniero de Diseño) | C40: 0 | D40: =C40*8 -> 0 | E40: 0 | F40: 0 | G40: =E40*D40*F40 -> 0 | H40: 0 | I40: 0 | J40: 0 | K40: 0
G41: =SUM(G37:G40) -> 0 | L41: =SUM(L37:L40) -> 0
B43: Actividad | C43: Días | D43: Semanas
B44: Tiempo de Planificación de Proyecto (GV) | C44: 0 | D44: =C44/5 -> 0
B45: Tiempo de Configuracion (Planta telefonica) | C45: 0 | D45: =C45/5 -> 0
B46: Tiempo de Configuración de Sistema (GV) | C46: 0 | D46: =C46/5 -> 0
B47: Tiempo de Cierre de Proyecto (GV) | C47: 0 | D47: =C47/5 -> 0
B48: Tiempo Total del Proyecto | C48: =SUM(C44:C47) -> 0 | D48: =SUM(D44:D47) -> 0
B50: MO | M50: Referencia Cálculo Anterior
B51: Colaborador | C51: Mano de Obra | H51: Viáticos | M51: Mano de Obra | N51: 79200
C52: Hora Hombre | D52: Precio por Día | E52: Días | F52: Personas | G52: Total | H52: Alimentación | I52: Combustible | J52: Hospedaje | K52: Total | M52: Viáticos | N52: 157500
B53: Configurador (Implementación) | C53: 0 | D53: =C53*8 -> 0 | E53: 0 | F53: 0 | G53: =E53*D53*F53 -> 0 | H53: 0 | I53: 0 | J53: 0 | K53: =(H53*F53*E53)+(I53*E53)+(J53*(E53-1))*F53 -> 0 | M53: Total | N53: =SUM(N51:N52) -> 236700
B54: Supervisor (Coordinador de Implementación) | C54: 0 | D54: =C54*8 -> 0 | E54: 0 | F54: 0 | G54: =E54*D54*F54 -> 0 | H54: 0 | I54: 0 | J54: 0 | K54: =(H54*F54*E54)+(I54*E54)+(J54*(E54-1))*F54 -> 0 | M54: Diferencia | N54: =N53-(G58+K58) -> 236700
B55: Project Manager | C55: 0 | D55: =C55*8 -> 0 | E55: 0 | F55: 0 | G55: =E55*D55*F55 -> 0 | H55: 0 | I55: 0 | J55: 0 | K55: =(H55*F55*E55)+(I55*E55)+(J55*(E55-1))*F55 -> 0
B56: Diseño (Ingeniero de Diseño) | C56: 0 | D56: =C56*8 -> 0 | E56: 0 | F56: 0 | G56: =E56*D56*F56 -> 0 | H56: 0 | I56: 0 | J56: 0 | M56: Diferencia Neta | N56: =N54+N38 -> 474300
G57: =SUM(G53:G56) -> 0 | K57: =SUM(K53:K56) -> 0
B59: Actividad | C59: Días | D59: Semanas
B60: Tiempo de Planificación de Proyecto (GV) | C60: 0 | D60: =C60/5 -> 0
B61: Tiempo de Configuracion (Planta telefonica) | C61: 0 | D61: =C61/5 -> 0
B62: Tiempo de Configuración de Sistema (GV) | C62: 0 | D62: =C62/5 -> 0
B63: Tiempo de Cierre de Proyecto (GV) | C63: 0 | D63: =C63/5 -> 0
B64: Tiempo Total del Proyecto | C64: 0 | D64: =SUM(D60:D63) -> 0
B69: INSUMOS BIOSEGURIDAD/ POR PERSONA
B70: Equipo Bioseguridad | C70: Cantidad | D70: Precio Unitario | E70: Sub Total
B71: bata quirúrgica | C71: 0 | D71: 0 | E71: =D71*C71 -> 0
B72: Mascarilla | C72: 0 | D72: 0 | E72: =D72*C72 -> 0
B73: guantes latex par | C73: 0 | D73: 0 | E73: =D73*C73 -> 0
B74: Gorros (cofia) | C74: 0 | D74: 0 | E74: =D74*C74 -> 0
B75: Careta o Google | C75: 0 | D75: 0 | E75: =D75*C75 -> 0
B76: Gel de mano 500 ml | C76: 0 | D76: 0 | E76: =D76*C76 -> 0
B77: Franela | C77: 0 | D77: 0 | E77: =D77*C77 -> 0
D79: Total | E79: =SUM(E71:E77) -> 0 | F79: =E79/25 -> 0
B81: INSUMOS VARIOS/ POR MANTO 20 CAMARAS
B82: consumibles | C82: Cantidad | D82: Precio Unitario | E82: Sub Total
B83: Espumas | C83: 0 | D83: 0 | E83: =D83*C83 -> 0
B84: Limpia contactos | C84: 0 | D84: 0 | E84: =D84*C84 -> 0
B85: Wipes | C85: 0 | D85: 0 | E85: =D85*C85 -> 0
B86: Franelas | C86: 0 | D86: 0 | E86: =D86*C86 -> 0
B87: Remplazo de Cableado | C87: 0 | D87: 0 | E87: =D87*C87 -> 0
D89: Total | E89: =SUM(E83:E87) -> 0 | F89: =E89/25 -> 0
B91: MANO DE OBRA MANTENIMENTO TONCONTIN
B92: Colaborador | C92: Mano de Obra | H92: Viáticos
C93: Hora Hombre | D93: Precio por Día | E93: Días | F93: Personas | G93: Total | H93: Alimentación | I93: Combustible | J93: Hospedaje | K93: Total
B94: Configurador (Implementación) | C94: 0 | D94: =C94*8 -> 0 | E94: 0 | F94: 0 | G94: =E94*D94*F94 -> 0 | H94: 0 | I94: 0 | J94: 0
B95: Supervisor (Coordinador de Implementación) | C95: 0 | D95: =C95*8 -> 0 | E95: 0 | F95: 0 | G95: =E95*D95*F95 -> 0 | H95: 0 | I95: 0 | J95: 0
B96: Project Manager | C96: 0 | D96: =C96*8 -> 0 | E96: 0 | F96: 0 | G96: =E96*D96*F96 -> 0 | H96: 0 | I96: 0 | J96: 0
B97: Diseño (Ingeniero de Diseño) | C97: 0 | D97: =C97*8 -> 0 | E97: 0 | F97: 0 | G97: =E97*D97*F97 -> 0 | H97: 0 | I97: 0 | J97: 0
G98: =SUM(G94:G97) -> 0 | K98: =SUM(K94:K97) -> 0
G99: =G98*25 -> 0 | K99: =K98*25 -> 0
B100: Actividad | C100: Días | D100: Semanas
B101: Tiempo de Planificación de Proyecto (GV) | C101: 0 | D101: =C101/5 -> 0
C102: 0 | D102: =C102/5 -> 0
B103: Tiempo de Configuración de Sistema (GV) | C103: 0 | D103: =C103/5 -> 0
B104: Tiempo de Cierre de Proyecto (GV) | C104: 0 | D104: =C104/5 -> 0
B105: Tiempo Total del Proyecto | C105: 0 | D105: =SUM(D101:D104) -> 0
B107: MANO MANTENIMENTO DE LA CEIBA
B108: Colaborador | C108: Mano de Obra | H108: Viáticos
C109: Hora Hombre | D109: Precio por Día | E109: Días | F109: Personas | G109: Total | H109: Alimentación | I109: Combustible | J109: Hospedaje | K109: Total
B110: Configurador (Implementación) | C110: 0 | D110: =C110*8 -> 0 | E110: 0 | F110: 0 | G110: =E110*D110*F110 -> 0 | H110: 0 | I110: 0 | J110: 0 | K110: =(H110*F110*E110)+(I110*E110)+(J110*(E110-1))*F110 -> 0
B111: Supervisor (Coordinador de Implementación) | C111: 0 | D111: =C111*8 -> 0 | E111: 0 | F111: 0 | G111: =E111*D111*F111 -> 0 | H111: 0 | I111: 0 | J111: 0 | K111: =(H111*F111*E111)+(I111*E111)+(J111*(E111-1))*F111 -> 0
B112: Project Manager | C112: 0 | D112: =C112*8 -> 0 | E112: 0 | F112: 0 | G112: =E112*D112*F112 -> 0 | H112: 0 | I112: 0 | J112: 0 | K112: =(H112*F112*E112)+(I112*E112)+(J112*(E112-1))*F112 -> 0
B113: Diseño (Ingeniero de Diseño) | C113: 0 | D113: =C113*8 -> 0 | E113: 0 | F113: 0 | G113: =E113*D113*F113 -> 0 | H113: 0 | I113: 0 | J113: 0
G114: =SUM(G110:G113) -> 0 | K114: =SUM(K110:K113) -> 0
G115: =G114*25 -> 0 | K115: =K114*25 -> 0
...

Sheet Transporte
L1: Destino / localidad | M1: KM ida y vuelta
C2: transporte | D2: can carros | E2: kms por viaje | F2: cant viajes | G2: total de kms | H2: costo por km | I2: total | L2: jaco | M2: 100
C3: 225 | D3: 1 | E3: 36 | F3: 1 | G3: =+F3*E3*D3 -> 36 | H3: 0.6 | I3: =+H3*G3 -> 21.6 | L3: AFZ | M3: 30
C4: =+C3/2 -> 112.5 | L4: Zona Franca Coyol | M4: 40
L5: Limón | M5: 360
L6: Global Park - Ultra Park | M6: 35
B7: real | L7: Florida Bebidas | M7: 35
B8: saldo | L8: Planta Cristal | M8: 35
L9: Planta Pepsi | M9: 30
L10: Fórum2 | M10: 10
L11: Puntarenas | M11: 170
L12: Nicoya | M12: 400
L13: San Ramon | M13: 100
L14: Guapiles | M14: 164
L15: Turrialba | M15: 210
L16: San Jose | M16: 36
L17: San Pedro | M17: 46
L18: Liberia | M18: 420
L19: Pérez Zeledón | M19: 350
L20: Paso Canoas | M20: 700
... L22: Cartago | M22: 85
L24: Solo la DISTANCIA sale de esta tabla.
L25: Cuantos viajes y cuantos carros lleva el proyecto se preguntan al cotizar.

Sheet OPEX Proyecto
A1: MATRIZ DE COSTO PROYECTO: | E1: =+Equipos!E1 -> 0
A3: OPEX | F3: Transporte | G3: Seguros | H3: IVA | I3: DAI | J3: Costo Untit | K3: Administración | L3: Costo total | M3: Margen GV | N3: Precio Venta | O3: Precio Venta
A4: Description | C4: Qty | D4: Costo Unit | E4: Costo Total | F4: 0.1 | G4: 0 | H4: 0.13 | I4: 0.14 | J4: Nacionalizado | K4: 0.03 | L4: Nacionaliado | M4: 0.3 | N4: Unitario | O4: Total
A5: Sección 1 | B5: IMPORTADO
B6: si | C6: 0 | D6: 0 | E6: =+D6*C6 -> 0 | F6: =IF(B6="si",D6*$F$4,0) -> 0 | G6: =(D6+F6)*$G$4 -> 0 | H6: =(D6+F6+G6)*$H$4 -> 0 | I6: =IF(B6="si",(D6+F6+G6+H6)*$I$4,0) -> 0 | J6: =D6+F6+G6+H6+I6 -> 0 | K6: =J6*$K$4 -> 0 | L6: =(J6+K6)*C6 -> 0 | M6: =(J6+K6)*$M$4/(1-$M$4) -> 0 | N6: =M6+J6+K6 -> 0 | O6: =N6*C6 -> 0
B7: si | C7: 0 | D7: 0 | E7: =+D7*C7 -> 0 | F7: =IF(B7="si",D7*$F$4,0) -> 0 | G7: =(D7+F7)*$G$4 -> 0 | H7: =(D7+F7+G7)*$H$4 -> 0 | I7: =IF(B7="si",(D7+F7+G7+H7)*$I$4,0) -> 0 | J7: =D7+F7+G7+H7+I7 -> 0 | K7: =J7*$K$4 -> 0 | L7: =(J7+K7)*C7 -> 0 | M7: =(J7+K7)*$M$4/(1-$M$4) -> 0 | N7: =M7+J7+K7 -> 0 | O7: =N7*C7 -> 0
B8: si | C8: 0 | D8: 0 | E8: =+D8*C8 -> 0 | F8: =IF(B8="si",D8*$F$4,0) -> 0 | G8: =(D8+F8)*$G$4 -> 0 | H8: =(D8+F8+G8)*$H$4 -> 0 | I8: =IF(B8="si",(D8+F8+G8+H8)*$I$4,0) -> 0 | J8: =D8+F8+G8+H8+I8 -> 0 | K8: =J8*$K$4 -> 0 | L8: =(J8+K8)*C8 -> 0 | M8: =(J8+K8)*$M$4/(1-$M$4) -> 0 | N8: =M8+J8+K8 -> 0 | O8: =N8*C8 -> 0
B9: si | C9: 0 | D9: 0 | E9: =+D9*C9 -> 0 | F9: =IF(B9="si",D9*$F$4,0) -> 0 | G9: =(D9+F9)*$G$4 -> 0 | H9: =(D9+F9+G9)*$H$4 -> 0 | I9: =IF(B9="si",(D9+F9+G9+H9)*$I$4,0) -> 0 | J9: =D9+F9+G9+H9+I9 -> 0 | K9: =J9*$K$4 -> 0 | L9: =(J9+K9)*C9 -> 0 | M9: =(J9+K9)*$M$4/(1-$M$4) -> 0 | N9: =M9+J9+K9 -> 0 | O9: =N9*C9 -> 0
B10: si | C10: 0 | D10: 0 | E10: =+D10*C10 -> 0 | F10: =IF(B10="si",D10*$F$4,0) -> 0 | G10: =(D10+F10)*$G$4 -> 0 | H10: =(D10+F10+G10)*$H$4 -> 0 | I10: =IF(B10="si",(D10+F10+G10+H10)*$I$4,0) -> 0 | J10: =D10+F10+G10+H10+I10 -> 0 | K10: =J10*$K$4 -> 0 | L10: =(J10+K10)*C10 -> 0 | M10: =(J10+K10)*$M$4/(1-$M$4) -> 0 | N10: =M10+J10+K10 -> 0 | O10: =N10*C10 -> 0
B11: si | C11: 0 | D11: 0 | E11: =+D11*C11 -> 0 | F11: =IF(B11="si",D11*$F$4,0) -> 0 | G11: =(D11+F11)*$G$4 -> 0 | H11: =(D11+F11+G11)*$H$4 -> 0 | I11: =IF(B11="si",(D11+F11+G11+H11)*$I$4,0) -> 0 | J11: =D11+F11+G11+H11+I11 -> 0 | K11: =J11*$K$4 -> 0 | L11: =(J11+K11)*C11 -> 0 | M11: =(J11+K11)*$M$4/(1-$M$4) -> 0 | N11: =M11+J11+K11 -> 0 | O11: =N11*C11 -> 0
B12: si | C12: 0 | D12: 0 | E12: =+D12*C12 -> 0 | F12: =IF(B12="si",D12*$F$4,0) -> 0 | G12: =(D12+F12)*$G$4 -> 0 | H12: =(D12+F12+G12)*$H$4 -> 0 | I12: =IF(B12="si",(D12+F12+G12+H12)*$I$4,0) -> 0 | J12: =D12+F12+G12+H12+I12 -> 0 | K12: =J12*$K$4 -> 0 | L12: =(J12+K12)*C12 -> 0 | M12: =(J12+K12)*$M$4/(1-$M$4) -> 0 | N12: =M12+J12+K12 -> 0 | O12: =N12*C12 -> 0
B13: si | C13: 0 | D13: 0 | E13: =+D13*C13 -> 0 | F13: =IF(B13="si",D13*$F$4,0) -> 0 | G13: =(D13+F13)*$G$4 -> 0 | H13: =(D13+F13+G13)*$H$4 -> 0 | I13: =IF(B13="si",(D13+F13+G13+H13)*$I$4,0) -> 0 | J13: =D13+F13+G13+H13+I13 -> 0 | K13: =J13*$K$4 -> 0 | L13: =(J13+K13)*C13 -> 0 | M13: =(J13+K13)*$M$4/(1-$M$4) -> 0 | N13: =M13+J13+K13 -> 0 | O13: =N13*C13 -> 0
B14: si | C14: 0 | D14: 0 | E14: =+D14*C14 -> 0 | F14: =IF(B14="si",D14*$F$4,0) -> 0 | G14: =(D14+F14)*$G$4 -> 0 | H14: =(D14+F14+G14)*$H$4 -> 0 | I14: =IF(B14="si",(D14+F14+G14+H14)*$I$4,0) -> 0 | J14: =D14+F14+G14+H14+I14 -> 0 | K14: =J14*$K$4 -> 0 | L14: =(J14+K14)*C14 -> 0 | M14: =(J14+K14)*$M$4/(1-$M$4) -> 0 | N14: =M14+J14+K14 -> 0 | O14: =N14*C14 -> 0
A15: Sección 2
B16: si | C16: 0 | D16: 0 | E16: =+C16*D16*(1-C25) -> 0 | F16: =IF(B16="si",D16*$F$4,0) -> 0 | G16: =(D16+F16)*$G$4 -> 0 | H16: =(D16+F16+G16)*$H$4 -> 0 | I16: =IF(B16="si",(D16+F16+G16+H16)*$I$4,0) -> 0 | J16: =D16+F16+G16+H16+I16 -> 0 | K16: =J16*$K$4 -> 0 | L16: =(J16+K16)*C16 -> 0 | M16: =(J16+K16)*$M$4/(1-$M$4) -> 0 | N16: =M16+J16+K16 -> 0 | O16: =N16*C16 -> 0
B17: si | C17: 0 | D17: 0 | E17: =+C17*D17 -> 0 | F17: =IF(B17="si",D17*$F$4,0) -> 0 | G17: =(D17+F17)*$G$4 -> 0 | H17: =(D17+F17+G17)*$H$4 -> 0 | I17: =IF(B17="si",(D17+F17+G17+H17)*$I$4,0) -> 0 | J17: =D17+F17+G17+H17+I17 -> 0 | K17: =J17*$K$4 -> 0 | L17: =(J17+K17)*C17 -> 0 | M17: =(J17+K17)*$M$4/(1-$M$4) -> 0 | N17: =M17+J17+K17 -> 0 | O17: =N17*C17 -> 0
B18: si | C18: 0 | D18: 0 | E18: =+C18*D18 -> 0 | F18: =IF(B18="si",D18*$F$4,0) -> 0 | G18: =(D18+F18)*$G$4 -> 0 | H18: =(D18+F18+G18)*$H$4 -> 0 | I18: =IF(B18="si",(D18+F18+G18+H18)*$I$4,0) -> 0 | J18: =D18+F18+G18+H18+I18 -> 0 | K18: =J18*$K$4 -> 0 | L18: =(J18+K18)*C18 -> 0 | M18: =(J18+K18)*$M$4/(1-$M$4) -> 0 | N18: =M18+J18+K18 -> 0 | O18: =N18*C18 -> 0
B19: si | C19: 0 | D19: 0 | E19: =+C19*D19 -> 0 | F19: =IF(B19="si",D19*$F$4,0) -> 0 | G19: =(D19+F19)*$G$4 -> 0 | H19: =(D19+F19+G19)*$H$4 -> 0 | I19: =IF(B19="si",(D19+F19+G19+H19)*$I$4,0) -> 0 | J19: =D19+F19+G19+H19+I19 -> 0 | K19: =J19*$K$4 -> 0 | L19: =(J19+K19)*C19 -> 0 | M19: =(J19+K19)*$M$4/(1-$M$4) -> 0 | N19: =M19+J19+K19 -> 0 | O19: =N19*C19 -> 0
B20: si | C20: 0 | D20: 0 | E20: =+C20*D20 -> 0 | F20: =IF(B20="si",D20*$F$4,0) -> 0 | G20: =(D20+F20)*$G$4 -> 0 | H20: =(D20+F20+G20)*$H$4 -> 0 | I20: =IF(B20="si",(D20+F20+G20+H20)*$I$4,0) -> 0 | J20: =D20+F20+G20+H20+I20 -> 0 | K20: =J20*$K$4 -> 0 | L20: =(J20+K20)*C20 -> 0 | M20: =(J20+K20)*$M$4/(1-$M$4) -> 0 | N20: =M20+J20+K20 -> 0 | O20: =N20*C20 -> 0
A21: Sección 3
B22: si | C22: 0 | D22: 0 | E22: =+C22*D22 -> 0 | F22: =IF(B22="si",D22*$F$4,0) -> 0 | G22: =(D22+F22)*$G$4 -> 0 | H22: =(D22+F22+G22)*$H$4 -> 0 | I22: =IF(B22="si",(D22+F22+G22+H22)*$I$4,0) -> 0 | J22: =D22+F22+G22+H22+I22 -> 0 | K22: =J22*$K$4 -> 0 | L22: =(J22+K22)*C22 -> 0 | M22: =(J22+K22)*$M$4/(1-$M$4) -> 0 | N22: =M22+J22+K22 -> 0 | O22: =N22*C22 -> 0
D24: Total FOB | E24: =SUM(E6:E22) -> 0 | J24: Costo Nac. | L24: =SUM(L6:L22) -> 0 | N24: Total Venta | O24: =SUM(O6:O22) -> 0
N25: UTILIDAD | O25: =O24-L24 -> 0
A27: IMPORTADO
A28: si
A29: no

Sheet Datos del proyecto
A1: DATOS DEL PROYECTO
A2: Se llena ANTES de armar la cotizacion. Deja registrado con que reglas y porcentajes se calculo esta oferta.
A4: IDENTIFICACION
A5: Tipo de cotizacion | C5: Estudio de mercado / Oferta de licitacion / Cliente privado | D5: Define los porcentajes recomendados
A6: Cliente
A7: Proyecto / descripcion
A8: Numero de licitacion | C8: Si aplica
A9: Asesor responsable | D9: Va tambien en la firma de la cotizacion
A10: Fecha de armado | B10: =TODAY() -> 46314
A11: Validez de la oferta (dias)
A12: Fecha limite de entrega
A14: REGIMEN FISCAL DEL CLIENTE | D14: Regla R3
A15: Cliente exento de impuesto | C15: si / no | D15: Si no se sabe, PREGUNTAR. Nunca asumir
A16: % impuesto al cliente | C16: ="Se aplica "&ROUND((IF(LOWER(TRIM('Datos del proyecto'!$B$15))="si",0,IF(ISNUMBER('Datos del proyecto'!$B$16),IF('Datos del proyecto'!$B$16>1,'Datos del proyecto'!$B$16/100,'Datos del proyecto'!$B$16),0.13)))*100,2)&"% (vacio = 13%)" -> Se aplica 13% (vacio = 13%) | D16: Va a la fila IMPUESTO de COTIZACION
A17: % administracion aplicado | D17: Hay clientes a los que no se les carga
A19: COSTO Y REGISTRO DE PROYECTO | D19: Reglas R4 y R5
A20: Proyecto registrado | C20: si / no | D20: Sin registro no aplica el descuento mayor
A21: Distribuidor del registro
A22: Marca del registro
A23: Fecha del registro | D23: Vence: confirmar plazo con el distribuidor
A24: Origen del costo unitario | C24: Precio de compra GV del catalogo (dealer) / costo de una cotizacion real / precio de lista, solo si no hay precio de compra | D24: Decir siempre cual se uso
A26: PORCENTAJES USADOS EN ESTA COTIZACION | D26: Se leen solos de cada pestana
A27: Equipos - Transporte | B27: =Equipos!G4 -> 0.1
A28: Equipos - Imprevistos | B28: =Equipos!H4 -> 0.03
A29: Equipos - IVA de linea | B29: =Equipos!I4 -> 0 | D29: Es un COSTO, no el impuesto al cliente
A30: Equipos - DAI | B30: =Equipos!J4 -> 0.15
A31: Equipos - Administracion | B31: =Equipos!L4 -> 0.03
A32: Equipos - Margen GV | B32: =Equipos!N4 -> 0.274 | D32: Cambiarlo mueve tambien OPEX GV
A33: MATERIALES - Margen GV | B33: =MATERIALES!M4 -> 0.3
A35: ALCANCE Y MANO DE OBRA | D35: Regla R8
A36: Alcance | C36: Solo equipo / + accesorios / + materiales / + mano de obra
A37: Ubicacion del proyecto | D37: Para kilometraje y combustible, regla R9
A38: Dias estimados | D38: SIEMPRE se pregunta, no se estima solo
A39: Cantidad de personas | D39: SIEMPRE se pregunta
A41: FINANCIAMIENTO | D41: Regla R13
A42: Lleva financiamiento | C42: si / no | D42: SIEMPRE preguntar, sin importar el tamano
A43: Plazo (anos) | D43: Solo si lleva
A44: Tasa anual | D44: Solo si lleva
A46: TIPO DE CAMBIO | D46: Regla R7
A47: Tipo de cambio usado | D47: Del banco, redondeado hacia arriba
A48: Fuente y fecha

Sheet Guia de pestanas
B1: GUIA DE PESTANAS
B2: Las 14 pestanas de trabajo, en el orden en que aparecen. No se listan las 4 de guia ni las 16 ocultas.
B4: Pestana | C4: Para que sirve | D4: Que se escribe a mano | E4: Que sale solo | F4: Conectada con
B5: RESUMEN | C5: Resumen de costo y venta por componente del proyecto. | D5: Nada. | E5: Costo, % del costo, % de venta, precio de venta y margen de cada componente. | F5: Toma costo y margen de Equipos, Productos 2, MATERIALES, OPEX GV y OPEX Proyecto.
B6: COTIZACION | C6: El documento que ve el cliente. Es la salida, no una entrada. | D6: Nada. Solo se revisa antes de exportar. | E6: Cantidad, descripcion, precio unitario y total de cada linea; SUBTOTAL, IMPUESTO y TOTAL. | F6: Espeja las 50 lineas de Equipos. El impuesto sale de Datos del proyecto.
B7: COTIZACION (Financ) | C7: La misma cotizacion en modalidad financiada: muestra la cuota mensual. | D7: Nada. | E7: Precio unitario mensual por cantidad = total mensual. | F7: Toma la cuota del cuadro de Financiamiento que corresponde al ID de la columna Financ. de Equipos.
B8: Equipos | C8: La pestana principal: el equipo que se vende. 50 lineas, filas 6 a 55. | D8: Description, IMPORTADO, Qty y Costo Unit. Mas el ID en Financ. si esa linea se financia. | E8: Transporte, imprevistos, IVA, DAI, costo nacionalizado, administracion, margen y precio de venta. | F8: Alimenta COTIZACION, RESUMEN y Financiamiento. Su margen (N4) tambien manda sobre OPEX GV.
B9: Productos 2 | C9: Segunda seccion de producto, si el proyecto separa dos bloques de equipo. 10 lineas. | D9: Las mismas cuatro columnas. | E9: Lo mismo que Equipos, con sus propios porcentajes. | F9: Alimenta RESUMEN y Financiamiento.
B10: MATERIALES | C10: Materiales de instalacion: tuberia, cable, cajas, conectores. 39 lineas. | D10: Las mismas cuatro columnas. Las CANTIDADES se preguntan en cada proyecto: no salen de ninguna tabla. | E10: Lo mismo que Equipos, con sus propios porcentajes. | F10: Alimenta RESUMEN y Financiamiento.
B11: Financiamiento | C11: Un cuadro de costos financieros por cada linea que se financie. 50 cuadros para Equipos. | D11: Interes anual y plazo de cada cuadro, si cambian. Anticipos y otros ingresos. | E11: Total a financiar, cuota mensual y anual, total de cuotas y costo financiero. | F11: Trae el precio de venta por ID desde la columna Financ. de cada pestana de producto.
B12: PTMO | C12: Calculadora de amortizacion mes a mes, de uso general. | D12: Importe, tasa, plazo y fecha de inicio. | E12: La tabla completa de pagos, con saldo que termina en cero. | F12: Independiente: no esta conectada a ningun cuadro de Financiamiento.
B13: RESUMEN (OPEX) | C13: El mismo resumen del proyecto, del lado de operacion. | D13: Nada. | E13: Costo, precio de venta y margen por componente. | F13: Toma los costos de las pestanas de producto y de OPEX.
B14: OPEX GV | C14: Costos de operacion de Grupo Vision: configuracion, puesta en marcha, ingenieria. | D14: Las mismas cuatro columnas. El costo unitario de la primera linea lo trae MANO DE OBRA. | E14: Lo mismo que Equipos. | F14: Su margen es la formula =Equipos!N4: cambiar el margen en Equipos lo mueve tambien.
B15: MANO DE OBRA | C15: El detalle de la instalacion: personas, dias, tarifas y viaticos. | D15: Cantidad de personas, dias, tarifas y viaticos. Los dias y las personas se preguntan siempre. | E15: Los totales que despues consume OPEX GV. | F15: Toma el costo del viaje de Transporte y entrega su total a OPEX GV.
... B18: Datos del proyecto | C18: La ficha congelada: quien es el cliente, que regimen fiscal tiene y con que porcentajes se armo esta oferta. | D18: Cliente, tipo de cotizacion, exencion, % de impuesto, registro de proyecto, alcance, financiamiento y tipo de cambio. | E18: La fecha, los porcentajes (se espejan de Equipos y MATERIALES) y la tasa de impuesto que se esta aplicando. | F18: El % de impuesto de esta ficha es el que usa la fila IMPUESTO de las dos cotizaciones.

Sheet Guia de formulas
B1: GUIA DE FORMULAS
B2: Las formulas que deciden la plata, explicadas en palabras. Ninguna se escribe a mano: todas vienen en el machote.
B4: Donde | C4: La formula tal cual esta | D4: Que significa
B5: EQUIPOS - de costo de compra a precio de venta, linea por linea
B6: F6 Costo Total | C6: =E6*D6 | D6: Costo unitario por cantidad. Es el FOB, antes de cualquier gasto.
B7: G6 Transporte | C7: =IF(C6="si", E6*$G$4, 0) | D7: Solo se cobra si la linea es IMPORTADO = si. Si es compra local, da cero.
B8: H6 Imprevistos | C8: =(E6+G6)*$H$4 | D8: Un colchon sobre el costo mas el transporte. Se aplica siempre.
B9: I6 IVA de linea | C9: =(E6+G6+H6)*$I$4 | D9: El IVA que el PROVEEDOR nos cobra a nosotros. Es un costo, no es el impuesto del cliente.
B10: OJO | C10: A diferencia del transporte y del DAI, esta formula NO mira la columna IMPORTADO. El porcentaje sale de la fila 4 de la pestana y se aplica a las 50 lineas por igual: en Equipos es 0% y en MATERIALES es 13%. O sea que el IVA lo decide EN QUE PESTANA escribiste la linea, no el producto.
B11: J6 DAI | C11: =IF(C6="si", (E6+G6+H6+I6)*$J$4, 0) | D11: El impuesto de aduanas. Igual que el transporte: solo si es importado.
B12: K6 Costo Nacionalizado | C12: =E6+G6+H6+I6+J6 | D12: Lo que de verdad cuesta poner una unidad en Costa Rica. Es la base de todo lo que sigue.
B13: L6 Administracion | C13: =K6*$L$4 | D13: Gasto administrativo sobre el costo nacionalizado.
B14: N6 Margen GV | C14: =(K6+L6)*$N$4/(1-$N$4) | D14: El margen esta en 27,40 %, y eso quiere decir 27,40 % del PRECIO DE VENTA, no del costo. Sobre el costo equivale a 37,74 %.
B15: OJO | C15: Por eso divide entre (1 - margen) en vez de multiplicar directo: es la unica forma de que el porcentaje se cumpla sobre el precio final. Multiplicando nada mas, el margen real quedaria por debajo del que dice la celda.
B16: O6 Precio Venta unitario | C16: =N6+K6+L6 | D16: Costo nacionalizado mas administracion mas utilidad. Es lo que ve el cliente por unidad.
B17: P6 Precio Venta total | C17: =O6*D6 | D17: Precio unitario por cantidad.
B18: P57 Total Venta | C18: =SUM(P6:P55) | D18: La suma de las 50 lineas. Es lo que alimenta el SUBTOTAL de la cotizacion.
B19: COTIZACION - lo que ve el cliente. No se escribe, se espeja
B20: B22 Cantidad | C20: =Equipos!D6 | D20: Copia la cantidad de la linea 1 de Equipos. Las 50 lineas se espejan igual, filas 22 a 71.
B21: C22 Descripcion | C21: =Equipos!B6 | D21: Copia la descripcion tal cual se escribio en Equipos.
B22: I22 Precio U. | C22: =Equipos!O6 | D22: Copia el precio de venta unitario ya calculado.
B23: J22 Total | C23: =I22*B22 | D23: Precio unitario por cantidad.
B24: J74 SUBTOTAL | C24: =SUM(J21:J73) | D24: Suma de todas las lineas, ANTES del impuesto al cliente. Es el monto que se anota en el control de cotizaciones.
B25: J75 IMPUESTO | C25: =J74*IF(LOWER(TRIM('Datos del proyecto'!$B$15))="si",0, IF(ISNUMBER('Datos del proyecto'!$B$16), IF('Datos del proyecto'!$B$16>1, 'Datos del proyecto'!$B$16/100, 'Datos del proyecto'!$B$16), 0.13)) | D25: El impuesto que paga el cliente, leido de la ficha Datos del proyecto: si B15 dice si (cliente exento) da cero; si no, usa el porcentaje de B16; si B16 esta vacio usa 13%. Si escribis 13 en vez de 13%, lo toma como 13% igual.
B26: J76 TOTAL | C26: =ROUNDDOWN(J74+J75, 2) | D26: Subtotal mas impuesto, truncado a dos decimales. No redondea hacia arriba: corta.
B27: FINANCIAMIENTO - un cuadro por cada linea que se financie
B28: C4 Total Venta Proyecto | C28: =SUMIF(Equipos!$Q$6:$Q$55, A3, Equipos!$O$6:$O$55) | D28: Busca en la columna Financ. de Equipos el ID de este cuadro y trae el precio de venta UNITARIO de esa linea. Si ningun ID coincide da cero, y el cuadro simplemente no aplica.
B29: OJO | C29: Por eso cada linea financiada lleva un ID distinto: si dos lineas comparten el mismo numero, el SUMIF suma dos precios unitarios y el resultado no significa nada.
B30: C8 Total a Financiar | C30: =C4-C5-C6 | D30: El monto a financiar, menos anticipos y otros ingresos.
B31: C12 Cuota mensual | C31: formula de anualidad estandar | D31: La cuota que paga el cliente cada mes, segun el interes anual y el plazo de ese cuadro.
B32: Cuadro n | C32: fila 3 + (n-1) * 17 | D32: Los cuadros de Equipos van en la columna A/B: el cuadro 1 arranca en la fila 3 y el cuadro 50 en la 836.
B33: COTIZACION (Financ) - la version con cuota mensual
B34: I22 Precio Unit. Mensual | C34: =IFERROR(IF(Equipos!Q6="","", INDEX(Financiamiento!$C:$C, 12+(Equipos!Q6-1)*17)), "") | D34: Busca el cuadro que corresponde al ID de esa linea y trae su cuota mensual. Si la linea no tiene ID, queda vacia.
B35: J22 Total Mensual | C35: =IFERROR(I22*B22, "") | D35: Cuota unitaria por cantidad. El IFERROR esta porque multiplicar vacio por un numero da error.
B36: RESUMEN - costo y margen por componente
B37: F4 P. Venta | C37: =[@Costo]/(1-[@[% de venta]]) | D37: La misma logica de margen sobre precio de venta, aplicada al componente completo.
B38: E4 % de venta | C38: =Equipos!N4 | D38: El porcentaje de cada fila viene de la pestana que le corresponde.
B39: OPEX GV, MANO DE OBRA y Transporte - la cadena que sorprende
B40: OPEX GV M4 | C40: =Equipos!N4 | D40: El margen de OPEX GV NO es independiente: es el mismo de Equipos. Cambiarlo alla lo mueve aca, sin aviso. MATERIALES y OPEX Proyecto si tienen el suyo propio.
B41: OPEX GV D6 | C41: ='MANO DE OBRA '!G9+'MANO DE OBRA '!K9 | D41: El costo de la primera linea de OPEX GV lo trae la pestana MANO DE OBRA.
B42: MANO DE OBRA I5 | C42: =Transporte!I3 | D42: Y MANO DE OBRA, a su vez, toma el costo del viaje de la pestana Transporte.
B43: Transporte G3 | C43: =F3*E3*D3 | D43: Total de kilometros = cantidad de viajes por kilometros por viaje por cantidad de carros.
B44: Transporte I3 | C44: =H3*G3 | D44: Costo total = costo por kilometro por el total de kilometros.
B45: OJO | C45: De la tabla de destinos sale UNICAMENTE la distancia. Cuantos viajes y cuantos carros lleva el proyecto se preguntan al cotizar: eso depende del sitio y no de una tabla.
